Workbook
Name OPEN_WL_IDs: '[1]Work list'!$Q$2:INDEX('[1]Work list'!$Q:$Q,MAX(2,COUNTIF('[1]Work list'!$Q:$Q,"WL-*")+1))
Name OPEN_WL_IDs: 'Work list'!$Q$2:INDEX('Work list'!$Q:$Q,MAX(2,COUNTIF('Work list'!$Q:$Q,"WL-*")+1))
Name U2U1500: 'Work report'!$U$2
Name WL_IDs: '[1]Work list'!$B$2:INDEX('[1]Work list'!$B:$B,MAX(2,COUNTIF('[1]Work list'!$B:$B,"WL-*")+1))
Name WL_IDs: 'Work list'!$B$2:INDEX('Work list'!$B:$B,MAX(2,COUNTIF('Work list'!$B:$B,"WL-*")+1))

Sheet Setup
B1: SETUP – Quản lý điền 1 lần trước khi gửi nhân viên
AA2: A – Valuable (New/Improvement)
A3: EmployeeID | B3: 15 | AA3: B – Normal (Clarification)
A4: Employee name | B4: Đỗ Lan | AA4: C – Low value (Already documented / not followed process)
A5: Department | B5: Dev & Team Lead
A6: Company | B6: Hung IT/GM
A7: Email (Company) | B7: lanit@hung-it-solutions.com
A8: Email (Google) | B8: lanit@hung-it-solutions.com
A9: Email (private)
A10: Mobil (Company)
A11: Mobil (private)
A12: Address
A13: Pay type | B13: have to choose (Summary)
A14: Hourly rate (/h) | B14: 10
A15: Monthly salary
A16: Max hours/month | B16: 160
A17: Entry date
A18: Holidays/Year
A19: Working days
A20: Exit date
A21: Hardware/PC ID
A22: Bank Name
A23: IBAN/Account Number
A24: BIC/Swift Code
A32: Drive-link-1 | B32: https://drive.google.com/drive/folders/1gtU3qlcFI3aMBTz2z80ioSKTDObCLAxx?usp=drive_link | C32: Task-Video-11 | D32: Mitarbeiter
A33: Drive-link-2 | B33: https://drive.google.com/drive/folders/1mFbEs13a5YOUaSOAh2gZI0RXJ38N9y98?usp=drive_link | C33: SD-04 | D33: Mitarbeiter
A34: Drive-link-3 | B34: Drive-link-3
A35: Drive-link-4 | B35: Drive-link-4

Sheet Link
A1: No | B1: Go to
A2: 1 | B2: Work list
A3: =A2+1 -> 2 | B3: Work report
A4: =A3+1 -> 3 | B4: Office time approval
A5: =A4+1 -> 4 | B5: Task Library
A6: =A5+1 -> 5 | B6: Missing tasks auto
A7: =A6+1 -> 6 | B7: Missing Tasks
A8: =A7+1 -> 7 | B8: Time check for tasks
A9: =A8+1 -> 8 | B9: Summary
A10: =A9+1 -> 9 | B10: Payments
A11: =A10+1 -> 10 | B11: Vacation, holiday, illness
A12: =A11+1 -> 11 | B12: Customers
A13: =A12+1 -> 12 | B13: Messages
A14: =A13+1 -> 13 | B14: Password
... A19: =A18+1 -> 18 | B19: Work rules

Sheet Work list
A1: Date assigned | B1: WL ID | C1: Title | D1: Description | E1: Customer | F1: Priority | G1: Due date | H1: Status | I1: Progress % | J1: Last update | K1: Reason / next action | L1: Total actual time (min) | M1: Completed date | N1: Overdue | O1: WL serial (hidden) | P1: Open rank (hidden) | Q1: Open WL IDs (hidden)
B2: =IF(OR($A2<>"",$C2<>"",$D2<>"",$E2<>"",$F2<>"",$G2<>""),"WL-"&TEXT($O2,"0000"),"") | H2: =IF($B2="","",IF(N($I2)>=100,"Completed",IF(COUNTIF('Work report'!$V$2:$V$1500,$B2)=0,"Not started",IF(OR(LEFT(UPPER(TRIM($K2)),8)="BLOCKED:",LEFT(UPPER(TRIM($K2)),8)="WAITING:"),"Blocked",IF(N($I2)>0,"In progress","Not started"))))) | I2: {=IF($B2="","",IFERROR(LOOKUP(2,1/('Work report'!$V$2:$V$1500=$B2),'Work report'!$J$2:$J$1500)*100,0))} | J2: {=IF($B2="","",IFERROR(LOOKUP(2,1/('Work report'!$V$2:$V$1500=$B2),'Work report'!$A$2:$A$1500),""))} | K2: {=IF($B2="","",IFERROR(LOOKUP(2,1/('Work report'!$V$2:$V$1500=$B2),'Work report'!$P$2:$P$1500),""))} | L2: =IF($B2="","",SUMIFS('Work report'!$G$2:$G$1500,'Work report'!$V$2:$V$1500,$B2)) | M2: =IF($B2="","",IF($H2="Completed",$J2,"")) | N2: =IF(AND($C2<>"",$H2<>"Completed",$G2<>"",$G2<TODAY()),"Overdue","") | O2: 1 | P2: =IF(AND($B2<>"",$H2<>"Completed",$H2<>"Cancelled"),COUNTIFS($B$2:$B2,"<>",$H$2:$H2,"<>Completed",$H$2:$H2,"<>Cancelled"),"") | Q2: =IFERROR(INDEX($B$2:$B$1500,MATCH(ROWS($Q$2:Q2),$P$2:$P$1500,0)),"")
B3: =IF(OR($A3<>"",$C3<>"",$D3<>"",$E3<>"",$F3<>"",$G3<>""),"WL-"&TEXT($O3,"0000"),"") | H3: =IF($B3="","",IF(N($I3)>=100,"Completed",IF(COUNTIF('Work report'!$V$2:$V$1500,$B3)=0,"Not started",IF(OR(LEFT(UPPER(TRIM($K3)),8)="BLOCKED:",LEFT(UPPER(TRIM($K3)),8)="WAITING:"),"Blocked",IF(N($I3)>0,"In progress","Not started"))))) | I3: {=IF($B3="","",IFERROR(LOOKUP(2,1/('Work report'!$V$2:$V$1500=$B3),'Work report'!$J$2:$J$1500)*100,0))} | J3: {=IF($B3="","",IFERROR(LOOKUP(2,1/('Work report'!$V$2:$V$1500=$B3),'Work report'!$A$2:$A$1500),""))} | K3: {=IF($B3="","",IFERROR(LOOKUP(2,1/('Work report'!$V$2:$V$1500=$B3),'Work report'!$P$2:$P$1500),""))} | L3: =IF($B3="","",SUMIFS('Work report'!$G$2:$G$1500,'Work report'!$V$2:$V$1500,$B3)) | M3: =IF($B3="","",IF($H3="Completed",$J3,"")) | N3: =IF(AND($C3<>"",$H3<>"Completed",$G3<>"",$G3<TODAY()),"Overdue","") | O3: 2 | P3: =IF(AND($B3<>"",$H3<>"Completed",$H3<>"Cancelled"),COUNTIFS($B$2:$B3,"<>",$H$2:$H3,"<>Completed",$H$2:$H3,"<>Cancelled"),"") | Q3: =IFERROR(INDEX($B$2:$B$1500,MATCH(ROWS($Q$2:Q3),$P$2:$P$1500,0)),"")
B4: =IF(OR($A4<>"",$C4<>"",$D4<>"",$E4<>"",$F4<>"",$G4<>""),"WL-"&TEXT($O4,"0000"),"") | H4: =IF($B4="","",IF(N($I4)>=100,"Completed",IF(COUNTIF('Work report'!$V$2:$V$1500,$B4)=0,"Not started",IF(OR(LEFT(UPPER(TRIM($K4)),8)="BLOCKED:",LEFT(UPPER(TRIM($K4)),8)="WAITING:"),"Blocked",IF(N($I4)>0,"In progress","Not started"))))) | I4: {=IF($B4="","",IFERROR(LOOKUP(2,1/('Work report'!$V$2:$V$1500=$B4),'Work report'!$J$2:$J$1500)*100,0))} | J4: {=IF($B4="","",IFERROR(LOOKUP(2,1/('Work report'!$V$2:$V$1500=$B4),'Work report'!$A$2:$A$1500),""))} | K4: {=IF($B4="","",IFERROR(LOOKUP(2,1/('Work report'!$V$2:$V$1500=$B4),'Work report'!$P$2:$P$1500),""))} | L4: =IF($B4="","",SUMIFS('Work report'!$G$2:$G$1500,'Work report'!$V$2:$V$1500,$B4)) | M4: =IF($B4="","",IF($H4="Completed",$J4,"")) | N4: =IF(AND($C4<>"",$H4<>"Completed",$G4<>"",$G4<TODAY()),"Overdue","") | O4: 3 | P4: =IF(AND($B4<>"",$H4<>"Completed",$H4<>"Cancelled"),COUNTIFS($B$2:$B4,"<>",$H$2:$H4,"<>Completed",$H$2:$H4,"<>Cancelled"),"") | Q4: =IFERROR(INDEX($B$2:$B$1500,MATCH(ROWS($Q$2:Q4),$P$2:$P$1500,0)),"")
B5: =IF(OR($A5<>"",$C5<>"",$D5<>"",$E5<>"",$F5<>"",$G5<>""),"WL-"&TEXT($O5,"0000"),"") | H5: =IF($B5="","",IF(N($I5)>=100,"Completed",IF(COUNTIF('Work report'!$V$2:$V$1500,$B5)=0,"Not started",IF(OR(LEFT(UPPER(TRIM($K5)),8)="BLOCKED:",LEFT(UPPER(TRIM($K5)),8)="WAITING:"),"Blocked",IF(N($I5)>0,"In progress","Not started"))))) | I5: {=IF($B5="","",IFERROR(LOOKUP(2,1/('Work report'!$V$2:$V$1500=$B5),'Work report'!$J$2:$J$1500)*100,0))} | J5: {=IF($B5="","",IFERROR(LOOKUP(2,1/('Work report'!$V$2:$V$1500=$B5),'Work report'!$A$2:$A$1500),""))} | K5: {=IF($B5="","",IFERROR(LOOKUP(2,1/('Work report'!$V$2:$V$1500=$B5),'Work report'!$P$2:$P$1500),""))} | L5: =IF($B5="","",SUMIFS('Work report'!$G$2:$G$1500,'Work report'!$V$2:$V$1500,$B5)) | M5: =IF($B5="","",IF($H5="Completed",$J5,"")) | N5: =IF(AND($C5<>"",$H5<>"Completed",$G5<>"",$G5<TODAY()),"Overdue","") | O5: 4 | P5: =IF(AND($B5<>"",$H5<>"Completed",$H5<>"Cancelled"),COUNTIFS($B$2:$B5,"<>",$H$2:$H5,"<>Completed",$H$2:$H5,"<>Cancelled"),"") | Q5: =IFERROR(INDEX($B$2:$B$1500,MATCH(ROWS($Q$2:Q5),$P$2:$P$1500,0)),"")
B6: =IF(OR($A6<>"",$C6<>"",$D6<>"",$E6<>"",$F6<>"",$G6<>""),"WL-"&TEXT($O6,"0000"),"") | H6: =IF($B6="","",IF(N($I6)>=100,"Completed",IF(COUNTIF('Work report'!$V$2:$V$1500,$B6)=0,"Not started",IF(OR(LEFT(UPPER(TRIM($K6)),8)="BLOCKED:",LEFT(UPPER(TRIM($K6)),8)="WAITING:"),"Blocked",IF(N($I6)>0,"In progress","Not started"))))) | I6: {=IF($B6="","",IFERROR(LOOKUP(2,1/('Work report'!$V$2:$V$1500=$B6),'Work report'!$J$2:$J$1500)*100,0))} | J6: {=IF($B6="","",IFERROR(LOOKUP(2,1/('Work report'!$V$2:$V$1500=$B6),'Work report'!$A$2:$A$1500),""))} | K6: {=IF($B6="","",IFERROR(LOOKUP(2,1/('Work report'!$V$2:$V$1500=$B6),'Work report'!$P$2:$P$1500),""))} | L6: =IF($B6="","",SUMIFS('Work report'!$G$2:$G$1500,'Work report'!$V$2:$V$1500,$B6)) | M6: =IF($B6="","",IF($H6="Completed",$J6,"")) | N6: =IF(AND($C6<>"",$H6<>"Completed",$G6<>"",$G6<TODAY()),"Overdue","") | O6: 5 | P6: =IF(AND($B6<>"",$H6<>"Completed",$H6<>"Cancelled"),COUNTIFS($B$2:$B6,"<>",$H$2:$H6,"<>Completed",$H$2:$H6,"<>Cancelled"),"") | Q6: =IFERROR(INDEX($B$2:$B$1500,MATCH(ROWS($Q$2:Q6),$P$2:$P$1500,0)),"")
B7: =IF(OR($A7<>"",$C7<>"",$D7<>"",$E7<>"",$F7<>"",$G7<>""),"WL-"&TEXT($O7,"0000"),"") | H7: =IF($B7="","",IF(N($I7)>=100,"Completed",IF(COUNTIF('Work report'!$V$2:$V$1500,$B7)=0,"Not started",IF(OR(LEFT(UPPER(TRIM($K7)),8)="BLOCKED:",LEFT(UPPER(TRIM($K7)),8)="WAITING:"),"Blocked",IF(N($I7)>0,"In progress","Not started"))))) | I7: {=IF($B7="","",IFERROR(LOOKUP(2,1/('Work report'!$V$2:$V$1500=$B7),'Work report'!$J$2:$J$1500)*100,0))} | J7: {=IF($B7="","",IFERROR(LOOKUP(2,1/('Work report'!$V$2:$V$1500=$B7),'Work report'!$A$2:$A$1500),""))} | K7: {=IF($B7="","",IFERROR(LOOKUP(2,1/('Work report'!$V$2:$V$1500=$B7),'Work report'!$P$2:$P$1500),""))} | L7: =IF($B7="","",SUMIFS('Work report'!$G$2:$G$1500,'Work report'!$V$2:$V$1500,$B7)) | M7: =IF($B7="","",IF($H7="Completed",$J7,"")) | N7: =IF(AND($C7<>"",$H7<>"Completed",$G7<>"",$G7<TODAY()),"Overdue","") | O7: 6 | P7: =IF(AND($B7<>"",$H7<>"Completed",$H7<>"Cancelled"),COUNTIFS($B$2:$B7,"<>",$H$2:$H7,"<>Completed",$H$2:$H7,"<>Cancelled"),"") | Q7: =IFERROR(INDEX($B$2:$B$1500,MATCH(ROWS($Q$2:Q7),$P$2:$P$1500,0)),"")
B8: =IF(OR($A8<>"",$C8<>"",$D8<>"",$E8<>"",$F8<>"",$G8<>""),"WL-"&TEXT($O8,"0000"),"") | H8: =IF($B8="","",IF(N($I8)>=100,"Completed",IF(COUNTIF('Work report'!$V$2:$V$1500,$B8)=0,"Not started",IF(OR(LEFT(UPPER(TRIM($K8)),8)="BLOCKED:",LEFT(UPPER(TRIM($K8)),8)="WAITING:"),"Blocked",IF(N($I8)>0,"In progress","Not started"))))) | I8: {=IF($B8="","",IFERROR(LOOKUP(2,1/('Work report'!$V$2:$V$1500=$B8),'Work report'!$J$2:$J$1500)*100,0))} | J8: {=IF($B8="","",IFERROR(LOOKUP(2,1/('Work report'!$V$2:$V$1500=$B8),'Work report'!$A$2:$A$1500),""))} | K8: {=IF($B8="","",IFERROR(LOOKUP(2,1/('Work report'!$V$2:$V$1500=$B8),'Work report'!$P$2:$P$1500),""))} | L8: =IF($B8="","",SUMIFS('Work report'!$G$2:$G$1500,'Work report'!$V$2:$V$1500,$B8)) | M8: =IF($B8="","",IF($H8="Completed",$J8,"")) | N8: =IF(AND($C8<>"",$H8<>"Completed",$G8<>"",$G8<TODAY()),"Overdue","") | O8: 7 | P8: =IF(AND($B8<>"",$H8<>"Completed",$H8<>"Cancelled"),COUNTIFS($B$2:$B8,"<>",$H$2:$H8,"<>Completed",$H$2:$H8,"<>Cancelled"),"") | Q8: =IFERROR(INDEX($B$2:$B$1500,MATCH(ROWS($Q$2:Q8),$P$2:$P$1500,0)),"")
B9: =IF(OR($A9<>"",$C9<>"",$D9<>"",$E9<>"",$F9<>"",$G9<>""),"WL-"&TEXT($O9,"0000"),"") | H9: =IF($B9="","",IF(N($I9)>=100,"Completed",IF(COUNTIF('Work report'!$V$2:$V$1500,$B9)=0,"Not started",IF(OR(LEFT(UPPER(TRIM($K9)),8)="BLOCKED:",LEFT(UPPER(TRIM($K9)),8)="WAITING:"),"Blocked",IF(N($I9)>0,"In progress","Not started"))))) | I9: {=IF($B9="","",IFERROR(LOOKUP(2,1/('Work report'!$V$2:$V$1500=$B9),'Work report'!$J$2:$J$1500)*100,0))} | J9: {=IF($B9="","",IFERROR(LOOKUP(2,1/('Work report'!$V$2:$V$1500=$B9),'Work report'!$A$2:$A$1500),""))} | K9: {=IF($B9="","",IFERROR(LOOKUP(2,1/('Work report'!$V$2:$V$1500=$B9),'Work report'!$P$2:$P$1500),""))} | L9: =IF($B9="","",SUMIFS('Work report'!$G$2:$G$1500,'Work report'!$V$2:$V$1500,$B9)) | M9: =IF($B9="","",IF($H9="Completed",$J9,"")) | N9: =IF(AND($C9<>"",$H9<>"Completed",$G9<>"",$G9<TODAY()),"Overdue","") | O9: 8 | P9: =IF(AND($B9<>"",$H9<>"Completed",$H9<>"Cancelled"),COUNTIFS($B$2:$B9,"<>",$H$2:$H9,"<>Completed",$H$2:$H9,"<>Cancelled"),"") | Q9: =IFERROR(INDEX($B$2:$B$1500,MATCH(ROWS($Q$2:Q9),$P$2:$P$1500,0)),"")
B10: =IF(OR($A10<>"",$C10<>"",$D10<>"",$E10<>"",$F10<>"",$G10<>""),"WL-"&TEXT($O10,"0000"),"") | H10: =IF($B10="","",IF(N($I10)>=100,"Completed",IF(COUNTIF('Work report'!$V$2:$V$1500,$B10)=0,"Not started",IF(OR(LEFT(UPPER(TRIM($K10)),8)="BLOCKED:",LEFT(UPPER(TRIM($K10)),8)="WAITING:"),"Blocked",IF(N($I10)>0,"In progress","Not started"))))) | I10: {=IF($B10="","",IFERROR(LOOKUP(2,1/('Work report'!$V$2:$V$1500=$B10),'Work report'!$J$2:$J$1500)*100,0))} | J10: {=IF($B10="","",IFERROR(LOOKUP(2,1/('Work report'!$V$2:$V$1500=$B10),'Work report'!$A$2:$A$1500),""))} | K10: {=IF($B10="","",IFERROR(LOOKUP(2,1/('Work report'!$V$2:$V$1500=$B10),'Work report'!$P$2:$P$1500),""))} | L10: =IF($B10="","",SUMIFS('Work report'!$G$2:$G$1500,'Work report'!$V$2:$V$1500,$B10)) | M10: =IF($B10="","",IF($H10="Completed",$J10,"")) | N10: =IF(AND($C10<>"",$H10<>"Completed",$G10<>"",$G10<TODAY()),"Overdue","") | O10: 9 | P10: =IF(AND($B10<>"",$H10<>"Completed",$H10<>"Cancelled"),COUNTIFS($B$2:$B10,"<>",$H$2:$H10,"<>Completed",$H$2:$H10,"<>Cancelled"),"") | Q10: =IFERROR(INDEX($B$2:$B$1500,MATCH(ROWS($Q$2:Q10),$P$2:$P$1500,0)),"")
B11: =IF(OR($A11<>"",$C11<>"",$D11<>"",$E11<>"",$F11<>"",$G11<>""),"WL-"&TEXT($O11,"0000"),"") | H11: =IF($B11="","",IF(N($I11)>=100,"Completed",IF(COUNTIF('Work report'!$V$2:$V$1500,$B11)=0,"Not started",IF(OR(LEFT(UPPER(TRIM($K11)),8)="BLOCKED:",LEFT(UPPER(TRIM($K11)),8)="WAITING:"),"Blocked",IF(N($I11)>0,"In progress","Not started"))))) | I11: {=IF($B11="","",IFERROR(LOOKUP(2,1/('Work report'!$V$2:$V$1500=$B11),'Work report'!$J$2:$J$1500)*100,0))} | J11: {=IF($B11="","",IFERROR(LOOKUP(2,1/('Work report'!$V$2:$V$1500=$B11),'Work report'!$A$2:$A$1500),""))} | K11: {=IF($B11="","",IFERROR(LOOKUP(2,1/('Work report'!$V$2:$V$1500=$B11),'Work report'!$P$2:$P$1500),""))} | L11: =IF($B11="","",SUMIFS('Work report'!$G$2:$G$1500,'Work report'!$V$2:$V$1500,$B11)) | M11: =IF($B11="","",IF($H11="Completed",$J11,"")) | N11: =IF(AND($C11<>"",$H11<>"Completed",$G11<>"",$G11<TODAY()),"Overdue","") | O11: 10 | P11: =IF(AND($B11<>"",$H11<>"Completed",$H11<>"Cancelled"),COUNTIFS($B$2:$B11,"<>",$H$2:$H11,"<>Completed",$H$2:$H11,"<>Cancelled"),"") | Q11: =IFERROR(INDEX($B$2:$B$1500,MATCH(ROWS($Q$2:Q11),$P$2:$P$1500,0)),"")
B12: =IF(OR($A12<>"",$C12<>"",$D12<>"",$E12<>"",$F12<>"",$G12<>""),"WL-"&TEXT($O12,"0000"),"") | H12: =IF($B12="","",IF(N($I12)>=100,"Completed",IF(COUNTIF('Work report'!$V$2:$V$1500,$B12)=0,"Not started",IF(OR(LEFT(UPPER(TRIM($K12)),8)="BLOCKED:",LEFT(UPPER(TRIM($K12)),8)="WAITING:"),"Blocked",IF(N($I12)>0,"In progress","Not started"))))) | I12: {=IF($B12="","",IFERROR(LOOKUP(2,1/('Work report'!$V$2:$V$1500=$B12),'Work report'!$J$2:$J$1500)*100,0))} | J12: {=IF($B12="","",IFERROR(LOOKUP(2,1/('Work report'!$V$2:$V$1500=$B12),'Work report'!$A$2:$A$1500),""))} | K12: {=IF($B12="","",IFERROR(LOOKUP(2,1/('Work report'!$V$2:$V$1500=$B12),'Work report'!$P$2:$P$1500),""))} | L12: =IF($B12="","",SUMIFS('Work report'!$G$2:$G$1500,'Work report'!$V$2:$V$1500,$B12)) | M12: =IF($B12="","",IF($H12="Completed",$J12,"")) | N12: =IF(AND($C12<>"",$H12<>"Completed",$G12<>"",$G12<TODAY()),"Overdue","") | O12: 11 | P12: =IF(AND($B12<>"",$H12<>"Completed",$H12<>"Cancelled"),COUNTIFS($B$2:$B12,"<>",$H$2:$H12,"<>Completed",$H$2:$H12,"<>Cancelled"),"") | Q12: =IFERROR(INDEX($B$2:$B$1500,MATCH(ROWS($Q$2:Q12),$P$2:$P$1500,0)),"")
B13: =IF(OR($A13<>"",$C13<>"",$D13<>"",$E13<>"",$F13<>"",$G13<>""),"WL-"&TEXT($O13,"0000"),"") | H13: =IF($B13="","",IF(N($I13)>=100,"Completed",IF(COUNTIF('Work report'!$V$2:$V$1500,$B13)=0,"Not started",IF(OR(LEFT(UPPER(TRIM($K13)),8)="BLOCKED:",LEFT(UPPER(TRIM($K13)),8)="WAITING:"),"Blocked",IF(N($I13)>0,"In progress","Not started"))))) | I13: {=IF($B13="","",IFERROR(LOOKUP(2,1/('Work report'!$V$2:$V$1500=$B13),'Work report'!$J$2:$J$1500)*100,0))} | J13: {=IF($B13="","",IFERROR(LOOKUP(2,1/('Work report'!$V$2:$V$1500=$B13),'Work report'!$A$2:$A$1500),""))} | K13: {=IF($B13="","",IFERROR(LOOKUP(2,1/('Work report'!$V$2:$V$1500=$B13),'Work report'!$P$2:$P$1500),""))} | L13: =IF($B13="","",SUMIFS('Work report'!$G$2:$G$1500,'Work report'!$V$2:$V$1500,$B13)) | M13: =IF($B13="","",IF($H13="Completed",$J13,"")) | N13: =IF(AND($C13<>"",$H13<>"Completed",$G13<>"",$G13<TODAY()),"Overdue","") | O13: 12 | P13: =IF(AND($B13<>"",$H13<>"Completed",$H13<>"Cancelled"),COUNTIFS($B$2:$B13,"<>",$H$2:$H13,"<>Completed",$H$2:$H13,"<>Cancelled"),"") | Q13: =IFERROR(INDEX($B$2:$B$1500,MATCH(ROWS($Q$2:Q13),$P$2:$P$1500,0)),"")
... B1500: =IF(OR($A1500<>"",$C1500<>"",$D1500<>"",$E1500<>"",$F1500<>"",$G1500<>""),"WL-"&TEXT($O1500,"0000"),"") | H1500: =IF($B1500="","",IF(N($I1500)>=100,"Completed",IF(COUNTIF('Work report'!$V$2:$V$1500,$B1500)=0,"Not started",IF(OR(LEFT(UPPER(TRIM($K1500)),8)="BLOCKED:",LEFT(UPPER(TRIM($K1500)),8)="WAITING:"),"Blocked",IF(N($I1500)>0,"In progress","Not started"))))) | I1500: {=IF($B1500="","",IFERROR(LOOKUP(2,1/('Work report'!$V$2:$V$1500=$B1500),'Work report'!$J$2:$J$1500)*100,0))} | J1500: {=IF($B1500="","",IFERROR(LOOKUP(2,1/('Work report'!$V$2:$V$1500=$B1500),'Work report'!$A$2:$A$1500),""))} | K1500: {=IF($B1500="","",IFERROR(LOOKUP(2,1/('Work report'!$V$2:$V$1500=$B1500),'Work report'!$P$2:$P$1500),""))} | L1500: =IF($B1500="","",SUMIFS('Work report'!$G$2:$G$1500,'Work report'!$V$2:$V$1500,$B1500)) | M1500: =IF($B1500="","",IF($H1500="Completed",$J1500,"")) | N1500: =IF(AND($C1500<>"",$H1500<>"Completed",$G1500<>"",$G1500<TODAY()),"Overdue","") | O1500: 1499 | P1500: =IF(AND($B1500<>"",$H1500<>"Completed",$H1500<>"Cancelled"),COUNTIFS($B$2:$B1500,"<>",$H$2:$H1500,"<>Completed",$H$2:$H1500,"<>Cancelled"),"") | Q1500: =IFERROR(INDEX($B$2:$B$1500,MATCH(ROWS($Q$2:Q1500),$P$2:$P$1500,0)),"")

Sheet Work report
A1: Date | B1: Task ID | C1: Quantity | D1: Task name | E1: Description | F1: Std time (min) | G1: Actual time (min) | H1: Delta (min) | I1: Credited time (min) | J1: Completion % | K1: Std time issue? | L1: Number of videos recorded | M1: Video duration (min) | N1: Time difference | O1: Video type | P1: Note | Q1: Link | R1: Task name 2001, 2002 | S1: Description 2001, 2002 | T1: Customer | U1: Rating | V1: WL ID (type/paste; dropdown = open tasks) | W1: Drive check (Drive-link-1 / N3) | X1: Helper key | Y1: Helper total count | Z1: Helper running count | AA1: Helper output index | AB1: Link2 | AC1: Link3 | AD1: Link4
C2: =IF($B2="","",1) | D2: =IF($B2="","",IFERROR(VLOOKUP($B2,'Task library'!$A:$E,2,FALSE()),"")) | E2: =IF($B2="","",IFERROR(VLOOKUP($B2,'Task library'!$A:$E,3,FALSE()),"")) | F2: =IF($B2="","",IFERROR(VLOOKUP($B2,'Task library'!$A:$E,4,FALSE()),"")) | H2: =IF(OR($B2="",$I2=""),"",IFERROR($I2-$G2,"")) | I2: =IF($B2="","",IF($G2="","",IF(ISNUMBER($U2),MAX(0,MIN($G2,$G2/10*$U2)),IF(OR(NOT(ISNUMBER($M2)),$M2<=0,$Q2="",NOT(OR($W2="OK",$W2="FILE LINK (check)"))),"",IF($G2<=$M2+5,$G2,$M2))))) | L2: =IF($B2="","",1) | N2: =IF($B2="","",IF($G2="","",IF(ISNUMBER($M2),$M2,0)-$G2)) | W2: =IF($B2="","",IF($Q2="","MISSING LINK",IF(NOT(ISNUMBER(SEARCH("drive.google.com",$Q2))),"NOT DRIVE LINK",IFERROR(IF(ISNUMBER(SEARCH(MID(Summary!$N$3,SEARCH("/folders/",Summary!$N$3)+9,SEARCH("?",Summary!$N$3&"?")-(SEARCH("/folders/",Summary!$N$3)+9)),$Q2)),"OK",IF(ISNUMBER(SEARCH("/file/d/",$Q2)),"FILE LINK (check)","WRONG DRIVE")),"WRONG DRIVE")))) | X2: =IF(OR($B2=2001,$B2=2002),IF(OR(LEN(TRIM($R2))=0,LEN(TRIM($S2))=0),"",TRIM($R2)&" | "&TRIM($S2)),"") | Y2: =IF($X2="","",COUNTIF($X$2:$X$1500,$X2)) | Z2: =IF($X2="","",COUNTIF($X$2:$X2,$X2)) | AA2: =IF(AND($X2<>"",$Y2>=3,$Z2=1),COUNTIF($AA$1:AA1,">0")+1,"")
C3: =IF($B3="","",1) | D3: =IF($B3="","",IFERROR(VLOOKUP($B3,'Task library'!$A:$E,2,FALSE()),"")) | E3: =IF($B3="","",IFERROR(VLOOKUP($B3,'Task library'!$A:$E,3,FALSE()),"")) | F3: =IF($B3="","",IFERROR(VLOOKUP($B3,'Task library'!$A:$E,4,FALSE()),"")) | H3: =IF(OR($B3="",$I3=""),"",IFERROR($I3-$G3,"")) | I3: =IF($B3="","",IF($G3="","",IF(ISNUMBER($U3),MAX(0,MIN($G3,$G3/10*$U3)),IF(OR(NOT(ISNUMBER($M3)),$M3<=0,$Q3="",NOT(OR($W3="OK",$W3="FILE LINK (check)"))),"",IF($G3<=$M3+5,$G3,$M3))))) | L3: =IF($B3="","",1) | N3: =IF($B3="","",IF($G3="","",IF(ISNUMBER($M3),$M3,0)-$G3)) | W3: =IF($B3="","",IF($Q3="","MISSING LINK",IF(NOT(ISNUMBER(SEARCH("drive.google.com",$Q3))),"NOT DRIVE LINK",IFERROR(IF(ISNUMBER(SEARCH(MID(Summary!$N$3,SEARCH("/folders/",Summary!$N$3)+9,SEARCH("?",Summary!$N$3&"?")-(SEARCH("/folders/",Summary!$N$3)+9)),$Q3)),"OK",IF(ISNUMBER(SEARCH("/file/d/",$Q3)),"FILE LINK (check)","WRONG DRIVE")),"WRONG DRIVE")))) | X3: =IF(OR($B3=2001,$B3=2002),IF(OR(LEN(TRIM($R3))=0,LEN(TRIM($S3))=0),"",TRIM($R3)&" | "&TRIM($S3)),"") | Y3: =IF($X3="","",COUNTIF($X$2:$X$1500,$X3)) | Z3: =IF($X3="","",COUNTIF($X$2:$X3,$X3)) | AA3: =IF(AND($X3<>"",$Y3>=3,$Z3=1),COUNTIF($AA$1:AA2,">0")+1,"")
C4: =IF($B4="","",1) | D4: =IF($B4="","",IFERROR(VLOOKUP($B4,'Task library'!$A:$E,2,FALSE()),"")) | E4: =IF($B4="","",IFERROR(VLOOKUP($B4,'Task library'!$A:$E,3,FALSE()),"")) | F4: =IF($B4="","",IFERROR(VLOOKUP($B4,'Task library'!$A:$E,4,FALSE()),"")) | H4: =IF(OR($B4="",$I4=""),"",IFERROR($I4-$G4,"")) | I4: =IF($B4="","",IF($G4="","",IF(ISNUMBER($U4),MAX(0,MIN($G4,$G4/10*$U4)),IF(OR(NOT(ISNUMBER($M4)),$M4<=0,$Q4="",NOT(OR($W4="OK",$W4="FILE LINK (check)"))),"",IF($G4<=$M4+5,$G4,$M4))))) | L4: =IF($B4="","",1) | N4: =IF($B4="","",IF($G4="","",IF(ISNUMBER($M4),$M4,0)-$G4)) | W4: =IF($B4="","",IF($Q4="","MISSING LINK",IF(NOT(ISNUMBER(SEARCH("drive.google.com",$Q4))),"NOT DRIVE LINK",IFERROR(IF(ISNUMBER(SEARCH(MID(Summary!$N$3,SEARCH("/folders/",Summary!$N$3)+9,SEARCH("?",Summary!$N$3&"?")-(SEARCH("/folders/",Summary!$N$3)+9)),$Q4)),"OK",IF(ISNUMBER(SEARCH("/file/d/",$Q4)),"FILE LINK (check)","WRONG DRIVE")),"WRONG DRIVE")))) | X4: =IF(OR($B4=2001,$B4=2002),IF(OR(LEN(TRIM($R4))=0,LEN(TRIM($S4))=0),"",TRIM($R4)&" | "&TRIM($S4)),"") | Y4: =IF($X4="","",COUNTIF($X$2:$X$1500,$X4)) | Z4: =IF($X4="","",COUNTIF($X$2:$X4,$X4)) | AA4: =IF(AND($X4<>"",$Y4>=3,$Z4=1),COUNTIF($AA$1:AA3,">0")+1,"")
C5: =IF($B5="","",1) | D5: =IF($B5="","",IFERROR(VLOOKUP($B5,'Task library'!$A:$E,2,FALSE()),"")) | E5: =IF($B5="","",IFERROR(VLOOKUP($B5,'Task library'!$A:$E,3,FALSE()),"")) | F5: =IF($B5="","",IFERROR(VLOOKUP($B5,'Task library'!$A:$E,4,FALSE()),"")) | H5: =IF(OR($B5="",$I5=""),"",IFERROR($I5-$G5,"")) | I5: =IF($B5="","",IF($G5="","",IF(ISNUMBER($U5),MAX(0,MIN($G5,$G5/10*$U5)),IF(OR(NOT(ISNUMBER($M5)),$M5<=0,$Q5="",NOT(OR($W5="OK",$W5="FILE LINK (check)"))),"",IF($G5<=$M5+5,$G5,$M5))))) | L5: =IF($B5="","",1) | N5: =IF($B5="","",IF($G5="","",IF(ISNUMBER($M5),$M5,0)-$G5)) | W5: =IF($B5="","",IF($Q5="","MISSING LINK",IF(NOT(ISNUMBER(SEARCH("drive.google.com",$Q5))),"NOT DRIVE LINK",IFERROR(IF(ISNUMBER(SEARCH(MID(Summary!$N$3,SEARCH("/folders/",Summary!$N$3)+9,SEARCH("?",Summary!$N$3&"?")-(SEARCH("/folders/",Summary!$N$3)+9)),$Q5)),"OK",IF(ISNUMBER(SEARCH("/file/d/",$Q5)),"FILE LINK (check)","WRONG DRIVE")),"WRONG DRIVE")))) | X5: =IF(OR($B5=2001,$B5=2002),IF(OR(LEN(TRIM($R5))=0,LEN(TRIM($S5))=0),"",TRIM($R5)&" | "&TRIM($S5)),"") | Y5: =IF($X5="","",COUNTIF($X$2:$X$1500,$X5)) | Z5: =IF($X5="","",COUNTIF($X$2:$X5,$X5)) | AA5: =IF(AND($X5<>"",$Y5>=3,$Z5=1),COUNTIF($AA$1:AA4,">0")+1,"")
C6: =IF($B6="","",1) | D6: =IF($B6="","",IFERROR(VLOOKUP($B6,'Task library'!$A:$E,2,FALSE()),"")) | E6: =IF($B6="","",IFERROR(VLOOKUP($B6,'Task library'!$A:$E,3,FALSE()),"")) | F6: =IF($B6="","",IFERROR(VLOOKUP($B6,'Task library'!$A:$E,4,FALSE()),"")) | H6: =IF(OR($B6="",$I6=""),"",IFERROR($I6-$G6,"")) | I6: =IF($B6="","",IF($G6="","",IF(ISNUMBER($U6),MAX(0,MIN($G6,$G6/10*$U6)),IF(OR(NOT(ISNUMBER($M6)),$M6<=0,$Q6="",NOT(OR($W6="OK",$W6="FILE LINK (check)"))),"",IF($G6<=$M6+5,$G6,$M6))))) | L6: =IF($B6="","",1) | N6: =IF($B6="","",IF($G6="","",IF(ISNUMBER($M6),$M6,0)-$G6)) | W6: =IF($B6="","",IF($Q6="","MISSING LINK",IF(NOT(ISNUMBER(SEARCH("drive.google.com",$Q6))),"NOT DRIVE LINK",IFERROR(IF(ISNUMBER(SEARCH(MID(Summary!$N$3,SEARCH("/folders/",Summary!$N$3)+9,SEARCH("?",Summary!$N$3&"?")-(SEARCH("/folders/",Summary!$N$3)+9)),$Q6)),"OK",IF(ISNUMBER(SEARCH("/file/d/",$Q6)),"FILE LINK (check)","WRONG DRIVE")),"WRONG DRIVE")))) | X6: =IF(OR($B6=2001,$B6=2002),IF(OR(LEN(TRIM($R6))=0,LEN(TRIM($S6))=0),"",TRIM($R6)&" | "&TRIM($S6)),"") | Y6: =IF($X6="","",COUNTIF($X$2:$X$1500,$X6)) | Z6: =IF($X6="","",COUNTIF($X$2:$X6,$X6)) | AA6: =IF(AND($X6<>"",$Y6>=3,$Z6=1),COUNTIF($AA$1:AA5,">0")+1,"")
C7: =IF($B7="","",1) | D7: =IF($B7="","",IFERROR(VLOOKUP($B7,'Task library'!$A:$E,2,FALSE()),"")) | E7: =IF($B7="","",IFERROR(VLOOKUP($B7,'Task library'!$A:$E,3,FALSE()),"")) | F7: =IF($B7="","",IFERROR(VLOOKUP($B7,'Task library'!$A:$E,4,FALSE()),"")) | H7: =IF(OR($B7="",$I7=""),"",IFERROR($I7-$G7,"")) | I7: =IF($B7="","",IF($G7="","",IF(ISNUMBER($U7),MAX(0,MIN($G7,$G7/10*$U7)),IF(OR(NOT(ISNUMBER($M7)),$M7<=0,$Q7="",NOT(OR($W7="OK",$W7="FILE LINK (check)"))),"",IF($G7<=$M7+5,$G7,$M7))))) | L7: =IF($B7="","",1) | N7: =IF($B7="","",IF($G7="","",IF(ISNUMBER($M7),$M7,0)-$G7)) | W7: =IF($B7="","",IF($Q7="","MISSING LINK",IF(NOT(ISNUMBER(SEARCH("drive.google.com",$Q7))),"NOT DRIVE LINK",IFERROR(IF(ISNUMBER(SEARCH(MID(Summary!$N$3,SEARCH("/folders/",Summary!$N$3)+9,SEARCH("?",Summary!$N$3&"?")-(SEARCH("/folders/",Summary!$N$3)+9)),$Q7)),"OK",IF(ISNUMBER(SEARCH("/file/d/",$Q7)),"FILE LINK (check)","WRONG DRIVE")),"WRONG DRIVE")))) | X7: =IF(OR($B7=2001,$B7=2002),IF(OR(LEN(TRIM($R7))=0,LEN(TRIM($S7))=0),"",TRIM($R7)&" | "&TRIM($S7)),"") | Y7: =IF($X7="","",COUNTIF($X$2:$X$1500,$X7)) | Z7: =IF($X7="","",COUNTIF($X$2:$X7,$X7)) | AA7: =IF(AND($X7<>"",$Y7>=3,$Z7=1),COUNTIF($AA$1:AA6,">0")+1,"")
C8: =IF($B8="","",1) | D8: =IF($B8="","",IFERROR(VLOOKUP($B8,'Task library'!$A:$E,2,FALSE()),"")) | E8: =IF($B8="","",IFERROR(VLOOKUP($B8,'Task library'!$A:$E,3,FALSE()),"")) | F8: =IF($B8="","",IFERROR(VLOOKUP($B8,'Task library'!$A:$E,4,FALSE()),"")) | H8: =IF(OR($B8="",$I8=""),"",IFERROR($I8-$G8,"")) | I8: =IF($B8="","",IF($G8="","",IF(ISNUMBER($U8),MAX(0,MIN($G8,$G8/10*$U8)),IF(OR(NOT(ISNUMBER($M8)),$M8<=0,$Q8="",NOT(OR($W8="OK",$W8="FILE LINK (check)"))),"",IF($G8<=$M8+5,$G8,$M8))))) | L8: =IF($B8="","",1) | N8: =IF($B8="","",IF($G8="","",IF(ISNUMBER($M8),$M8,0)-$G8)) | W8: =IF($B8="","",IF($Q8="","MISSING LINK",IF(NOT(ISNUMBER(SEARCH("drive.google.com",$Q8))),"NOT DRIVE LINK",IFERROR(IF(ISNUMBER(SEARCH(MID(Summary!$N$3,SEARCH("/folders/",Summary!$N$3)+9,SEARCH("?",Summary!$N$3&"?")-(SEARCH("/folders/",Summary!$N$3)+9)),$Q8)),"OK",IF(ISNUMBER(SEARCH("/file/d/",$Q8)),"FILE LINK (check)","WRONG DRIVE")),"WRONG DRIVE")))) | X8: =IF(OR($B8=2001,$B8=2002),IF(OR(LEN(TRIM($R8))=0,LEN(TRIM($S8))=0),"",TRIM($R8)&" | "&TRIM($S8)),"") | Y8: =IF($X8="","",COUNTIF($X$2:$X$1500,$X8)) | Z8: =IF($X8="","",COUNTIF($X$2:$X8,$X8)) | AA8: =IF(AND($X8<>"",$Y8>=3,$Z8=1),COUNTIF($AA$1:AA7,">0")+1,"")
C9: =IF($B9="","",1) | D9: =IF($B9="","",IFERROR(VLOOKUP($B9,'Task library'!$A:$E,2,FALSE()),"")) | E9: =IF($B9="","",IFERROR(VLOOKUP($B9,'Task library'!$A:$E,3,FALSE()),"")) | F9: =IF($B9="","",IFERROR(VLOOKUP($B9,'Task library'!$A:$E,4,FALSE()),"")) | H9: =IF(OR($B9="",$I9=""),"",IFERROR($I9-$G9,"")) | I9: =IF($B9="","",IF($G9="","",IF(ISNUMBER($U9),MAX(0,MIN($G9,$G9/10*$U9)),IF(OR(NOT(ISNUMBER($M9)),$M9<=0,$Q9="",NOT(OR($W9="OK",$W9="FILE LINK (check)"))),"",IF($G9<=$M9+5,$G9,$M9))))) | L9: =IF($B9="","",1) | N9: =IF($B9="","",IF($G9="","",IF(ISNUMBER($M9),$M9,0)-$G9)) | W9: =IF($B9="","",IF($Q9="","MISSING LINK",IF(NOT(ISNUMBER(SEARCH("drive.google.com",$Q9))),"NOT DRIVE LINK",IFERROR(IF(ISNUMBER(SEARCH(MID(Summary!$N$3,SEARCH("/folders/",Summary!$N$3)+9,SEARCH("?",Summary!$N$3&"?")-(SEARCH("/folders/",Summary!$N$3)+9)),$Q9)),"OK",IF(ISNUMBER(SEARCH("/file/d/",$Q9)),"FILE LINK (check)","WRONG DRIVE")),"WRONG DRIVE")))) | X9: =IF(OR($B9=2001,$B9=2002),IF(OR(LEN(TRIM($R9))=0,LEN(TRIM($S9))=0),"",TRIM($R9)&" | "&TRIM($S9)),"") | Y9: =IF($X9="","",COUNTIF($X$2:$X$1500,$X9)) | Z9: =IF($X9="","",COUNTIF($X$2:$X9,$X9)) | AA9: =IF(AND($X9<>"",$Y9>=3,$Z9=1),COUNTIF($AA$1:AA8,">0")+1,"")
C10: =IF($B10="","",1) | D10: =IF($B10="","",IFERROR(VLOOKUP($B10,'Task library'!$A:$E,2,FALSE()),"")) | E10: =IF($B10="","",IFERROR(VLOOKUP($B10,'Task library'!$A:$E,3,FALSE()),"")) | F10: =IF($B10="","",IFERROR(VLOOKUP($B10,'Task library'!$A:$E,4,FALSE()),"")) | H10: =IF(OR($B10="",$I10=""),"",IFERROR($I10-$G10,"")) | I10: =IF($B10="","",IF($G10="","",IF(ISNUMBER($U10),MAX(0,MIN($G10,$G10/10*$U10)),IF(OR(NOT(ISNUMBER($M10)),$M10<=0,$Q10="",NOT(OR($W10="OK",$W10="FILE LINK (check)"))),"",IF($G10<=$M10+5,$G10,$M10))))) | L10: =IF($B10="","",1) | N10: =IF($B10="","",IF($G10="","",IF(ISNUMBER($M10),$M10,0)-$G10)) | W10: =IF($B10="","",IF($Q10="","MISSING LINK",IF(NOT(ISNUMBER(SEARCH("drive.google.com",$Q10))),"NOT DRIVE LINK",IFERROR(IF(ISNUMBER(SEARCH(MID(Summary!$N$3,SEARCH("/folders/",Summary!$N$3)+9,SEARCH("?",Summary!$N$3&"?")-(SEARCH("/folders/",Summary!$N$3)+9)),$Q10)),"OK",IF(ISNUMBER(SEARCH("/file/d/",$Q10)),"FILE LINK (check)","WRONG DRIVE")),"WRONG DRIVE")))) | X10: =IF(OR($B10=2001,$B10=2002),IF(OR(LEN(TRIM($R10))=0,LEN(TRIM($S10))=0),"",TRIM($R10)&" | "&TRIM($S10)),"") | Y10: =IF($X10="","",COUNTIF($X$2:$X$1500,$X10)) | Z10: =IF($X10="","",COUNTIF($X$2:$X10,$X10)) | AA10: =IF(AND($X10<>"",$Y10>=3,$Z10=1),COUNTIF($AA$1:AA9,">0")+1,"")
C11: =IF($B11="","",1) | D11: =IF($B11="","",IFERROR(VLOOKUP($B11,'Task library'!$A:$E,2,FALSE()),"")) | E11: =IF($B11="","",IFERROR(VLOOKUP($B11,'Task library'!$A:$E,3,FALSE()),"")) | F11: =IF($B11="","",IFERROR(VLOOKUP($B11,'Task library'!$A:$E,4,FALSE()),"")) | H11: =IF(OR($B11="",$I11=""),"",IFERROR($I11-$G11,"")) | I11: =IF($B11="","",IF($G11="","",IF(ISNUMBER($U11),MAX(0,MIN($G11,$G11/10*$U11)),IF(OR(NOT(ISNUMBER($M11)),$M11<=0,$Q11="",NOT(OR($W11="OK",$W11="FILE LINK (check)"))),"",IF($G11<=$M11+5,$G11,$M11))))) | L11: =IF($B11="","",1) | N11: =IF($B11="","",IF($G11="","",IF(ISNUMBER($M11),$M11,0)-$G11)) | W11: =IF($B11="","",IF($Q11="","MISSING LINK",IF(NOT(ISNUMBER(SEARCH("drive.google.com",$Q11))),"NOT DRIVE LINK",IFERROR(IF(ISNUMBER(SEARCH(MID(Summary!$N$3,SEARCH("/folders/",Summary!$N$3)+9,SEARCH("?",Summary!$N$3&"?")-(SEARCH("/folders/",Summary!$N$3)+9)),$Q11)),"OK",IF(ISNUMBER(SEARCH("/file/d/",$Q11)),"FILE LINK (check)","WRONG DRIVE")),"WRONG DRIVE")))) | X11: =IF(OR($B11=2001,$B11=2002),IF(OR(LEN(TRIM($R11))=0,LEN(TRIM($S11))=0),"",TRIM($R11)&" | "&TRIM($S11)),"") | Y11: =IF($X11="","",COUNTIF($X$2:$X$1500,$X11)) | Z11: =IF($X11="","",COUNTIF($X$2:$X11,$X11)) | AA11: =IF(AND($X11<>"",$Y11>=3,$Z11=1),COUNTIF($AA$1:AA10,">0")+1,"")
C12: =IF($B12="","",1) | D12: =IF($B12="","",IFERROR(VLOOKUP($B12,'Task library'!$A:$E,2,FALSE()),"")) | E12: =IF($B12="","",IFERROR(VLOOKUP($B12,'Task library'!$A:$E,3,FALSE()),"")) | F12: =IF($B12="","",IFERROR(VLOOKUP($B12,'Task library'!$A:$E,4,FALSE()),"")) | H12: =IF(OR($B12="",$I12=""),"",IFERROR($I12-$G12,"")) | I12: =IF($B12="","",IF($G12="","",IF(ISNUMBER($U12),MAX(0,MIN($G12,$G12/10*$U12)),IF(OR(NOT(ISNUMBER($M12)),$M12<=0,$Q12="",NOT(OR($W12="OK",$W12="FILE LINK (check)"))),"",IF($G12<=$M12+5,$G12,$M12))))) | L12: =IF($B12="","",1) | N12: =IF($B12="","",IF($G12="","",IF(ISNUMBER($M12),$M12,0)-$G12)) | W12: =IF($B12="","",IF($Q12="","MISSING LINK",IF(NOT(ISNUMBER(SEARCH("drive.google.com",$Q12))),"NOT DRIVE LINK",IFERROR(IF(ISNUMBER(SEARCH(MID(Summary!$N$3,SEARCH("/folders/",Summary!$N$3)+9,SEARCH("?",Summary!$N$3&"?")-(SEARCH("/folders/",Summary!$N$3)+9)),$Q12)),"OK",IF(ISNUMBER(SEARCH("/file/d/",$Q12)),"FILE LINK (check)","WRONG DRIVE")),"WRONG DRIVE")))) | X12: =IF(OR($B12=2001,$B12=2002),IF(OR(LEN(TRIM($R12))=0,LEN(TRIM($S12))=0),"",TRIM($R12)&" | "&TRIM($S12)),"") | Y12: =IF($X12="","",COUNTIF($X$2:$X$1500,$X12)) | Z12: =IF($X12="","",COUNTIF($X$2:$X12,$X12)) | AA12: =IF(AND($X12<>"",$Y12>=3,$Z12=1),COUNTIF($AA$1:AA11,">0")+1,"")
C13: =IF($B13="","",1) | D13: =IF($B13="","",IFERROR(VLOOKUP($B13,'Task library'!$A:$E,2,FALSE()),"")) | E13: =IF($B13="","",IFERROR(VLOOKUP($B13,'Task library'!$A:$E,3,FALSE()),"")) | F13: =IF($B13="","",IFERROR(VLOOKUP($B13,'Task library'!$A:$E,4,FALSE()),"")) | H13: =IF(OR($B13="",$I13=""),"",IFERROR($I13-$G13,"")) | I13: =IF($B13="","",IF($G13="","",IF(ISNUMBER($U13),MAX(0,MIN($G13,$G13/10*$U13)),IF(OR(NOT(ISNUMBER($M13)),$M13<=0,$Q13="",NOT(OR($W13="OK",$W13="FILE LINK (check)"))),"",IF($G13<=$M13+5,$G13,$M13))))) | L13: =IF($B13="","",1) | N13: =IF($B13="","",IF($G13="","",IF(ISNUMBER($M13),$M13,0)-$G13)) | W13: =IF($B13="","",IF($Q13="","MISSING LINK",IF(NOT(ISNUMBER(SEARCH("drive.google.com",$Q13))),"NOT DRIVE LINK",IFERROR(IF(ISNUMBER(SEARCH(MID(Summary!$N$3,SEARCH("/folders/",Summary!$N$3)+9,SEARCH("?",Summary!$N$3&"?")-(SEARCH("/folders/",Summary!$N$3)+9)),$Q13)),"OK",IF(ISNUMBER(SEARCH("/file/d/",$Q13)),"FILE LINK (check)","WRONG DRIVE")),"WRONG DRIVE")))) | X13: =IF(OR($B13=2001,$B13=2002),IF(OR(LEN(TRIM($R13))=0,LEN(TRIM($S13))=0),"",TRIM($R13)&" | "&TRIM($S13)),"") | Y13: =IF($X13="","",COUNTIF($X$2:$X$1500,$X13)) | Z13: =IF($X13="","",COUNTIF($X$2:$X13,$X13)) | AA13: =IF(AND($X13<>"",$Y13>=3,$Z13=1),COUNTIF($AA$1:AA12,">0")+1,"")
... C1500: =IF($B1500="","",1) | D1500: =IF($B1500="","",IFERROR(VLOOKUP($B1500,'Task library'!$A:$E,2,FALSE()),"")) | E1500: =IF($B1500="","",IFERROR(VLOOKUP($B1500,'Task library'!$A:$E,3,FALSE()),"")) | F1500: =IF($B1500="","",IFERROR(VLOOKUP($B1500,'Task library'!$A:$E,4,FALSE()),"")) | H1500: =IF(OR($B1500="",$I1500=""),"",IFERROR($I1500-$G1500,"")) | I1500: =IF($B1500="","",IF($G1500="","",IF(ISNUMBER($U1500),MAX(0,MIN($G1500,$G1500/10*$U1500)),IF(OR(NOT(ISNUMBER($M1500)),$M1500<=0,$Q1500="",NOT(OR($W1500="OK",$W1500="FILE LINK (check)"))),"",IF($G1500<=$M1500+5,$G1500,$M1500))))) | L1500: =IF($B1500="","",1) | N1500: =IF($B1500="","",IF($G1500="","",IF(ISNUMBER($M1500),$M1500,0)-$G1500)) | W1500: =IF($B1500="","",IF($Q1500="","MISSING LINK",IF(NOT(ISNUMBER(SEARCH("drive.google.com",$Q1500))),"NOT DRIVE LINK",IFERROR(IF(ISNUMBER(SEARCH(MID(Summary!$N$3,SEARCH("/folders/",Summary!$N$3)+9,SEARCH("?",Summary!$N$3&"?")-(SEARCH("/folders/",Summary!$N$3)+9)),$Q1500)),"OK",IF(ISNUMBER(SEARCH("/file/d/",$Q1500)),"FILE LINK (check)","WRONG DRIVE")),"WRONG DRIVE")))) | X1500: =IF(OR($B1500=2001,$B1500=2002),IF(OR(LEN(TRIM($R1500))=0,LEN(TRIM($S1500))=0),"",TRIM($R1500)&" | "&TRIM($S1500)),"") | Y1500: =IF($X1500="","",COUNTIF($X$2:$X$1500,$X1500)) | Z1500: =IF($X1500="","",COUNTIF($X$2:$X1500,$X1500)) | AA1500: =IF(AND($X1500<>"",$Y1500>=3,$Z1500=1),COUNTIF($AA$1:AA1499,">0")+1,"")

Sheet Office time approval
A1: Date | B1: Start work 1 | C1: Start lunch | D1: Start work 2 | E1: Start afternoon break | F1: Start work 3 | G1: End workday | H1: Work report total (min) | I1: Actual worked (min) | J1: Delta (min) | K1: Explanation of delta | L1: Approval status | M1: Approved delta -> Summary C (min)
A2: {=IFERROR(INDEX(_xlfn.UNIQUE(_xlfn._xlws.FILTER('Work report'!$A$2:$A$1500,'Work report'!$B$2:$B$1500<>"")),ROW(A1)),"")} | H2: =IF($A2="","",SUMIFS('Work report'!$I$2:$I$1500,'Work report'!$A$2:$A$1500,$A2,'Work report'!$B$2:$B$1500,"<>")) | I2: =IF( SUM( IF(AND($B2<>"",$C2<>""),($C2-$B2)*1440,0), IF(AND($D2<>"",$E2<>""),($E2-$D2)*1440,0), IF(AND($F2<>"",$G2<>""),($G2-$F2)*1440,0) )=0, "", SUM( IF(AND($B2<>"",$C2<>""),($C2-$B2)*1440,0), IF(AND($D2<>"",$E2<>""),($E2-$D2)*1440,0), IF(AND($F2<>"",$G2<>""),($G2-$F2)*1440,0) ) ) | J2: =IF(OR($H2="",$I2=""),"",$I2-$H2) | M2: =IF(OR($J2="",$L2<>"Approved"),"",$J2)
A3: {=IFERROR(INDEX(_xlfn.UNIQUE(_xlfn._xlws.FILTER('Work report'!$A$2:$A$1500,'Work report'!$B$2:$B$1500<>"")),ROW(A2)),"")} | H3: =IF($A3="","",SUMIFS('Work report'!$I$2:$I$1500,'Work report'!$A$2:$A$1500,$A3,'Work report'!$B$2:$B$1500,"<>")) | I3: =IF( SUM( IF(AND($B3<>"",$C3<>""),($C3-$B3)*1440,0), IF(AND($D3<>"",$E3<>""),($E3-$D3)*1440,0), IF(AND($F3<>"",$G3<>""),($G3-$F3)*1440,0) )=0, "", SUM( IF(AND($B3<>"",$C3<>""),($C3-$B3)*1440,0), IF(AND($D3<>"",$E3<>""),($E3-$D3)*1440,0), IF(AND($F3<>"",$G3<>""),($G3-$F3)*1440,0) ) ) | J3: =IF(OR($H3="",$I3=""),"",$I3-$H3) | M3: =IF(OR($J3="",$L3<>"Approved"),"",$J3)
A4: {=IFERROR(INDEX(_xlfn.UNIQUE(_xlfn._xlws.FILTER('Work report'!$A$2:$A$1500,'Work report'!$B$2:$B$1500<>"")),ROW(A3)),"")} | H4: =IF($A4="","",SUMIFS('Work report'!$I$2:$I$1500,'Work report'!$A$2:$A$1500,$A4,'Work report'!$B$2:$B$1500,"<>")) | I4: =IF( SUM( IF(AND($B4<>"",$C4<>""),($C4-$B4)*1440,0), IF(AND($D4<>"",$E4<>""),($E4-$D4)*1440,0), IF(AND($F4<>"",$G4<>""),($G4-$F4)*1440,0) )=0, "", SUM( IF(AND($B4<>"",$C4<>""),($C4-$B4)*1440,0), IF(AND($D4<>"",$E4<>""),($E4-$D4)*1440,0), IF(AND($F4<>"",$G4<>""),($G4-$F4)*1440,0) ) ) | J4: =IF(OR($H4="",$I4=""),"",$I4-$H4) | M4: =IF(OR($J4="",$L4<>"Approved"),"",$J4)
A5: {=IFERROR(INDEX(_xlfn.UNIQUE(_xlfn._xlws.FILTER('Work report'!$A$2:$A$1500,'Work report'!$B$2:$B$1500<>"")),ROW(A4)),"")} | H5: =IF($A5="","",SUMIFS('Work report'!$I$2:$I$1500,'Work report'!$A$2:$A$1500,$A5,'Work report'!$B$2:$B$1500,"<>")) | I5: =IF( SUM( IF(AND($B5<>"",$C5<>""),($C5-$B5)*1440,0), IF(AND($D5<>"",$E5<>""),($E5-$D5)*1440,0), IF(AND($F5<>"",$G5<>""),($G5-$F5)*1440,0) )=0, "", SUM( IF(AND($B5<>"",$C5<>""),($C5-$B5)*1440,0), IF(AND($D5<>"",$E5<>""),($E5-$D5)*1440,0), IF(AND($F5<>"",$G5<>""),($G5-$F5)*1440,0) ) ) | J5: =IF(OR($H5="",$I5=""),"",$I5-$H5) | M5: =IF(OR($J5="",$L5<>"Approved"),"",$J5)
A6: {=IFERROR(INDEX(_xlfn.UNIQUE(_xlfn._xlws.FILTER('Work report'!$A$2:$A$1500,'Work report'!$B$2:$B$1500<>"")),ROW(A5)),"")} | H6: =IF($A6="","",SUMIFS('Work report'!$I$2:$I$1500,'Work report'!$A$2:$A$1500,$A6,'Work report'!$B$2:$B$1500,"<>")) | I6: =IF( SUM( IF(AND($B6<>"",$C6<>""),($C6-$B6)*1440,0), IF(AND($D6<>"",$E6<>""),($E6-$D6)*1440,0), IF(AND($F6<>"",$G6<>""),($G6-$F6)*1440,0) )=0, "", SUM( IF(AND($B6<>"",$C6<>""),($C6-$B6)*1440,0), IF(AND($D6<>"",$E6<>""),($E6-$D6)*1440,0), IF(AND($F6<>"",$G6<>""),($G6-$F6)*1440,0) ) ) | J6: =IF(OR($H6="",$I6=""),"",$I6-$H6) | M6: =IF(OR($J6="",$L6<>"Approved"),"",$J6)
A7: {=IFERROR(INDEX(_xlfn.UNIQUE(_xlfn._xlws.FILTER('Work report'!$A$2:$A$1500,'Work report'!$B$2:$B$1500<>"")),ROW(A6)),"")} | H7: =IF($A7="","",SUMIFS('Work report'!$I$2:$I$1500,'Work report'!$A$2:$A$1500,$A7,'Work report'!$B$2:$B$1500,"<>")) | I7: =IF( SUM( IF(AND($B7<>"",$C7<>""),($C7-$B7)*1440,0), IF(AND($D7<>"",$E7<>""),($E7-$D7)*1440,0), IF(AND($F7<>"",$G7<>""),($G7-$F7)*1440,0) )=0, "", SUM( IF(AND($B7<>"",$C7<>""),($C7-$B7)*1440,0), IF(AND($D7<>"",$E7<>""),($E7-$D7)*1440,0), IF(AND($F7<>"",$G7<>""),($G7-$F7)*1440,0) ) ) | J7: =IF(OR($H7="",$I7=""),"",$I7-$H7) | M7: =IF(OR($J7="",$L7<>"Approved"),"",$J7)
A8: {=IFERROR(INDEX(_xlfn.UNIQUE(_xlfn._xlws.FILTER('Work report'!$A$2:$A$1500,'Work report'!$B$2:$B$1500<>"")),ROW(A7)),"")} | H8: =IF($A8="","",SUMIFS('Work report'!$I$2:$I$1500,'Work report'!$A$2:$A$1500,$A8,'Work report'!$B$2:$B$1500,"<>")) | I8: =IF( SUM( IF(AND($B8<>"",$C8<>""),($C8-$B8)*1440,0), IF(AND($D8<>"",$E8<>""),($E8-$D8)*1440,0), IF(AND($F8<>"",$G8<>""),($G8-$F8)*1440,0) )=0, "", SUM( IF(AND($B8<>"",$C8<>""),($C8-$B8)*1440,0), IF(AND($D8<>"",$E8<>""),($E8-$D8)*1440,0), IF(AND($F8<>"",$G8<>""),($G8-$F8)*1440,0) ) ) | J8: =IF(OR($H8="",$I8=""),"",$I8-$H8) | M8: =IF(OR($J8="",$L8<>"Approved"),"",$J8)
A9: {=IFERROR(INDEX(_xlfn.UNIQUE(_xlfn._xlws.FILTER('Work report'!$A$2:$A$1500,'Work report'!$B$2:$B$1500<>"")),ROW(A8)),"")} | H9: =IF($A9="","",SUMIFS('Work report'!$I$2:$I$1500,'Work report'!$A$2:$A$1500,$A9,'Work report'!$B$2:$B$1500,"<>")) | I9: =IF( SUM( IF(AND($B9<>"",$C9<>""),($C9-$B9)*1440,0), IF(AND($D9<>"",$E9<>""),($E9-$D9)*1440,0), IF(AND($F9<>"",$G9<>""),($G9-$F9)*1440,0) )=0, "", SUM( IF(AND($B9<>"",$C9<>""),($C9-$B9)*1440,0), IF(AND($D9<>"",$E9<>""),($E9-$D9)*1440,0), IF(AND($F9<>"",$G9<>""),($G9-$F9)*1440,0) ) ) | J9: =IF(OR($H9="",$I9=""),"",$I9-$H9) | M9: =IF(OR($J9="",$L9<>"Approved"),"",$J9)
A10: {=IFERROR(INDEX(_xlfn.UNIQUE(_xlfn._xlws.FILTER('Work report'!$A$2:$A$1500,'Work report'!$B$2:$B$1500<>"")),ROW(A9)),"")} | H10: =IF($A10="","",SUMIFS('Work report'!$I$2:$I$1500,'Work report'!$A$2:$A$1500,$A10,'Work report'!$B$2:$B$1500,"<>")) | I10: =IF( SUM( IF(AND($B10<>"",$C10<>""),($C10-$B10)*1440,0), IF(AND($D10<>"",$E10<>""),($E10-$D10)*1440,0), IF(AND($F10<>"",$G10<>""),($G10-$F10)*1440,0) )=0, "", SUM( IF(AND($B10<>"",$C10<>""),($C10-$B10)*1440,0), IF(AND($D10<>"",$E10<>""),($E10-$D10)*1440,0), IF(AND($F10<>"",$G10<>""),($G10-$F10)*1440,0) ) ) | J10: =IF(OR($H10="",$I10=""),"",$I10-$H10) | M10: =IF(OR($J10="",$L10<>"Approved"),"",$J10)
A11: {=IFERROR(INDEX(_xlfn.UNIQUE(_xlfn._xlws.FILTER('Work report'!$A$2:$A$1500,'Work report'!$B$2:$B$1500<>"")),ROW(A10)),"")} | H11: =IF($A11="","",SUMIFS('Work report'!$I$2:$I$1500,'Work report'!$A$2:$A$1500,$A11,'Work report'!$B$2:$B$1500,"<>")) | I11: =IF( SUM( IF(AND($B11<>"",$C11<>""),($C11-$B11)*1440,0), IF(AND($D11<>"",$E11<>""),($E11-$D11)*1440,0), IF(AND($F11<>"",$G11<>""),($G11-$F11)*1440,0) )=0, "", SUM( IF(AND($B11<>"",$C11<>""),($C11-$B11)*1440,0), IF(AND($D11<>"",$E11<>""),($E11-$D11)*1440,0), IF(AND($F11<>"",$G11<>""),($G11-$F11)*1440,0) ) ) | J11: =IF(OR($H11="",$I11=""),"",$I11-$H11) | M11: =IF(OR($J11="",$L11<>"Approved"),"",$J11)
A12: {=IFERROR(INDEX(_xlfn.UNIQUE(_xlfn._xlws.FILTER('Work report'!$A$2:$A$1500,'Work report'!$B$2:$B$1500<>"")),ROW(A11)),"")} | H12: =IF($A12="","",SUMIFS('Work report'!$I$2:$I$1500,'Work report'!$A$2:$A$1500,$A12,'Work report'!$B$2:$B$1500,"<>")) | I12: =IF( SUM( IF(AND($B12<>"",$C12<>""),($C12-$B12)*1440,0), IF(AND($D12<>"",$E12<>""),($E12-$D12)*1440,0), IF(AND($F12<>"",$G12<>""),($G12-$F12)*1440,0) )=0, "", SUM( IF(AND($B12<>"",$C12<>""),($C12-$B12)*1440,0), IF(AND($D12<>"",$E12<>""),($E12-$D12)*1440,0), IF(AND($F12<>"",$G12<>""),($G12-$F12)*1440,0) ) ) | J12: =IF(OR($H12="",$I12=""),"",$I12-$H12) | M12: =IF(OR($J12="",$L12<>"Approved"),"",$J12)
A13: {=IFERROR(INDEX(_xlfn.UNIQUE(_xlfn._xlws.FILTER('Work report'!$A$2:$A$1500,'Work report'!$B$2:$B$1500<>"")),ROW(A12)),"")} | H13: =IF($A13="","",SUMIFS('Work report'!$I$2:$I$1500,'Work report'!$A$2:$A$1500,$A13,'Work report'!$B$2:$B$1500,"<>")) | I13: =IF( SUM( IF(AND($B13<>"",$C13<>""),($C13-$B13)*1440,0), IF(AND($D13<>"",$E13<>""),($E13-$D13)*1440,0), IF(AND($F13<>"",$G13<>""),($G13-$F13)*1440,0) )=0, "", SUM( IF(AND($B13<>"",$C13<>""),($C13-$B13)*1440,0), IF(AND($D13<>"",$E13<>""),($E13-$D13)*1440,0), IF(AND($F13<>"",$G13<>""),($G13-$F13)*1440,0) ) ) | J13: =IF(OR($H13="",$I13=""),"",$I13-$H13) | M13: =IF(OR($J13="",$L13<>"Approved"),"",$J13)
... A1500: {=IFERROR(INDEX(_xlfn.UNIQUE(_xlfn._xlws.FILTER('Work report'!$A$2:$A$1500,'Work report'!$B$2:$B$1500<>"")),ROW(A1499)),"")} | H1500: =IF($A1500="","",SUMIFS('Work report'!$I$2:$I$1500,'Work report'!$A$2:$A$1500,$A1500,'Work report'!$B$2:$B$1500,"<>")) | I1500: =IF( SUM( IF(AND($B1500<>"",$C1500<>""),($C1500-$B1500)*1440,0), IF(AND($D1500<>"",$E1500<>""),($E1500-$D1500)*1440,0), IF(AND($F1500<>"",$G1500<>""),($G1500-$F1500)*1440,0) )=0, "", SUM( IF(AND($B1500<>"",$C1500<>""),($C1500-$B1500)*1440,0), IF(AND($D1500<>"",$E1500<>""),($E1500-$D1500)*1440,0), IF(AND($F1500<>"",$G1500<>""),($G1500-$F1500)*1440,0) ) ) | J1500: =IF(OR($H1500="",$I1500=""),"",$I1500-$H1500) | M1500: =IF(OR($J1500="",$L1500<>"Approved"),"",$J1500)

Sheet Task library
A1: No | B1: Task name | C1: Description | D1: Std time (min) | E1: Link template | F1: Note1 | G1: Note2
A2: DEV01 | B2: Tiếp nhận yêu cầu | C2: Nhận yêu cầu từ khách hàng, chủ doanh nghiệp hoặc bộ phận nội bộ | D2: 1 | F2: for Dev
A3: DEV02 | B3: Làm rõ yêu cầu | C3: Hỏi lại những điểm chưa rõ, xác định mục tiêu thật sự của chức năng/dự án | D3: 1 | F3: for Dev
A4: DEV03 | B4: Phân tích nghiệp vụ | C4: Chuyển yêu cầu kinh doanh thành yêu cầu kỹ thuật dễ hiểu cho lập trình viên | D4: 1 | F4: for Dev
A5: DEV04 | B5: Xác định phạm vi công việc | C5: Chốt việc nào làm, việc nào chưa làm, tránh mở rộng ngoài kế hoạch | D5: 1 | F5: for Dev
A6: DEV05 | B6: Chia nhỏ task | C6: Tách dự án lớn thành các đầu việc nhỏ, rõ ràng, có thể giao cho từng người | D6: 1 | F6: for Dev
A7: DEV06 | B7: Ước lượng thời gian | C7: Dự tính thời gian hoàn thành từng task, xác định việc gấp và việc có thể để sau | D7: 1 | F7: for Dev
A8: DEV07 | B8: Phân công công việc | C8: Giao task cho lập trình viên phù hợp với năng lực, kinh nghiệm và thời gian | D8: 1 | F8: for Dev
A9: DEV08 | B9: Theo dõi tiến độ | C9: Kiểm tra task đang làm, task bị kẹt, task đã xong, task cần hỗ trợ | D9: 1 | F9: for Dev
A10: DEV09 | B10: Kiểm tra chất lượng đầu ra | C10: Xem chức năng có chạy đúng, giao diện có ổn, dữ liệu có chính xác không | D10: 1 | F10: for Dev
A11: DEV10 | B11: Review logic / giải pháp | C11: Kiểm tra cách làm của lập trình viên có hợp lý, bền vững và dễ bảo trì không | D11: 1 | F11: for Dev
A12: DEV11 | B12: Kiểm soát lỗi phát sinh | C12: Theo dõi bug, phân loại mức độ nghiêm trọng và giao người xử lý | D12: 1 | F12: for Dev
A13: DEV12 | B13: Ưu tiên công việc | C13: Sắp xếp thứ tự xử lý: lỗi nghiêm trọng, khách đang chờ, việc ảnh hưởng doanh thu | D13: 1 | F13: for Dev
... A21: DEV20 | B21: Chuẩn hóa quy trình làm việc | C21: Xây dựng quy tắc đặt task, ghi log, quay video, nghiệm thu, bàn giao và lưu tài liệu | D21: 1 | F21: for Dev
A22: DTL01 | B22: Tiếp nhận và làm rõ yêu cầu | C22: Đọc yêu cầu từ anh, khách hàng hoặc nội bộ; hỏi lại điểm chưa rõ; xác định mục tiêu thật sự của công việc | D22: 1 | F22: for IT Team Lead | G22: Tin nhắn, email, tài liệu yêu cầu, ghi chú phân tích
A23: DTL02 | B23: Phân tích yêu cầu thành task kỹ thuật | C23: Chuyển yêu cầu chung thành các task nhỏ cho lập trình viên: frontend, backend, database, API, deploy, test | D23: 1 | F23: for IT Team Lead | G23: File/task list, ảnh chụp task, link Trello/Drive/Excel
A24: DTL03 | B24: Lập kế hoạch triển khai | C24: Xác định thứ tự làm việc, thời gian dự kiến, người phụ trách, rủi ro và mốc kiểm tra | D24: 1 | F24: for IT Team Lead | G24: Kế hoạch ngắn, bảng phân công, ghi chú trong Work list
A25: DTL04 | B25: Phân công việc cho lập trình viên | C25: Giao task đúng người, đúng năng lực; ghi rõ yêu cầu, deadline, kết quả cần bàn giao | D25: 1 | F25: for IT Team Lead | G25: Tin nhắn giao việc, task trong hệ thống, Work list
A26: DTL05 | B26: Theo dõi tiến độ nhóm lập trình | C26: Kiểm tra ai đang làm gì, task nào xong, task nào bị kẹt, task nào cần ưu tiên | D26: 1 | F26: for IT Team Lead | G26: Báo cáo tiến độ, ảnh chụp bảng task, ghi chú follow-up
A27: DTL06 | B27: Hỗ trợ lập trình viên khi bị kẹt | C27: Hướng dẫn cách debug, tìm nguyên nhân lỗi, gợi ý phương án xử lý hoặc chia nhỏ vấn đề | D27: 1 | F27: for IT Team Lead | G27: Video trao đổi, ghi chú hướng xử lý, đoạn code/log liên quan
A28: DTL07 | B28: Review code và logic xử lý | C28: Kiểm tra code của lập trình viên: logic, bảo mật, dễ bảo trì, tránh sửa tạm gây lỗi sau này | D28: 1 | F28: for IT Team Lead | G28: Pull request, ảnh code, ghi chú review, video review
A29: DTL08 | B29: Kiểm tra chức năng sau khi lập trình viên hoàn thành | C29: Test lại chức năng: nhập dữ liệu, bấm nút, kiểm tra kết quả, kiểm tra lỗi trên desktop/mobile | D29: 1 | F29: for IT Team Lead | G29: Video test, ảnh trước/sau, link trang đã sửa
A30: DTL09 | B30: Kiểm soát lỗi phát sinh / bug tracking | C30: Ghi nhận lỗi, phân loại mức độ nghiêm trọng, giao người sửa và kiểm tra lại sau khi sửa | D30: 1 | F30: for IT Team Lead | G30: Danh sách bug, ảnh lỗi, video lỗi, ghi chú kết quả sửa
A31: DTL10 | B31: Quản lý deploy / cập nhật lên server | C31: Kiểm tra điều kiện trước khi đưa code lên live; hạn chế deploy vội gây lỗi website đang chạy | D31: 1 | F31: for IT Team Lead | G31: Video deploy, log deploy, ghi chú version, link trang sau deploy
A32: DTL11 | B32: Kiểm tra sau deploy | C32: Sau khi cập nhật lên server, kiểm tra website/app có hoạt động bình thường không: giao diện, form, menu, đặt bàn, đặt món, chatbot... | D32: 1 | F32: for IT Team Lead | G32: Video test live, ảnh chụp trang live, checklist sau deploy
A33: DTL12 | B33: Quản lý database / migration quan trọng | C33: Kiểm tra thay đổi database, migration, backup trước khi sửa dữ liệu quan trọng | D33: 1 | F33: for IT Team Lead | G33: File migration, ảnh database, log backup, video thao tác
... A39: DTL18 | B39: Kiểm tra bằng chứng công việc của lập trình viên | C39: Xem video, link Drive, mô tả task, thời lượng, kết quả thực tế để đánh giá công việc có hợp lệ không | D39: 1 | F39: for IT Team Lead | G39: Link video, Work report, ghi chú đánh giá, điểm review
A40: 1001 | B40: Học & Tìm hiểu | C40: Học / tìm hiểu quy trình – tài liệu | D40: 1 | F40: other
A41: 2001 | B41: Việc mới | C41: Tất cả những việc chưa có trên hệ thống | D41: 1 | F41: other
A42: 2002 | B42: Task dự phòng | C42: Tạm thời ko dùng Task dự phòng này | D42: 1 | F42: other

Sheet Missing tasks auto 
A1: Date | B1: Employee | C1: Task name | D1: Description | E1: Quantity | F1: Time allotted for the task (min) | G1: Video link (Google Drive) | H1: Video duration (min) | I1: Date recorded | J1: Approved time + Bonus time | K1: Manual task name | L1: Manual description | M1: Reason / Note | N1: Status | O1: Final task name | P1: Final description | Q1: Source
A2: =IF($C2="","",IFERROR(INDEX('Work report'!$A$2:$A$1500,MATCH(ROWS($C$2:C2),'Work report'!$AA$2:$AA$1500,0)),"")) | B2: =IF($C2="","",Setup!$B$4) | C2: =IFERROR(INDEX('Work report'!$R$2:$R$1500,MATCH(ROWS($C$2:C2),'Work report'!$AA$2:$AA$1500,0)),"") | D2: =IFERROR(INDEX('Work report'!$S$2:$S$1500,MATCH(ROWS($D$2:D2),'Work report'!$AA$2:$AA$1500,0)),"") | E2: =IF($C2="","",IFERROR(INDEX('Work report'!$C$2:$C$1500,MATCH(ROWS($C$2:C2),'Work report'!$AA$2:$AA$1500,0)),"")) | F2: =IF($C2="","",IFERROR(INDEX('Work report'!$F$2:$F$1500,MATCH(ROWS($C$2:C2),'Work report'!$AA$2:$AA$1500,0)),"")) | G2: =IF($C2="","",IFERROR(HYPERLINK(INDEX('Work report'!$Q$2:$Q$1500,MATCH(ROWS($C$2:C2),'Work report'!$AA$2:$AA$1500,0)),INDEX('Work report'!$Q$2:$Q$1500,MATCH(ROWS($C$2:C2),'Work report'!$AA$2:$AA$1500,0))),"")) | H2: =IF($C2="","",IFERROR(INDEX('Work report'!$M$2:$M$1500,MATCH(ROWS($C$2:C2),'Work report'!$AA$2:$AA$1500,0)),"")) | I2: =IF($C2="","",IFERROR(INDEX('Work report'!$A$2:$A$1500,MATCH(ROWS($C$2:C2),'Work report'!$AA$2:$AA$1500,0)),"")) | J2: =IF($C2="","",IFERROR(INDEX('Work report'!$I$2:$I$1500,MATCH(ROWS($C$2:C2),'Work report'!$AA$2:$AA$1500,0)),"")) | O2: =IF($C2<>"",$C2,$K2) -> 0 | P2: =IF($D2<>"",$D2,$L2) -> 0 | Q2: =IF($C2<>"","System",IF($K2<>"","Manual",""))
A3: =IF($C3="","",IFERROR(INDEX('Work report'!$A$2:$A$1500,MATCH(ROWS($C$2:C3),'Work report'!$AA$2:$AA$1500,0)),"")) | B3: =IF($C3="","",Setup!$B$4) | C3: =IFERROR(INDEX('Work report'!$R$2:$R$1500,MATCH(ROWS($C$2:C3),'Work report'!$AA$2:$AA$1500,0)),"") | D3: =IFERROR(INDEX('Work report'!$S$2:$S$1500,MATCH(ROWS($D$2:D3),'Work report'!$AA$2:$AA$1500,0)),"") | E3: =IF($C3="","",IFERROR(INDEX('Work report'!$C$2:$C$1500,MATCH(ROWS($C$2:C3),'Work report'!$AA$2:$AA$1500,0)),"")) | F3: =IF($C3="","",IFERROR(INDEX('Work report'!$F$2:$F$1500,MATCH(ROWS($C$2:C3),'Work report'!$AA$2:$AA$1500,0)),"")) | G3: =IF($C3="","",IFERROR(HYPERLINK(INDEX('Work report'!$Q$2:$Q$1500,MATCH(ROWS($C$2:C3),'Work report'!$AA$2:$AA$1500,0)),INDEX('Work report'!$Q$2:$Q$1500,MATCH(ROWS($C$2:C3),'Work report'!$AA$2:$AA$1500,0))),"")) | H3: =IF($C3="","",IFERROR(INDEX('Work report'!$M$2:$M$1500,MATCH(ROWS($C$2:C3),'Work report'!$AA$2:$AA$1500,0)),"")) | I3: =IF($C3="","",IFERROR(INDEX('Work report'!$A$2:$A$1500,MATCH(ROWS($C$2:C3),'Work report'!$AA$2:$AA$1500,0)),"")) | J3: =IF($C3="","",IFERROR(INDEX('Work report'!$I$2:$I$1500,MATCH(ROWS($C$2:C3),'Work report'!$AA$2:$AA$1500,0)),"")) | O3: =IF($C3<>"",$C3,$K3) -> 0 | P3: =IF($D3<>"",$D3,$L3) -> 0 | Q3: =IF($C3<>"","System",IF($K3<>"","Manual",""))
A4: =IF($C4="","",IFERROR(INDEX('Work report'!$A$2:$A$1500,MATCH(ROWS($C$2:C4),'Work report'!$AA$2:$AA$1500,0)),"")) | B4: =IF($C4="","",Setup!$B$4) | C4: =IFERROR(INDEX('Work report'!$R$2:$R$1500,MATCH(ROWS($C$2:C4),'Work report'!$AA$2:$AA$1500,0)),"") | D4: =IFERROR(INDEX('Work report'!$S$2:$S$1500,MATCH(ROWS($D$2:D4),'Work report'!$AA$2:$AA$1500,0)),"") | E4: =IF($C4="","",IFERROR(INDEX('Work report'!$C$2:$C$1500,MATCH(ROWS($C$2:C4),'Work report'!$AA$2:$AA$1500,0)),"")) | F4: =IF($C4="","",IFERROR(INDEX('Work report'!$F$2:$F$1500,MATCH(ROWS($C$2:C4),'Work report'!$AA$2:$AA$1500,0)),"")) | G4: =IF($C4="","",IFERROR(HYPERLINK(INDEX('Work report'!$Q$2:$Q$1500,MATCH(ROWS($C$2:C4),'Work report'!$AA$2:$AA$1500,0)),INDEX('Work report'!$Q$2:$Q$1500,MATCH(ROWS($C$2:C4),'Work report'!$AA$2:$AA$1500,0))),"")) | H4: =IF($C4="","",IFERROR(INDEX('Work report'!$M$2:$M$1500,MATCH(ROWS($C$2:C4),'Work report'!$AA$2:$AA$1500,0)),"")) | I4: =IF($C4="","",IFERROR(INDEX('Work report'!$A$2:$A$1500,MATCH(ROWS($C$2:C4),'Work report'!$AA$2:$AA$1500,0)),"")) | J4: =IF($C4="","",IFERROR(INDEX('Work report'!$I$2:$I$1500,MATCH(ROWS($C$2:C4),'Work report'!$AA$2:$AA$1500,0)),"")) | O4: =IF($C4<>"",$C4,$K4) -> 0 | P4: =IF($D4<>"",$D4,$L4) -> 0 | Q4: =IF($C4<>"","System",IF($K4<>"","Manual",""))
A5: =IF($C5="","",IFERROR(INDEX('Work report'!$A$2:$A$1500,MATCH(ROWS($C$2:C5),'Work report'!$AA$2:$AA$1500,0)),"")) | B5: =IF($C5="","",Setup!$B$4) | C5: =IFERROR(INDEX('Work report'!$R$2:$R$1500,MATCH(ROWS($C$2:C5),'Work report'!$AA$2:$AA$1500,0)),"") | D5: =IFERROR(INDEX('Work report'!$S$2:$S$1500,MATCH(ROWS($D$2:D5),'Work report'!$AA$2:$AA$1500,0)),"") | E5: =IF($C5="","",IFERROR(INDEX('Work report'!$C$2:$C$1500,MATCH(ROWS($C$2:C5),'Work report'!$AA$2:$AA$1500,0)),"")) | F5: =IF($C5="","",IFERROR(INDEX('Work report'!$F$2:$F$1500,MATCH(ROWS($C$2:C5),'Work report'!$AA$2:$AA$1500,0)),"")) | G5: =IF($C5="","",IFERROR(HYPERLINK(INDEX('Work report'!$Q$2:$Q$1500,MATCH(ROWS($C$2:C5),'Work report'!$AA$2:$AA$1500,0)),INDEX('Work report'!$Q$2:$Q$1500,MATCH(ROWS($C$2:C5),'Work report'!$AA$2:$AA$1500,0))),"")) | H5: =IF($C5="","",IFERROR(INDEX('Work report'!$M$2:$M$1500,MATCH(ROWS($C$2:C5),'Work report'!$AA$2:$AA$1500,0)),"")) | I5: =IF($C5="","",IFERROR(INDEX('Work report'!$A$2:$A$1500,MATCH(ROWS($C$2:C5),'Work report'!$AA$2:$AA$1500,0)),"")) | J5: =IF($C5="","",IFERROR(INDEX('Work report'!$I$2:$I$1500,MATCH(ROWS($C$2:C5),'Work report'!$AA$2:$AA$1500,0)),"")) | O5: =IF($C5<>"",$C5,$K5) -> 0 | P5: =IF($D5<>"",$D5,$L5) -> 0 | Q5: =IF($C5<>"","System",IF($K5<>"","Manual",""))
A6: =IF($C6="","",IFERROR(INDEX('Work report'!$A$2:$A$1500,MATCH(ROWS($C$2:C6),'Work report'!$AA$2:$AA$1500,0)),"")) | B6: =IF($C6="","",Setup!$B$4) | C6: =IFERROR(INDEX('Work report'!$R$2:$R$1500,MATCH(ROWS($C$2:C6),'Work report'!$AA$2:$AA$1500,0)),"") | D6: =IFERROR(INDEX('Work report'!$S$2:$S$1500,MATCH(ROWS($D$2:D6),'Work report'!$AA$2:$AA$1500,0)),"") | E6: =IF($C6="","",IFERROR(INDEX('Work report'!$C$2:$C$1500,MATCH(ROWS($C$2:C6),'Work report'!$AA$2:$AA$1500,0)),"")) | F6: =IF($C6="","",IFERROR(INDEX('Work report'!$F$2:$F$1500,MATCH(ROWS($C$2:C6),'Work report'!$AA$2:$AA$1500,0)),"")) | G6: =IF($C6="","",IFERROR(HYPERLINK(INDEX('Work report'!$Q$2:$Q$1500,MATCH(ROWS($C$2:C6),'Work report'!$AA$2:$AA$1500,0)),INDEX('Work report'!$Q$2:$Q$1500,MATCH(ROWS($C$2:C6),'Work report'!$AA$2:$AA$1500,0))),"")) | H6: =IF($C6="","",IFERROR(INDEX('Work report'!$M$2:$M$1500,MATCH(ROWS($C$2:C6),'Work report'!$AA$2:$AA$1500,0)),"")) | I6: =IF($C6="","",IFERROR(INDEX('Work report'!$A$2:$A$1500,MATCH(ROWS($C$2:C6),'Work report'!$AA$2:$AA$1500,0)),"")) | J6: =IF($C6="","",IFERROR(INDEX('Work report'!$I$2:$I$1500,MATCH(ROWS($C$2:C6),'Work report'!$AA$2:$AA$1500,0)),"")) | O6: =IF($C6<>"",$C6,$K6) -> 0 | P6: =IF($D6<>"",$D6,$L6) -> 0 | Q6: =IF($C6<>"","System",IF($K6<>"","Manual",""))
A7: =IF($C7="","",IFERROR(INDEX('Work report'!$A$2:$A$1500,MATCH(ROWS($C$2:C7),'Work report'!$AA$2:$AA$1500,0)),"")) | B7: =IF($C7="","",Setup!$B$4) | C7: =IFERROR(INDEX('Work report'!$R$2:$R$1500,MATCH(ROWS($C$2:C7),'Work report'!$AA$2:$AA$1500,0)),"") | D7: =IFERROR(INDEX('Work report'!$S$2:$S$1500,MATCH(ROWS($D$2:D7),'Work report'!$AA$2:$AA$1500,0)),"") | E7: =IF($C7="","",IFERROR(INDEX('Work report'!$C$2:$C$1500,MATCH(ROWS($C$2:C7),'Work report'!$AA$2:$AA$1500,0)),"")) | F7: =IF($C7="","",IFERROR(INDEX('Work report'!$F$2:$F$1500,MATCH(ROWS($C$2:C7),'Work report'!$AA$2:$AA$1500,0)),"")) | G7: =IF($C7="","",IFERROR(HYPERLINK(INDEX('Work report'!$Q$2:$Q$1500,MATCH(ROWS($C$2:C7),'Work report'!$AA$2:$AA$1500,0)),INDEX('Work report'!$Q$2:$Q$1500,MATCH(ROWS($C$2:C7),'Work report'!$AA$2:$AA$1500,0))),"")) | H7: =IF($C7="","",IFERROR(INDEX('Work report'!$M$2:$M$1500,MATCH(ROWS($C$2:C7),'Work report'!$AA$2:$AA$1500,0)),"")) | I7: =IF($C7="","",IFERROR(INDEX('Work report'!$A$2:$A$1500,MATCH(ROWS($C$2:C7),'Work report'!$AA$2:$AA$1500,0)),"")) | J7: =IF($C7="","",IFERROR(INDEX('Work report'!$I$2:$I$1500,MATCH(ROWS($C$2:C7),'Work report'!$AA$2:$AA$1500,0)),"")) | O7: =IF($C7<>"",$C7,$K7) -> 0 | P7: =IF($D7<>"",$D7,$L7) -> 0 | Q7: =IF($C7<>"","System",IF($K7<>"","Manual",""))
A8: =IF($C8="","",IFERROR(INDEX('Work report'!$A$2:$A$1500,MATCH(ROWS($C$2:C8),'Work report'!$AA$2:$AA$1500,0)),"")) | B8: =IF($C8="","",Setup!$B$4) | C8: =IFERROR(INDEX('Work report'!$R$2:$R$1500,MATCH(ROWS($C$2:C8),'Work report'!$AA$2:$AA$1500,0)),"") | D8: =IFERROR(INDEX('Work report'!$S$2:$S$1500,MATCH(ROWS($D$2:D8),'Work report'!$AA$2:$AA$1500,0)),"") | E8: =IF($C8="","",IFERROR(INDEX('Work report'!$C$2:$C$1500,MATCH(ROWS($C$2:C8),'Work report'!$AA$2:$AA$1500,0)),"")) | F8: =IF($C8="","",IFERROR(INDEX('Work report'!$F$2:$F$1500,MATCH(ROWS($C$2:C8),'Work report'!$AA$2:$AA$1500,0)),"")) | G8: =IF($C8="","",IFERROR(HYPERLINK(INDEX('Work report'!$Q$2:$Q$1500,MATCH(ROWS($C$2:C8),'Work report'!$AA$2:$AA$1500,0)),INDEX('Work report'!$Q$2:$Q$1500,MATCH(ROWS($C$2:C8),'Work report'!$AA$2:$AA$1500,0))),"")) | H8: =IF($C8="","",IFERROR(INDEX('Work report'!$M$2:$M$1500,MATCH(ROWS($C$2:C8),'Work report'!$AA$2:$AA$1500,0)),"")) | I8: =IF($C8="","",IFERROR(INDEX('Work report'!$A$2:$A$1500,MATCH(ROWS($C$2:C8),'Work report'!$AA$2:$AA$1500,0)),"")) | J8: =IF($C8="","",IFERROR(INDEX('Work report'!$I$2:$I$1500,MATCH(ROWS($C$2:C8),'Work report'!$AA$2:$AA$1500,0)),"")) | O8: =IF($C8<>"",$C8,$K8) -> 0 | P8: =IF($D8<>"",$D8,$L8) -> 0 | Q8: =IF($C8<>"","System",IF($K8<>"","Manual",""))
A9: =IF($C9="","",IFERROR(INDEX('Work report'!$A$2:$A$1500,MATCH(ROWS($C$2:C9),'Work report'!$AA$2:$AA$1500,0)),"")) | B9: =IF($C9="","",Setup!$B$4) | C9: =IFERROR(INDEX('Work report'!$R$2:$R$1500,MATCH(ROWS($C$2:C9),'Work report'!$AA$2:$AA$1500,0)),"") | D9: =IFERROR(INDEX('Work report'!$S$2:$S$1500,MATCH(ROWS($D$2:D9),'Work report'!$AA$2:$AA$1500,0)),"") | E9: =IF($C9="","",IFERROR(INDEX('Work report'!$C$2:$C$1500,MATCH(ROWS($C$2:C9),'Work report'!$AA$2:$AA$1500,0)),"")) | F9: =IF($C9="","",IFERROR(INDEX('Work report'!$F$2:$F$1500,MATCH(ROWS($C$2:C9),'Work report'!$AA$2:$AA$1500,0)),"")) | G9: =IF($C9="","",IFERROR(HYPERLINK(INDEX('Work report'!$Q$2:$Q$1500,MATCH(ROWS($C$2:C9),'Work report'!$AA$2:$AA$1500,0)),INDEX('Work report'!$Q$2:$Q$1500,MATCH(ROWS($C$2:C9),'Work report'!$AA$2:$AA$1500,0))),"")) | H9: =IF($C9="","",IFERROR(INDEX('Work report'!$M$2:$M$1500,MATCH(ROWS($C$2:C9),'Work report'!$AA$2:$AA$1500,0)),"")) | I9: =IF($C9="","",IFERROR(INDEX('Work report'!$A$2:$A$1500,MATCH(ROWS($C$2:C9),'Work report'!$AA$2:$AA$1500,0)),"")) | J9: =IF($C9="","",IFERROR(INDEX('Work report'!$I$2:$I$1500,MATCH(ROWS($C$2:C9),'Work report'!$AA$2:$AA$1500,0)),"")) | O9: =IF($C9<>"",$C9,$K9) -> 0 | P9: =IF($D9<>"",$D9,$L9) -> 0 | Q9: =IF($C9<>"","System",IF($K9<>"","Manual",""))
A10: =IF($C10="","",IFERROR(INDEX('Work report'!$A$2:$A$1500,MATCH(ROWS($C$2:C10),'Work report'!$AA$2:$AA$1500,0)),"")) | B10: =IF($C10="","",Setup!$B$4) | C10: =IFERROR(INDEX('Work report'!$R$2:$R$1500,MATCH(ROWS($C$2:C10),'Work report'!$AA$2:$AA$1500,0)),"") | D10: =IFERROR(INDEX('Work report'!$S$2:$S$1500,MATCH(ROWS($D$2:D10),'Work report'!$AA$2:$AA$1500,0)),"") | E10: =IF($C10="","",IFERROR(INDEX('Work report'!$C$2:$C$1500,MATCH(ROWS($C$2:C10),'Work report'!$AA$2:$AA$1500,0)),"")) | F10: =IF($C10="","",IFERROR(INDEX('Work report'!$F$2:$F$1500,MATCH(ROWS($C$2:C10),'Work report'!$AA$2:$AA$1500,0)),"")) | G10: =IF($C10="","",IFERROR(HYPERLINK(INDEX('Work report'!$Q$2:$Q$1500,MATCH(ROWS($C$2:C10),'Work report'!$AA$2:$AA$1500,0)),INDEX('Work report'!$Q$2:$Q$1500,MATCH(ROWS($C$2:C10),'Work report'!$AA$2:$AA$1500,0))),"")) | H10: =IF($C10="","",IFERROR(INDEX('Work report'!$M$2:$M$1500,MATCH(ROWS($C$2:C10),'Work report'!$AA$2:$AA$1500,0)),"")) | I10: =IF($C10="","",IFERROR(INDEX('Work report'!$A$2:$A$1500,MATCH(ROWS($C$2:C10),'Work report'!$AA$2:$AA$1500,0)),"")) | J10: =IF($C10="","",IFERROR(INDEX('Work report'!$I$2:$I$1500,MATCH(ROWS($C$2:C10),'Work report'!$AA$2:$AA$1500,0)),"")) | O10: =IF($C10<>"",$C10,$K10) -> 0 | P10: =IF($D10<>"",$D10,$L10) -> 0 | Q10: =IF($C10<>"","System",IF($K10<>"","Manual",""))
A11: =IF($C11="","",IFERROR(INDEX('Work report'!$A$2:$A$1500,MATCH(ROWS($C$2:C11),'Work report'!$AA$2:$AA$1500,0)),"")) | B11: =IF($C11="","",Setup!$B$4) | C11: =IFERROR(INDEX('Work report'!$R$2:$R$1500,MATCH(ROWS($C$2:C11),'Work report'!$AA$2:$AA$1500,0)),"") | D11: =IFERROR(INDEX('Work report'!$S$2:$S$1500,MATCH(ROWS($D$2:D11),'Work report'!$AA$2:$AA$1500,0)),"") | E11: =IF($C11="","",IFERROR(INDEX('Work report'!$C$2:$C$1500,MATCH(ROWS($C$2:C11),'Work report'!$AA$2:$AA$1500,0)),"")) | F11: =IF($C11="","",IFERROR(INDEX('Work report'!$F$2:$F$1500,MATCH(ROWS($C$2:C11),'Work report'!$AA$2:$AA$1500,0)),"")) | G11: =IF($C11="","",IFERROR(HYPERLINK(INDEX('Work report'!$Q$2:$Q$1500,MATCH(ROWS($C$2:C11),'Work report'!$AA$2:$AA$1500,0)),INDEX('Work report'!$Q$2:$Q$1500,MATCH(ROWS($C$2:C11),'Work report'!$AA$2:$AA$1500,0))),"")) | H11: =IF($C11="","",IFERROR(INDEX('Work report'!$M$2:$M$1500,MATCH(ROWS($C$2:C11),'Work report'!$AA$2:$AA$1500,0)),"")) | I11: =IF($C11="","",IFERROR(INDEX('Work report'!$A$2:$A$1500,MATCH(ROWS($C$2:C11),'Work report'!$AA$2:$AA$1500,0)),"")) | J11: =IF($C11="","",IFERROR(INDEX('Work report'!$I$2:$I$1500,MATCH(ROWS($C$2:C11),'Work report'!$AA$2:$AA$1500,0)),"")) | O11: =IF($C11<>"",$C11,$K11) -> 0 | P11: =IF($D11<>"",$D11,$L11) -> 0 | Q11: =IF($C11<>"","System",IF($K11<>"","Manual",""))
A12: =IF($C12="","",IFERROR(INDEX('Work report'!$A$2:$A$1500,MATCH(ROWS($C$2:C12),'Work report'!$AA$2:$AA$1500,0)),"")) | B12: =IF($C12="","",Setup!$B$4) | C12: =IFERROR(INDEX('Work report'!$R$2:$R$1500,MATCH(ROWS($C$2:C12),'Work report'!$AA$2:$AA$1500,0)),"") | D12: =IFERROR(INDEX('Work report'!$S$2:$S$1500,MATCH(ROWS($D$2:D12),'Work report'!$AA$2:$AA$1500,0)),"") | E12: =IF($C12="","",IFERROR(INDEX('Work report'!$C$2:$C$1500,MATCH(ROWS($C$2:C12),'Work report'!$AA$2:$AA$1500,0)),"")) | F12: =IF($C12="","",IFERROR(INDEX('Work report'!$F$2:$F$1500,MATCH(ROWS($C$2:C12),'Work report'!$AA$2:$AA$1500,0)),"")) | G12: =IF($C12="","",IFERROR(HYPERLINK(INDEX('Work report'!$Q$2:$Q$1500,MATCH(ROWS($C$2:C12),'Work report'!$AA$2:$AA$1500,0)),INDEX('Work report'!$Q$2:$Q$1500,MATCH(ROWS($C$2:C12),'Work report'!$AA$2:$AA$1500,0))),"")) | H12: =IF($C12="","",IFERROR(INDEX('Work report'!$M$2:$M$1500,MATCH(ROWS($C$2:C12),'Work report'!$AA$2:$AA$1500,0)),"")) | I12: =IF($C12="","",IFERROR(INDEX('Work report'!$A$2:$A$1500,MATCH(ROWS($C$2:C12),'Work report'!$AA$2:$AA$1500,0)),"")) | J12: =IF($C12="","",IFERROR(INDEX('Work report'!$I$2:$I$1500,MATCH(ROWS($C$2:C12),'Work report'!$AA$2:$AA$1500,0)),"")) | O12: =IF($C12<>"",$C12,$K12) -> 0 | P12: =IF($D12<>"",$D12,$L12) -> 0 | Q12: =IF($C12<>"","System",IF($K12<>"","Manual",""))
A13: =IF($C13="","",IFERROR(INDEX('Work report'!$A$2:$A$1500,MATCH(ROWS($C$2:C13),'Work report'!$AA$2:$AA$1500,0)),"")) | B13: =IF($C13="","",Setup!$B$4) | C13: =IFERROR(INDEX('Work report'!$R$2:$R$1500,MATCH(ROWS($C$2:C13),'Work report'!$AA$2:$AA$1500,0)),"") | D13: =IFERROR(INDEX('Work report'!$S$2:$S$1500,MATCH(ROWS($D$2:D13),'Work report'!$AA$2:$AA$1500,0)),"") | E13: =IF($C13="","",IFERROR(INDEX('Work report'!$C$2:$C$1500,MATCH(ROWS($C$2:C13),'Work report'!$AA$2:$AA$1500,0)),"")) | F13: =IF($C13="","",IFERROR(INDEX('Work report'!$F$2:$F$1500,MATCH(ROWS($C$2:C13),'Work report'!$AA$2:$AA$1500,0)),"")) | G13: =IF($C13="","",IFERROR(HYPERLINK(INDEX('Work report'!$Q$2:$Q$1500,MATCH(ROWS($C$2:C13),'Work report'!$AA$2:$AA$1500,0)),INDEX('Work report'!$Q$2:$Q$1500,MATCH(ROWS($C$2:C13),'Work report'!$AA$2:$AA$1500,0))),"")) | H13: =IF($C13="","",IFERROR(INDEX('Work report'!$M$2:$M$1500,MATCH(ROWS($C$2:C13),'Work report'!$AA$2:$AA$1500,0)),"")) | I13: =IF($C13="","",IFERROR(INDEX('Work report'!$A$2:$A$1500,MATCH(ROWS($C$2:C13),'Work report'!$AA$2:$AA$1500,0)),"")) | J13: =IF($C13="","",IFERROR(INDEX('Work report'!$I$2:$I$1500,MATCH(ROWS($C$2:C13),'Work report'!$AA$2:$AA$1500,0)),"")) | O13: =IF($C13<>"",$C13,$K13) -> 0 | P13: =IF($D13<>"",$D13,$L13) -> 0 | Q13: =IF($C13<>"","System",IF($K13<>"","Manual",""))
... A37: =IF($C37="","",IFERROR(INDEX('Work report'!$A$2:$A$1500,MATCH(ROWS($C$2:C37),'Work report'!$AA$2:$AA$1500,0)),"")) | B37: =IF($C37="","",Setup!$B$4) | C37: =IFERROR(INDEX('Work report'!$R$2:$R$1500,MATCH(ROWS($C$2:C37),'Work report'!$AA$2:$AA$1500,0)),"") | D37: =IFERROR(INDEX('Work report'!$S$2:$S$1500,MATCH(ROWS($D$2:D37),'Work report'!$AA$2:$AA$1500,0)),"") | E37: =IF($C37="","",IFERROR(INDEX('Work report'!$C$2:$C$1500,MATCH(ROWS($C$2:C37),'Work report'!$AA$2:$AA$1500,0)),"")) | F37: =IF($C37="","",IFERROR(INDEX('Work report'!$F$2:$F$1500,MATCH(ROWS($C$2:C37),'Work report'!$AA$2:$AA$1500,0)),"")) | G37: =IF($C37="","",IFERROR(HYPERLINK(INDEX('Work report'!$Q$2:$Q$1500,MATCH(ROWS($C$2:C37),'Work report'!$AA$2:$AA$1500,0)),INDEX('Work report'!$Q$2:$Q$1500,MATCH(ROWS($C$2:C37),'Work report'!$AA$2:$AA$1500,0))),"")) | H37: =IF($C37="","",IFERROR(INDEX('Work report'!$M$2:$M$1500,MATCH(ROWS($C$2:C37),'Work report'!$AA$2:$AA$1500,0)),"")) | I37: =IF($C37="","",IFERROR(INDEX('Work report'!$A$2:$A$1500,MATCH(ROWS($C$2:C37),'Work report'!$AA$2:$AA$1500,0)),"")) | J37: =IF($C37="","",IFERROR(INDEX('Work report'!$I$2:$I$1500,MATCH(ROWS($C$2:C37),'Work report'!$AA$2:$AA$1500,0)),"")) | O37: =IF($C37<>"",$C37,$K37) -> 0 | P37: =IF($D37<>"",$D37,$L37) -> 0 | Q37: =IF($C37<>"","System",IF($K37<>"","Manual",""))
A38: =IF($C38="","",IFERROR(INDEX('Work report'!$A$2:$A$1500,MATCH(ROWS($C$2:C38),'Work report'!$AA$2:$AA$1500,0)),"")) | B38: =IF($C38="","",Setup!$B$4) | C38: =IFERROR(INDEX('Work report'!$R$2:$R$1500,MATCH(ROWS($C$2:C38),'Work report'!$AA$2:$AA$1500,0)),"") | D38: =IFERROR(INDEX('Work report'!$S$2:$S$1500,MATCH(ROWS($D$2:D38),'Work report'!$AA$2:$AA$1500,0)),"") | E38: =IF($C38="","",IFERROR(INDEX('Work report'!$C$2:$C$1500,MATCH(ROWS($C$2:C38),'Work report'!$AA$2:$AA$1500,0)),"")) | F38: =IF($C38="","",IFERROR(INDEX('Work report'!$F$2:$F$1500,MATCH(ROWS($C$2:C38),'Work report'!$AA$2:$AA$1500,0)),"")) | G38: =IF($C38="","",IFERROR(HYPERLINK(INDEX('Work report'!$Q$2:$Q$1500,MATCH(ROWS($C$2:C38),'Work report'!$AA$2:$AA$1500,0)),INDEX('Work report'!$Q$2:$Q$1500,MATCH(ROWS($C$2:C38),'Work report'!$AA$2:$AA$1500,0))),"")) | H38: =IF($C38="","",IFERROR(INDEX('Work report'!$M$2:$M$1500,MATCH(ROWS($C$2:C38),'Work report'!$AA$2:$AA$1500,0)),"")) | I38: =IF($C38="","",IFERROR(INDEX('Work report'!$A$2:$A$1500,MATCH(ROWS($C$2:C38),'Work report'!$AA$2:$AA$1500,0)),"")) | J38: =IF($C38="","",IFERROR(INDEX('Work report'!$I$2:$I$1500,MATCH(ROWS($C$2:C38),'Work report'!$AA$2:$AA$1500,0)),"")) | O38: =IF($C38<>"",$C38,$K38) -> 0 | P38: =IF($D38<>"",$D38,$L38) -> 0 | Q38: =IF($C2<>"","System",IF($K2<>"","Manual",""))
A39: =IF($C39="","",IFERROR(INDEX('Work report'!$A$2:$A$1500,MATCH(ROWS($C$2:C39),'Work report'!$AA$2:$AA$1500,0)),"")) | B39: =IF($C39="","",Setup!$B$4) | C39: =IFERROR(INDEX('Work report'!$R$2:$R$1500,MATCH(ROWS($C$2:C39),'Work report'!$AA$2:$AA$1500,0)),"") | D39: =IFERROR(INDEX('Work report'!$S$2:$S$1500,MATCH(ROWS($D$2:D39),'Work report'!$AA$2:$AA$1500,0)),"") | E39: =IF($C39="","",IFERROR(INDEX('Work report'!$C$2:$C$1500,MATCH(ROWS($C$2:C39),'Work report'!$AA$2:$AA$1500,0)),"")) | F39: =IF($C39="","",IFERROR(INDEX('Work report'!$F$2:$F$1500,MATCH(ROWS($C$2:C39),'Work report'!$AA$2:$AA$1500,0)),"")) | G39: =IF($C39="","",IFERROR(HYPERLINK(INDEX('Work report'!$Q$2:$Q$1500,MATCH(ROWS($C$2:C39),'Work report'!$AA$2:$AA$1500,0)),INDEX('Work report'!$Q$2:$Q$1500,MATCH(ROWS($C$2:C39),'Work report'!$AA$2:$AA$1500,0))),"")) | H39: =IF($C39="","",IFERROR(INDEX('Work report'!$M$2:$M$1500,MATCH(ROWS($C$2:C39),'Work report'!$AA$2:$AA$1500,0)),"")) | I39: =IF($C39="","",IFERROR(INDEX('Work report'!$A$2:$A$1500,MATCH(ROWS($C$2:C39),'Work report'!$AA$2:$AA$1500,0)),"")) | J39: =IF($C39="","",IFERROR(INDEX('Work report'!$I$2:$I$1500,MATCH(ROWS($C$2:C39),'Work report'!$AA$2:$AA$1500,0)),"")) | O39: =IF($C39<>"",$C39,$K39) -> 0 | P39: =IF($D39<>"",$D39,$L39) -> 0 | Q39: =IF($C3<>"","System",IF($K3<>"","Manual",""))
A40: =IF($C40="","",IFERROR(INDEX('Work report'!$A$2:$A$1500,MATCH(ROWS($C$2:C40),'Work report'!$AA$2:$AA$1500,0)),"")) | B40: =IF($C40="","",Setup!$B$4) | C40: =IFERROR(INDEX('Work report'!$R$2:$R$1500,MATCH(ROWS($C$2:C40),'Work report'!$AA$2:$AA$1500,0)),"") | D40: =IFERROR(INDEX('Work report'!$S$2:$S$1500,MATCH(ROWS($D$2:D40),'Work report'!$AA$2:$AA$1500,0)),"") | E40: =IF($C40="","",IFERROR(INDEX('Work report'!$C$2:$C$1500,MATCH(ROWS($C$2:C40),'Work report'!$AA$2:$AA$1500,0)),"")) | F40: =IF($C40="","",IFERROR(INDEX('Work report'!$F$2:$F$1500,MATCH(ROWS($C$2:C40),'Work report'!$AA$2:$AA$1500,0)),"")) | G40: =IF($C40="","",IFERROR(HYPERLINK(INDEX('Work report'!$Q$2:$Q$1500,MATCH(ROWS($C$2:C40),'Work report'!$AA$2:$AA$1500,0)),INDEX('Work report'!$Q$2:$Q$1500,MATCH(ROWS($C$2:C40),'Work report'!$AA$2:$AA$1500,0))),"")) | H40: =IF($C40="","",IFERROR(INDEX('Work report'!$M$2:$M$1500,MATCH(ROWS($C$2:C40),'Work report'!$AA$2:$AA$1500,0)),"")) | I40: =IF($C40="","",IFERROR(INDEX('Work report'!$A$2:$A$1500,MATCH(ROWS($C$2:C40),'Work report'!$AA$2:$AA$1500,0)),"")) | J40: =IF($C40="","",IFERROR(INDEX('Work report'!$I$2:$I$1500,MATCH(ROWS($C$2:C40),'Work report'!$AA$2:$AA$1500,0)),"")) | O40: =IF($C40<>"",$C40,$K40) -> 0 | P40: =IF($D40<>"",$D40,$L40) -> 0 | Q40: =IF($C4<>"","System",IF($K4<>"","Manual",""))
A41: =IF($C41="","",IFERROR(INDEX('Work report'!$A$2:$A$1500,MATCH(ROWS($C$2:C41),'Work report'!$AA$2:$AA$1500,0)),"")) | B41: =IF($C41="","",Setup!$B$4) | C41: =IFERROR(INDEX('Work report'!$R$2:$R$1500,MATCH(ROWS($C$2:C41),'Work report'!$AA$2:$AA$1500,0)),"") | D41: =IFERROR(INDEX('Work report'!$S$2:$S$1500,MATCH(ROWS($D$2:D41),'Work report'!$AA$2:$AA$1500,0)),"") | E41: =IF($C41="","",IFERROR(INDEX('Work report'!$C$2:$C$1500,MATCH(ROWS($C$2:C41),'Work report'!$AA$2:$AA$1500,0)),"")) | F41: =IF($C41="","",IFERROR(INDEX('Work report'!$F$2:$F$1500,MATCH(ROWS($C$2:C41),'Work report'!$AA$2:$AA$1500,0)),"")) | G41: =IF($C41="","",IFERROR(HYPERLINK(INDEX('Work report'!$Q$2:$Q$1500,MATCH(ROWS($C$2:C41),'Work report'!$AA$2:$AA$1500,0)),INDEX('Work report'!$Q$2:$Q$1500,MATCH(ROWS($C$2:C41),'Work report'!$AA$2:$AA$1500,0))),"")) | H41: =IF($C41="","",IFERROR(INDEX('Work report'!$M$2:$M$1500,MATCH(ROWS($C$2:C41),'Work report'!$AA$2:$AA$1500,0)),"")) | I41: =IF($C41="","",IFERROR(INDEX('Work report'!$A$2:$A$1500,MATCH(ROWS($C$2:C41),'Work report'!$AA$2:$AA$1500,0)),"")) | J41: =IF($C41="","",IFERROR(INDEX('Work report'!$I$2:$I$1500,MATCH(ROWS($C$2:C41),'Work report'!$AA$2:$AA$1500,0)),"")) | O41: =IF($C41<>"",$C41,$K41) -> 0 | P41: =IF($D41<>"",$D41,$L41) -> 0 | Q41: =IF($C5<>"","System",IF($K5<>"","Manual",""))
A42: =IF($C42="","",IFERROR(INDEX('Work report'!$A$2:$A$1500,MATCH(ROWS($C$2:C42),'Work report'!$AA$2:$AA$1500,0)),"")) | B42: =IF($C42="","",Setup!$B$4) | C42: =IFERROR(INDEX('Work report'!$R$2:$R$1500,MATCH(ROWS($C$2:C42),'Work report'!$AA$2:$AA$1500,0)),"") | D42: =IFERROR(INDEX('Work report'!$S$2:$S$1500,MATCH(ROWS($D$2:D42),'Work report'!$AA$2:$AA$1500,0)),"") | E42: =IF($C42="","",IFERROR(INDEX('Work report'!$C$2:$C$1500,MATCH(ROWS($C$2:C42),'Work report'!$AA$2:$AA$1500,0)),"")) | F42: =IF($C42="","",IFERROR(INDEX('Work report'!$F$2:$F$1500,MATCH(ROWS($C$2:C42),'Work report'!$AA$2:$AA$1500,0)),"")) | G42: =IF($C42="","",IFERROR(HYPERLINK(INDEX('Work report'!$Q$2:$Q$1500,MATCH(ROWS($C$2:C42),'Work report'!$AA$2:$AA$1500,0)),INDEX('Work report'!$Q$2:$Q$1500,MATCH(ROWS($C$2:C42),'Work report'!$AA$2:$AA$1500,0))),"")) | H42: =IF($C42="","",IFERROR(INDEX('Work report'!$M$2:$M$1500,MATCH(ROWS($C$2:C42),'Work report'!$AA$2:$AA$1500,0)),"")) | I42: =IF($C42="","",IFERROR(INDEX('Work report'!$A$2:$A$1500,MATCH(ROWS($C$2:C42),'Work report'!$AA$2:$AA$1500,0)),"")) | J42: =IF($C42="","",IFERROR(INDEX('Work report'!$I$2:$I$1500,MATCH(ROWS($C$2:C42),'Work report'!$AA$2:$AA$1500,0)),"")) | O42: =IF($C42<>"",$C42,$K42) -> 0 | P42: =IF($D42<>"",$D42,$L42) -> 0 | Q42: =IF($C6<>"","System",IF($K6<>"","Manual",""))
A43: =IF($C43="","",IFERROR(INDEX('Work report'!$A$2:$A$1500,MATCH(ROWS($C$2:C43),'Work report'!$AA$2:$AA$1500,0)),"")) | B43: =IF($C43="","",Setup!$B$4) | C43: =IFERROR(INDEX('Work report'!$R$2:$R$1500,MATCH(ROWS($C$2:C43),'Work report'!$AA$2:$AA$1500,0)),"") | D43: =IFERROR(INDEX('Work report'!$S$2:$S$1500,MATCH(ROWS($D$2:D43),'Work report'!$AA$2:$AA$1500,0)),"") | E43: =IF($C43="","",IFERROR(INDEX('Work report'!$C$2:$C$1500,MATCH(ROWS($C$2:C43),'Work report'!$AA$2:$AA$1500,0)),"")) | F43: =IF($C43="","",IFERROR(INDEX('Work report'!$F$2:$F$1500,MATCH(ROWS($C$2:C43),'Work report'!$AA$2:$AA$1500,0)),"")) | G43: =IF($C43="","",IFERROR(HYPERLINK(INDEX('Work report'!$Q$2:$Q$1500,MATCH(ROWS($C$2:C43),'Work report'!$AA$2:$AA$1500,0)),INDEX('Work report'!$Q$2:$Q$1500,MATCH(ROWS($C$2:C43),'Work report'!$AA$2:$AA$1500,0))),"")) | H43: =IF($C43="","",IFERROR(INDEX('Work report'!$M$2:$M$1500,MATCH(ROWS($C$2:C43),'Work report'!$AA$2:$AA$1500,0)),"")) | I43: =IF($C43="","",IFERROR(INDEX('Work report'!$A$2:$A$1500,MATCH(ROWS($C$2:C43),'Work report'!$AA$2:$AA$1500,0)),"")) | J43: =IF($C43="","",IFERROR(INDEX('Work report'!$I$2:$I$1500,MATCH(ROWS($C$2:C43),'Work report'!$AA$2:$AA$1500,0)),"")) | O43: =IF($C43<>"",$C43,$K43) -> 0 | P43: =IF($D43<>"",$D43,$L43) -> 0 | Q43: =IF($C7<>"","System",IF($K7<>"","Manual",""))
A44: =IF($C44="","",IFERROR(INDEX('Work report'!$A$2:$A$1500,MATCH(ROWS($C$2:C44),'Work report'!$AA$2:$AA$1500,0)),"")) | B44: =IF($C44="","",Setup!$B$4) | C44: =IFERROR(INDEX('Work report'!$R$2:$R$1500,MATCH(ROWS($C$2:C44),'Work report'!$AA$2:$AA$1500,0)),"") | D44: =IFERROR(INDEX('Work report'!$S$2:$S$1500,MATCH(ROWS($D$2:D44),'Work report'!$AA$2:$AA$1500,0)),"") | E44: =IF($C44="","",IFERROR(INDEX('Work report'!$C$2:$C$1500,MATCH(ROWS($C$2:C44),'Work report'!$AA$2:$AA$1500,0)),"")) | F44: =IF($C44="","",IFERROR(INDEX('Work report'!$F$2:$F$1500,MATCH(ROWS($C$2:C44),'Work report'!$AA$2:$AA$1500,0)),"")) | G44: =IF($C44="","",IFERROR(HYPERLINK(INDEX('Work report'!$Q$2:$Q$1500,MATCH(ROWS($C$2:C44),'Work report'!$AA$2:$AA$1500,0)),INDEX('Work report'!$Q$2:$Q$1500,MATCH(ROWS($C$2:C44),'Work report'!$AA$2:$AA$1500,0))),"")) | H44: =IF($C44="","",IFERROR(INDEX('Work report'!$M$2:$M$1500,MATCH(ROWS($C$2:C44),'Work report'!$AA$2:$AA$1500,0)),"")) | I44: =IF($C44="","",IFERROR(INDEX('Work report'!$A$2:$A$1500,MATCH(ROWS($C$2:C44),'Work report'!$AA$2:$AA$1500,0)),"")) | J44: =IF($C44="","",IFERROR(INDEX('Work report'!$I$2:$I$1500,MATCH(ROWS($C$2:C44),'Work report'!$AA$2:$AA$1500,0)),"")) | O44: =IF($C44<>"",$C44,$K44) -> 0 | P44: =IF($D44<>"",$D44,$L44) -> 0 | Q44: =IF($C8<>"","System",IF($K8<>"","Manual",""))
A45: =IF($C45="","",IFERROR(INDEX('Work report'!$A$2:$A$1500,MATCH(ROWS($C$2:C45),'Work report'!$AA$2:$AA$1500,0)),"")) | B45: =IF($C45="","",Setup!$B$4) | C45: =IFERROR(INDEX('Work report'!$R$2:$R$1500,MATCH(ROWS($C$2:C45),'Work report'!$AA$2:$AA$1500,0)),"") | D45: =IFERROR(INDEX('Work report'!$S$2:$S$1500,MATCH(ROWS($D$2:D45),'Work report'!$AA$2:$AA$1500,0)),"") | E45: =IF($C45="","",IFERROR(INDEX('Work report'!$C$2:$C$1500,MATCH(ROWS($C$2:C45),'Work report'!$AA$2:$AA$1500,0)),"")) | F45: =IF($C45="","",IFERROR(INDEX('Work report'!$F$2:$F$1500,MATCH(ROWS($C$2:C45),'Work report'!$AA$2:$AA$1500,0)),"")) | G45: =IF($C45="","",IFERROR(HYPERLINK(INDEX('Work report'!$Q$2:$Q$1500,MATCH(ROWS($C$2:C45),'Work report'!$AA$2:$AA$1500,0)),INDEX('Work report'!$Q$2:$Q$1500,MATCH(ROWS($C$2:C45),'Work report'!$AA$2:$AA$1500,0))),"")) | H45: =IF($C45="","",IFERROR(INDEX('Work report'!$M$2:$M$1500,MATCH(ROWS($C$2:C45),'Work report'!$AA$2:$AA$1500,0)),"")) | I45: =IF($C45="","",IFERROR(INDEX('Work report'!$A$2:$A$1500,MATCH(ROWS($C$2:C45),'Work report'!$AA$2:$AA$1500,0)),"")) | J45: =IF($C45="","",IFERROR(INDEX('Work report'!$I$2:$I$1500,MATCH(ROWS($C$2:C45),'Work report'!$AA$2:$AA$1500,0)),"")) | O45: =IF($C45<>"",$C45,$K45) -> 0 | P45: =IF($D45<>"",$D45,$L45) -> 0 | Q45: =IF($C9<>"","System",IF($K9<>"","Manual",""))
A46: =IF($C46="","",IFERROR(INDEX('Work report'!$A$2:$A$1500,MATCH(ROWS($C$2:C46),'Work report'!$AA$2:$AA$1500,0)),"")) | B46: =IF($C46="","",Setup!$B$4) | C46: =IFERROR(INDEX('Work report'!$R$2:$R$1500,MATCH(ROWS($C$2:C46),'Work report'!$AA$2:$AA$1500,0)),"") | D46: =IFERROR(INDEX('Work report'!$S$2:$S$1500,MATCH(ROWS($D$2:D46),'Work report'!$AA$2:$AA$1500,0)),"") | E46: =IF($C46="","",IFERROR(INDEX('Work report'!$C$2:$C$1500,MATCH(ROWS($C$2:C46),'Work report'!$AA$2:$AA$1500,0)),"")) | F46: =IF($C46="","",IFERROR(INDEX('Work report'!$F$2:$F$1500,MATCH(ROWS($C$2:C46),'Work report'!$AA$2:$AA$1500,0)),"")) | G46: =IF($C46="","",IFERROR(HYPERLINK(INDEX('Work report'!$Q$2:$Q$1500,MATCH(ROWS($C$2:C46),'Work report'!$AA$2:$AA$1500,0)),INDEX('Work report'!$Q$2:$Q$1500,MATCH(ROWS($C$2:C46),'Work report'!$AA$2:$AA$1500,0))),"")) | H46: =IF($C46="","",IFERROR(INDEX('Work report'!$M$2:$M$1500,MATCH(ROWS($C$2:C46),'Work report'!$AA$2:$AA$1500,0)),"")) | I46: =IF($C46="","",IFERROR(INDEX('Work report'!$A$2:$A$1500,MATCH(ROWS($C$2:C46),'Work report'!$AA$2:$AA$1500,0)),"")) | J46: =IF($C46="","",IFERROR(INDEX('Work report'!$I$2:$I$1500,MATCH(ROWS($C$2:C46),'Work report'!$AA$2:$AA$1500,0)),"")) | O46: =IF($C46<>"",$C46,$K46) -> 0 | P46: =IF($D46<>"",$D46,$L46) -> 0 | Q46: =IF($C10<>"","System",IF($K10<>"","Manual",""))
A47: =IF($C47="","",IFERROR(INDEX('Work report'!$A$2:$A$1500,MATCH(ROWS($C$2:C47),'Work report'!$AA$2:$AA$1500,0)),"")) | B47: =IF($C47="","",Setup!$B$4) | C47: =IFERROR(INDEX('Work report'!$R$2:$R$1500,MATCH(ROWS($C$2:C47),'Work report'!$AA$2:$AA$1500,0)),"") | D47: =IFERROR(INDEX('Work report'!$S$2:$S$1500,MATCH(ROWS($D$2:D47),'Work report'!$AA$2:$AA$1500,0)),"") | E47: =IF($C47="","",IFERROR(INDEX('Work report'!$C$2:$C$1500,MATCH(ROWS($C$2:C47),'Work report'!$AA$2:$AA$1500,0)),"")) | F47: =IF($C47="","",IFERROR(INDEX('Work report'!$F$2:$F$1500,MATCH(ROWS($C$2:C47),'Work report'!$AA$2:$AA$1500,0)),"")) | G47: =IF($C47="","",IFERROR(HYPERLINK(INDEX('Work report'!$Q$2:$Q$1500,MATCH(ROWS($C$2:C47),'Work report'!$AA$2:$AA$1500,0)),INDEX('Work report'!$Q$2:$Q$1500,MATCH(ROWS($C$2:C47),'Work report'!$AA$2:$AA$1500,0))),"")) | H47: =IF($C47="","",IFERROR(INDEX('Work report'!$M$2:$M$1500,MATCH(ROWS($C$2:C47),'Work report'!$AA$2:$AA$1500,0)),"")) | I47: =IF($C47="","",IFERROR(INDEX('Work report'!$A$2:$A$1500,MATCH(ROWS($C$2:C47),'Work report'!$AA$2:$AA$1500,0)),"")) | J47: =IF($C47="","",IFERROR(INDEX('Work report'!$I$2:$I$1500,MATCH(ROWS($C$2:C47),'Work report'!$AA$2:$AA$1500,0)),"")) | O47: =IF($C47<>"",$C47,$K47) -> 0 | P47: =IF($D47<>"",$D47,$L47) -> 0 | Q47: =IF($C11<>"","System",IF($K11<>"","Manual",""))
A48: =IF($C48="","",IFERROR(INDEX('Work report'!$A$2:$A$1500,MATCH(ROWS($C$2:C48),'Work report'!$AA$2:$AA$1500,0)),"")) | B48: =IF($C48="","",Setup!$B$4) | C48: =IFERROR(INDEX('Work report'!$R$2:$R$1500,MATCH(ROWS($C$2:C48),'Work report'!$AA$2:$AA$1500,0)),"") | D48: =IFERROR(INDEX('Work report'!$S$2:$S$1500,MATCH(ROWS($D$2:D48),'Work report'!$AA$2:$AA$1500,0)),"") | E48: =IF($C48="","",IFERROR(INDEX('Work report'!$C$2:$C$1500,MATCH(ROWS($C$2:C48),'Work report'!$AA$2:$AA$1500,0)),"")) | F48: =IF($C48="","",IFERROR(INDEX('Work report'!$F$2:$F$1500,MATCH(ROWS($C$2:C48),'Work report'!$AA$2:$AA$1500,0)),"")) | G48: =IF($C48="","",IFERROR(HYPERLINK(INDEX('Work report'!$Q$2:$Q$1500,MATCH(ROWS($C$2:C48),'Work report'!$AA$2:$AA$1500,0)),INDEX('Work report'!$Q$2:$Q$1500,MATCH(ROWS($C$2:C48),'Work report'!$AA$2:$AA$1500,0))),"")) | H48: =IF($C48="","",IFERROR(INDEX('Work report'!$M$2:$M$1500,MATCH(ROWS($C$2:C48),'Work report'!$AA$2:$AA$1500,0)),"")) | I48: =IF($C48="","",IFERROR(INDEX('Work report'!$A$2:$A$1500,MATCH(ROWS($C$2:C48),'Work report'!$AA$2:$AA$1500,0)),"")) | J48: =IF($C48="","",IFERROR(INDEX('Work report'!$I$2:$I$1500,MATCH(ROWS($C$2:C48),'Work report'!$AA$2:$AA$1500,0)),"")) | O48: =IF($C48<>"",$C48,$K48) -> 0 | P48: =IF($D48<>"",$D48,$L48) -> 0 | Q48: =IF($C12<>"","System",IF($K12<>"","Manual",""))
A49: =IF($C49="","",IFERROR(INDEX('Work report'!$A$2:$A$1500,MATCH(ROWS($C$2:C49),'Work report'!$AA$2:$AA$1500,0)),"")) | B49: =IF($C49="","",Setup!$B$4) | C49: =IFERROR(INDEX('Work report'!$R$2:$R$1500,MATCH(ROWS($C$2:C49),'Work report'!$AA$2:$AA$1500,0)),"") | D49: =IFERROR(INDEX('Work report'!$S$2:$S$1500,MATCH(ROWS($D$2:D49),'Work report'!$AA$2:$AA$1500,0)),"") | E49: =IF($C49="","",IFERROR(INDEX('Work report'!$C$2:$C$1500,MATCH(ROWS($C$2:C49),'Work report'!$AA$2:$AA$1500,0)),"")) | F49: =IF($C49="","",IFERROR(INDEX('Work report'!$F$2:$F$1500,MATCH(ROWS($C$2:C49),'Work report'!$AA$2:$AA$1500,0)),"")) | G49: =IF($C49="","",IFERROR(HYPERLINK(INDEX('Work report'!$Q$2:$Q$1500,MATCH(ROWS($C$2:C49),'Work report'!$AA$2:$AA$1500,0)),INDEX('Work report'!$Q$2:$Q$1500,MATCH(ROWS($C$2:C49),'Work report'!$AA$2:$AA$1500,0))),"")) | H49: =IF($C49="","",IFERROR(INDEX('Work report'!$M$2:$M$1500,MATCH(ROWS($C$2:C49),'Work report'!$AA$2:$AA$1500,0)),"")) | I49: =IF($C49="","",IFERROR(INDEX('Work report'!$A$2:$A$1500,MATCH(ROWS($C$2:C49),'Work report'!$AA$2:$AA$1500,0)),"")) | J49: =IF($C49="","",IFERROR(INDEX('Work report'!$I$2:$I$1500,MATCH(ROWS($C$2:C49),'Work report'!$AA$2:$AA$1500,0)),"")) | O49: =IF($C49<>"",$C49,$K49) -> 0 | P49: =IF($D49<>"",$D49,$L49) -> 0 | Q49: =IF($C13<>"","System",IF($K13<>"","Manual",""))
... A1001: =IF($C1001="","",IFERROR(INDEX('Work report'!$A$2:$A$1500,MATCH(ROWS($C$2:C1001),'Work report'!$AA$2:$AA$1500,0)),"")) | B1001: =IF($C1001="","",Setup!$B$4) | C1001: =IFERROR(INDEX('Work report'!$R$2:$R$1500,MATCH(ROWS($C$2:C1001),'Work report'!$AA$2:$AA$1500,0)),"") | D1001: =IFERROR(INDEX('Work report'!$S$2:$S$1500,MATCH(ROWS($D$2:D1001),'Work report'!$AA$2:$AA$1500,0)),"") | E1001: =IF($C1001="","",IFERROR(INDEX('Work report'!$C$2:$C$1500,MATCH(ROWS($C$2:C1001),'Work report'!$AA$2:$AA$1500,0)),"")) | F1001: =IF($C1001="","",IFERROR(INDEX('Work report'!$F$2:$F$1500,MATCH(ROWS($C$2:C1001),'Work report'!$AA$2:$AA$1500,0)),"")) | G1001: =IF($C1001="","",IFERROR(HYPERLINK(INDEX('Work report'!$Q$2:$Q$1500,MATCH(ROWS($C$2:C1001),'Work report'!$AA$2:$AA$1500,0)),INDEX('Work report'!$Q$2:$Q$1500,MATCH(ROWS($C$2:C1001),'Work report'!$AA$2:$AA$1500,0))),"")) | H1001: =IF($C1001="","",IFERROR(INDEX('Work report'!$M$2:$M$1500,MATCH(ROWS($C$2:C1001),'Work report'!$AA$2:$AA$1500,0)),"")) | I1001: =IF($C1001="","",IFERROR(INDEX('Work report'!$A$2:$A$1500,MATCH(ROWS($C$2:C1001),'Work report'!$AA$2:$AA$1500,0)),"")) | J1001: =IF($C1001="","",IFERROR(INDEX('Work report'!$I$2:$I$1500,MATCH(ROWS($C$2:C1001),'Work report'!$AA$2:$AA$1500,0)),"")) | O1001: =IF($C1001<>"",$C1001,$K1001) -> 0 | P1001: =IF($D1001<>"",$D1001,$L1001) -> 0 | Q1001: =IF($C965<>"","System",IF($K965<>"","Manual",""))

Sheet Missing tasks
A1: Date | B1: Employee | C1: Task name | D1: Description | E1: Quantity | F1: Time allotted for the task (min) | G1: Video link (Google Drive) | H1: Video duration (min) | I1: Date recorded | J1: Approved time + Bonus time
B12: =IF($C12="","",Setup!$B$4)
B13: =IF($C13="","",Setup!$B$4)
B14: =IF($C14="","",Setup!$B$4)
B15: =IF($C15="","",Setup!$B$4)
B16: =IF($C16="","",Setup!$B$4)
B17: =IF($C17="","",Setup!$B$4)
B18: =IF($C18="","",Setup!$B$4)
B19: =IF($C19="","",Setup!$B$4)
B20: =IF($C20="","",Setup!$B$4)
B21: =IF($C21="","",Setup!$B$4)
B22: =IF($C22="","",Setup!$B$4)
B23: =IF($C23="","",Setup!$B$4)
... B500: =IF($C500="","",Setup!$B$4)

Sheet Time check for tasks
A1: Date | B1: Employee | C1: Task ID | D1: Task name | E1: Current std time (min) | F1: Actual time (min) | G1: Proposed std time (min) | H1: Difference time | I1: Reason / Note | J1: Video link (Google Drive) | K1: Video duration (min) | L1: Time check type | M1: Status | N1: Reviewed by | O1: Decision note | P1: Approved time + Bonus time
B2: =IF($C2="","",Setup!$B$4) | D2: =IF($C2="","",_xlfn.XLOOKUP($C2,'Task library'!$A:$A,'Task library'!$B:$B,"")) | E2: =IF($C2="","",_xlfn.XLOOKUP($C2,'Task library'!$A:$A,'Task library'!$D:$D,"")) | H2: =IF(OR($C2="",$E2="",$G2=""),"",$E2-$G2) | L2: =IF(G2="","",IF(G2>E2,"Time check – higher",IF(G2<E2,"Time check – lower","")))
B3: =IF($C3="","",Setup!$B$4) | D3: =IF($C3="","",_xlfn.XLOOKUP($C3,'Task library'!$A:$A,'Task library'!$B:$B,"")) | E3: =IF($C3="","",_xlfn.XLOOKUP($C3,'Task library'!$A:$A,'Task library'!$D:$D,"")) | H3: =IF(OR($C3="",$E3="",$G3=""),"",$E3-$G3) | L3: =IF(G3="","",IF(G3>E3,"Time check – higher",IF(G3<E3,"Time check – lower","")))
B4: =IF($C4="","",Setup!$B$4) | D4: =IF($C4="","",_xlfn.XLOOKUP($C4,'Task library'!$A:$A,'Task library'!$B:$B,"")) | E4: =IF($C4="","",_xlfn.XLOOKUP($C4,'Task library'!$A:$A,'Task library'!$D:$D,"")) | H4: =IF(OR($C4="",$E4="",$G4=""),"",$E4-$G4) | L4: =IF(G4="","",IF(G4>E4,"Time check – higher",IF(G4<E4,"Time check – lower","")))
B5: =IF($C5="","",Setup!$B$4) | D5: =IF($C5="","",_xlfn.XLOOKUP($C5,'Task library'!$A:$A,'Task library'!$B:$B,"")) | E5: =IF($C5="","",_xlfn.XLOOKUP($C5,'Task library'!$A:$A,'Task library'!$D:$D,"")) | H5: =IF(OR($C5="",$E5="",$G5=""),"",$E5-$G5) | L5: =IF(G5="","",IF(G5>E5,"Time check – higher",IF(G5<E5,"Time check – lower","")))
B6: =IF($C6="","",Setup!$B$4) | D6: =IF($C6="","",_xlfn.XLOOKUP($C6,'Task library'!$A:$A,'Task library'!$B:$B,"")) | E6: =IF($C6="","",_xlfn.XLOOKUP($C6,'Task library'!$A:$A,'Task library'!$D:$D,"")) | H6: =IF(OR($C6="",$E6="",$G6=""),"",$E6-$G6) | L6: =IF(G6="","",IF(G6>E6,"Time check – higher",IF(G6<E6,"Time check – lower","")))
B7: =IF($C7="","",Setup!$B$4) | D7: =IF($C7="","",_xlfn.XLOOKUP($C7,'Task library'!$A:$A,'Task library'!$B:$B,"")) | E7: =IF($C7="","",_xlfn.XLOOKUP($C7,'Task library'!$A:$A,'Task library'!$D:$D,"")) | H7: =IF(OR($C7="",$E7="",$G7=""),"",$E7-$G7) | L7: =IF(G7="","",IF(G7>E7,"Time check – higher",IF(G7<E7,"Time check – lower","")))
B8: =IF($C8="","",Setup!$B$4) | D8: =IF($C8="","",_xlfn.XLOOKUP($C8,'Task library'!$A:$A,'Task library'!$B:$B,"")) | E8: =IF($C8="","",_xlfn.XLOOKUP($C8,'Task library'!$A:$A,'Task library'!$D:$D,"")) | H8: =IF(OR($C8="",$E8="",$G8=""),"",$E8-$G8) | L8: =IF(G8="","",IF(G8>E8,"Time check – higher",IF(G8<E8,"Time check – lower","")))
B9: =IF($C9="","",Setup!$B$4) | D9: =IF($C9="","",_xlfn.XLOOKUP($C9,'Task library'!$A:$A,'Task library'!$B:$B,"")) | E9: =IF($C9="","",_xlfn.XLOOKUP($C9,'Task library'!$A:$A,'Task library'!$D:$D,"")) | H9: =IF(OR($C9="",$E9="",$G9=""),"",$E9-$G9) | L9: =IF(G9="","",IF(G9>E9,"Time check – higher",IF(G9<E9,"Time check – lower","")))
B10: =IF($C10="","",Setup!$B$4) | D10: =IF($C10="","",_xlfn.XLOOKUP($C10,'Task library'!$A:$A,'Task library'!$B:$B,"")) | E10: =IF($C10="","",_xlfn.XLOOKUP($C10,'Task library'!$A:$A,'Task library'!$D:$D,"")) | H10: =IF(OR($C10="",$E10="",$G10=""),"",$E10-$G10) | L10: =IF(G10="","",IF(G10>E10,"Time check – higher",IF(G10<E10,"Time check – lower","")))
B11: =IF($C11="","",Setup!$B$4) | D11: =IF($C11="","",_xlfn.XLOOKUP($C11,'Task library'!$A:$A,'Task library'!$B:$B,"")) | E11: =IF($C11="","",_xlfn.XLOOKUP($C11,'Task library'!$A:$A,'Task library'!$D:$D,"")) | H11: =IF(OR($C11="",$E11="",$G11=""),"",$E11-$G11) | L11: =IF(G11="","",IF(G11>E11,"Time check – higher",IF(G11<E11,"Time check – lower","")))
B12: =IF($C12="","",Setup!$B$4) | D12: =IF($C12="","",_xlfn.XLOOKUP($C12,'Task library'!$A:$A,'Task library'!$B:$B,"")) | E12: =IF($C12="","",_xlfn.XLOOKUP($C12,'Task library'!$A:$A,'Task library'!$D:$D,"")) | H12: =IF(OR($C12="",$E12="",$G12=""),"",$E12-$G12) | L12: =IF(G12="","",IF(G12>E12,"Time check – higher",IF(G12<E12,"Time check – lower","")))
B13: =IF($C13="","",Setup!$B$4) | D13: =IF($C13="","",_xlfn.XLOOKUP($C13,'Task library'!$A:$A,'Task library'!$B:$B,"")) | E13: =IF($C13="","",_xlfn.XLOOKUP($C13,'Task library'!$A:$A,'Task library'!$D:$D,"")) | H13: =IF(OR($C13="",$E13="",$G13=""),"",$E13-$G13) | L13: =IF(G13="","",IF(G13>E13,"Time check – higher",IF(G13<E13,"Time check – lower","")))
... B494: =IF($C494="","",Setup!$B$4) | D494: =IF($C494="","",_xlfn.XLOOKUP($C494,'Task library'!$A:$A,'Task library'!$B:$B,"")) | E494: =IF($C494="","",_xlfn.XLOOKUP($C494,'Task library'!$A:$A,'Task library'!$D:$D,"")) | H494: =IF(OR($C494="",$E494="",$G494=""),"",$E494-$G494) | L494: =IF(G494="","",IF(G494>E494,"Time check – higher",IF(G494<E494,"Time check – lower","")))
H495: =IF(OR($C495="",$E495="",$G495=""),"",$E495-$G495) | L495: =IF(G495="","",IF(G495>E495,"Time check – higher",IF(G495<E495,"Time check – lower","")))
H496: =IF(OR($C496="",$E496="",$G496=""),"",$E496-$G496) | L496: =IF(G496="","",IF(G496>E496,"Time check – higher",IF(G496<E496,"Time check – lower","")))
H497: =IF(OR($C497="",$E497="",$G497=""),"",$E497-$G497) | L497: =IF(G497="","",IF(G497>E497,"Time check – higher",IF(G497<E497,"Time check – lower","")))
H498: =IF(OR($C498="",$E498="",$G498=""),"",$E498-$G498) | L498: =IF(G498="","",IF(G498>E498,"Time check – higher",IF(G498<E498,"Time check – lower","")))
H499: =IF(OR($C499="",$E499="",$G499=""),"",$E499-$G499) | L499: =IF(G499="","",IF(G499>E499,"Time check – higher",IF(G499<E499,"Time check – lower","")))
H500: =IF(OR($C500="",$E500="",$G500=""),"",$E500-$G500) | L500: =IF(G500="","",IF(G500>E500,"Time check – higher",IF(G500<E500,"Time check – lower","")))
H501: =IF(OR($C501="",$E501="",$G501=""),"",$E501-$G501) | L501: =IF(G501="","",IF(G501>E501,"Time check – higher",IF(G501<E501,"Time check – lower","")))
H502: =IF(OR($C502="",$E502="",$G502=""),"",$E502-$G502) | L502: =IF(G502="","",IF(G502>E502,"Time check – higher",IF(G502<E502,"Time check – lower","")))
H503: =IF(OR($C503="",$E503="",$G503=""),"",$E503-$G503) | L503: =IF(G503="","",IF(G503>E503,"Time check – higher",IF(G503<E503,"Time check – lower","")))
H504: =IF(OR($C504="",$E504="",$G504=""),"",$E504-$G504) | L504: =IF(G504="","",IF(G504>E504,"Time check – higher",IF(G504<E504,"Time check – lower","")))
H505: =IF(OR($C505="",$E505="",$G505=""),"",$E505-$G505) | L505: =IF(G505="","",IF(G505>E505,"Time check – higher",IF(G505<E505,"Time check – lower","")))
H506: =IF(OR($C506="",$E506="",$G506=""),"",$E506-$G506) | L506: =IF(G506="","",IF(G506>E506,"Time check – higher",IF(G506<E506,"Time check – lower","")))
... H1995: =IF(OR($C1995="",$E1995="",$G1995=""),"",$E1995-$G1995) | L1995: =IF(G1995="","",IF(G1995>E1995,"Time check – higher",IF(G1995<E1995,"Time check – lower","")))

Sheet Summary
A1: SUMMARY – Hours & Pay (Auto)
A3: Name | B3: =IFERROR(INDEX(Setup!$B:$B,MATCH("Employee name",Setup!$A:$A,0)),"") -> Đỗ Lan | D3: Pay type | E3: Hourly | G3: Email (Company) | H3: =IFERROR(INDEX(Setup!$B:$B,MATCH("Email (Company)",Setup!$A:$A,0)),"") -> lanit@hung-it-solutions.com | L3: Drive-link-1 | N3: =Setup!B32 -> https://drive.google.com/drive/folders/1gtU3qlcFI3aMBTz2z80ioSKTDObCLAxx?usp=drive_link | Y3: Total tasks | Z3: =COUNTIF('Work list'!$B$2:$B$1500,"WL-*") -> 0 | AA3: Not started | AB3: =COUNTIF('Work list'!$H$2:$H$1500,"Not started") -> 0
A4: From date | B4: =MIN('Work report'!$A:$A) -> 0 | D4: Hourly rate (/h) | E4: =IFERROR(INDEX(Setup!$B:$B,MATCH("Hourly rate (/h)",Setup!$A:$A,0)),"") -> 10 | G4: Email (Google) | H4: =IFERROR(INDEX(Setup!$B:$B,MATCH("Email (Google)",Setup!$A:$A,0)),"") -> lanit@hung-it-solutions.com | L4: Drive-link-2 | N4: =Setup!B33 -> https://drive.google.com/drive/folders/1mFbEs13a5YOUaSOAh2gZI0RXJ38N9y98?usp=drive_link | Y4: Completed | Z4: =COUNTIF('Work list'!$H$2:$H$1500,"Completed") -> 0 | AA4: In progress | AB4: =COUNTIF('Work list'!$H$2:$H$1500,"In progress") -> 0
A5: To date | B5: =MAX('Work report'!$A:$A) -> 0 | D5: Monthly salary | E5: =IFERROR(INDEX(Setup!$B:$B,MATCH("Monthly salary",Setup!$A:$A,0)),"") -> 0 | G5: Mobil (Company) | H5: =IFERROR(INDEX(Setup!$B:$B,MATCH("Mobil (Company)",Setup!$A:$A,0)),"") -> 0 | L5: Drive-link-3 | N5: =Setup!B34 -> Drive-link-3 | Y5: Open tasks | Z5: =COUNTIFS('Work list'!$B$2:$B$1500,"WL-*",'Work list'!$H$2:$H$1500,"<>Completed",'Work list'!$H$2:$H$1500,"<>Cancelled") -> 0 | AA5: Due in next 3 days | AB5: =COUNTIFS('Work list'!$B$2:$B$1500,"WL-*",'Work list'!$H$2:$H$1500,"<>Completed",'Work list'!$H$2:$H$1500,"<>Cancelled",'Work list'!$G$2:$G$1500,">="&TODAY(),'Work list'!$G$2:$G$1500,"<="&TODAY()+3) -> 0
A6: Selected year | B6: =IF($B$5=0,"",YEAR($B$5)) | D6: BonusM % | E6: 0 | G6: Max hours / month | H6: =IFERROR(INDEX(Setup!$B:$B,MATCH("Max hours/month",Setup!$A:$A,0)),"") -> 160 | L6: Drive-link-4 | N6: =Setup!B35 -> Drive-link-4 | Y6: Blocked | Z6: =COUNTIF('Work list'!$H$2:$H$1500,"Blocked") -> 0 | AA6: Open tasks without due date | AB6: =COUNTIFS('Work list'!$B$2:$B$1500,"WL-*",'Work list'!$H$2:$H$1500,"<>Completed",'Work list'!$H$2:$H$1500,"<>Cancelled",'Work list'!$G$2:$G$1500,"") -> 0
D7: BonusA % | E7: =IF($B$8="","",SUMIFS($AH:$AH,$A:$A,$B$8)/500) | Y7: Overdue | Z7: =COUNTIF('Work list'!$N$2:$N$1500,"Overdue") -> 0 | AA7: Open tasks without next action | AB7: =COUNTIFS('Work list'!$B$2:$B$1500,"WL-*",'Work list'!$H$2:$H$1500,"<>Completed",'Work list'!$H$2:$H$1500,"<>Cancelled",'Work list'!$K$2:$K$1500,"") -> 0
A8: End month | B8: =IF($B$5=0,"",DATE(YEAR($B$5),MONTH($B$5),1)) | D8: BonusT % | E8: =IFERROR(E6+E7,"") | Y8: Total actual time (min) | Z8: =SUM('Work list'!$L$2:$L$1500) -> 0 | AA8: Avg progress of open tasks | AB8: =IFERROR(AVERAGEIFS('Work list'!$I$2:$I$1500,'Work list'!$B$2:$B$1500,"WL-*",'Work list'!$H$2:$H$1500,"<>Completed",'Work list'!$H$2:$H$1500,"<>Cancelled"),0) -> 0
Y9: Total actual time (h) | Z9: =Z8/60 -> 0 | AA9: Completion rate | AB9: =IFERROR(Z4/Z3*100,0) -> 0
A10: Month | B10: Lines | C10: Hours (credited – quality based) | D10: Salary (calc) | E10: Bonus (calc) | F10: Total (calc) | G10: Salary paid | H10: Bonus paid | I10: Money received | J10: Δ (recv-calc) | K10: Work hours (real) | L10: Learn hours | M10: Δ hours (real - credited) | N10: Value by real hours | O10: Support cost | P10: Efficiency (%) | Q10: Δ time (credited vs expected) [Monthly] | R10: Mth 2–3d: Videos | S10: Mth 2–3d: Min | T10: Rpt ≥5: Videos | U10: Rpt ≥5: Min | V10: Aprv. Time ≥5 | W10: TC↓: Videos | X10: TC↓: Min | Y10: Aprv. Time low | Z10: TC↑: Videos | AA10: TC↑: Min | AB10: Aprv. Time hig | AC10: Work speed | AD10: Quality | AE10: Learning ability | AF10: Adherence to deadlines | AG10: Initiative | AH10: Total score | AI10: Video Δ (M-I) | AJ10: Messages Net (min)
A11: =IF($B$4=0,"",DATE(YEAR($B$4),MONTH($B$4),1)) | B11: =IF($A11="","",COUNTIFS('Work report'!$A:$A,">="&$A11,'Work report'!$A:$A,"<"&EDATE($A11,1),'Work report'!$B:$B,"<>")) | C11: =IF($A11="","",(SUMIFS('Work report'!$I:$I,'Work report'!$A:$A,">="&$A11,'Work report'!$A:$A,"<"&EDATE($A11,1),'Work report'!$B:$B,"<>",'Work report'!$B:$B,"<>1001")+SUMIFS('Work report'!$I:$I,'Work report'!$A:$A,">="&$A11,'Work report'!$A:$A,"<"&EDATE($A11,1),'Work report'!$B:$B,1001,'Work report'!$U:$U,"<>")+SUMIFS('Office time approval'!$M:$M,'Office time approval'!$A:$A,">="&$A11,'Office time approval'!$A:$A,"<"&EDATE($A11,1),'Office time approval'!$L:$L,"Approved")+SUMIFS('Vacation, holiday, illness'!$K:$K,'Vacation, holiday, illness'!$A:$A,">="&$A11,'Vacation, holiday, illness'!$A:$A,"<"&EDATE($A11,1)))/60) | D11: =IF($A11="","",IF($E$3="Hourly",$C11*$E$4,IF($E$3="Monthly",IF($C11>0,$E$5,0),0))) | E11: =IF($A11="","",$D11*$E$8) | F11: =IF($A11="","",D11+E11+((V11+Y11+AB11)/60)*$E$4) | G11: =IF($A11="","",SUMIFS(Payments!$C:$C,Payments!$A:$A,">="&$A11,Payments!$A:$A,"<"&EDATE($A11,1),Payments!$B:$B,"Salary")) | H11: =IF($A11="","",SUMIFS(Payments!$C:$C,Payments!$A:$A,">="&$A11,Payments!$A:$A,"<"&EDATE($A11,1),Payments!$B:$B,"Bonus")) | I11: =IF($A11="","",SUMIFS(Payments!$C:$C,Payments!$A:$A,">="&$A11,Payments!$A:$A,"<"&EDATE($A11,1))) | J11: =IF($A11="","",$I11-$F11) | K11: =IF($A11="","",IF($E$3="Monthly",SUMIFS('Work report'!$F:$F,'Work report'!$A:$A,">="&$A11,'Work report'!$A:$A,"<"&EDATE($A11,1),'Work report'!$B:$B,"<>",'Work report'!$B:$B,"<>1001")/60,SUMIFS('Work report'!$G:$G,'Work report'!$A:$A,">="&$A11,'Work report'!$A:$A,"<"&EDATE($A11,1),'Work report'!$B:$B,"<>",'Work report'!$B:$B,"<>1001")/60)) | L11: =IF($A11="","",IF($E$3="Monthly",SUMIFS('Work report'!$F:$F,'Work report'!$A:$A,">="&$A11,'Work report'!$A:$A,"<"&EDATE($A11,1),'Work report'!$B:$B,1001)/60,SUMIFS('Work report'!$G:$G,'Work report'!$A:$A,">="&$A11,'Work report'!$A:$A,"<"&EDATE($A11,1),'Work report'!$B:$B,1001)/60)) | M11: =IF($A11="","",$K11+$L11-$C11) | N11: =IF($A11="","",$E$4*($K11+$L11)) | O11: =IF($A11="","",$I11-$D11) | P11: =IFERROR($C11/($K11+$L11),"") | Q11: =IF($A11="","",IF($E$3<>"Monthly","",IFERROR($C11-($E$5/$E$4),""))) | R11: =IF($A11="","",SUMIFS('Work report'!$L:$L,'Work report'!$A:$A,">="&$A11,'Work report'!$A:$A,"<"&EDATE($A11,1))) | S11: =IF($A11="","",SUMIFS('Work report'!$M:$M,'Work report'!$A:$A,">="&$A11,'Work report'!$A:$A,"<"&EDATE($A11,1))) | T11: =IF($A11="","",SUMIFS('Missing tasks'!$E:$E,'Missing tasks'!$A:$A,">="&$A11,'Missing tasks'!$A:$A,"<"&EDATE($A11,1))) | U11: =IF($A11="","",SUMIFS('Missing tasks'!$H:$H,'Missing tasks'!$A:$A,">="&$A11,'Missing tasks'!$A:$A,"<"&EDATE($A11,1))) | V11: =IF($A11="","",SUMIFS('Missing tasks'!$J:$J,'Missing tasks'!$I:$I,">="&$A11,'Missing tasks'!$I:$I,"<"&EDATE($A11,1))) | W11: =IF($A11="","",COUNTIFS('Time check for tasks'!$A:$A,">="&$A11,'Time check for tasks'!$A:$A,"<"&EDATE($A11,1),'Time check for tasks'!$K:$K,">0",'Time check for tasks'!$L:$L,"Time check – lower")) | X11: =IF($A11="","",SUMIFS('Time check for tasks'!$K:$K,'Time check for tasks'!$A:$A,">="&$A11,'Time check for tasks'!$A:$A,"<"&EDATE($A11,1),'Time check for tasks'!$K:$K,">0",'Time check for tasks'!$L:$L,"Time check – lower")) | Y11: =IF($A11="","",SUMIFS('Time check for tasks'!$P:$P,'Time check for tasks'!$A:$A,">="&$A11,'Time check for tasks'!$A:$A,"<"&EDATE($A11,1),'Time check for tasks'!$P:$P,">0",'Time check for tasks'!$L:$L,"Time check – lower")) | Z11: =IF($A11="","",COUNTIFS('Time check for tasks'!$A:$A,">="&$A11,'Time check for tasks'!$A:$A,"<"&EDATE($A11,1),'Time check for tasks'!$K:$K,">0",'Time check for tasks'!$L:$L,"Time check – higher")) | AA11: =IF($A11="","",SUMIFS('Time check for tasks'!$K:$K,'Time check for tasks'!$A:$A,">="&$A11,'Time check for tasks'!$A:$A,"<"&EDATE($A11,1),'Time check for tasks'!$K:$K,">0",'Time check for tasks'!$L:$L,"Time check – higher")) | AB11: =IF($A11="","",SUMIFS('Time check for tasks'!$P:$P,'Time check for tasks'!$A:$A,">="&$A11,'Time check for tasks'!$A:$A,"<"&EDATE($A11,1),'Time check for tasks'!$P:$P,">0",'Time check for tasks'!$L:$L,"Time check – higher")) | AH11: =IF(COUNT(AC11:AG11)=0,"",SUM(AC11:AG11)) | AI11: =IF($A11="","",SUMIFS('Work report'!$N:$N,'Work report'!$A:$A,">="&$A11,'Work report'!$A:$A,"<"&EDATE($A11,1))) | AJ11: =IF($A11="","",SUMIFS(Messages!$T:$T,Messages!$A:$A,">="&$A11,Messages!$A:$A,"<"&EDATE($A11,1)))
A12: =IF(A11="","",IF(EDATE(A11,1)>$B$8,"",EDATE(A11,1))) | B12: =IF($A12="","",COUNTIFS('Work report'!$A:$A,">="&$A12,'Work report'!$A:$A,"<"&EDATE($A12,1),'Work report'!$B:$B,"<>")) | C12: =IF($A12="","",(SUMIFS('Work report'!$I:$I,'Work report'!$A:$A,">="&$A12,'Work report'!$A:$A,"<"&EDATE($A12,1),'Work report'!$B:$B,"<>",'Work report'!$B:$B,"<>1001")+SUMIFS('Work report'!$I:$I,'Work report'!$A:$A,">="&$A12,'Work report'!$A:$A,"<"&EDATE($A12,1),'Work report'!$B:$B,1001,'Work report'!$U:$U,"<>")+SUMIFS('Office time approval'!$M:$M,'Office time approval'!$A:$A,">="&$A12,'Office time approval'!$A:$A,"<"&EDATE($A12,1),'Office time approval'!$L:$L,"Approved")+SUMIFS('Vacation, holiday, illness'!$K:$K,'Vacation, holiday, illness'!$A:$A,">="&$A12,'Vacation, holiday, illness'!$A:$A,"<"&EDATE($A12,1)))/60) | D12: =IF($A12="","",IF($E$3="Hourly",$C12*$E$4,IF($E$3="Monthly",IF($C12>0,$E$5,0),0))) | E12: =IF($A12="","",$D12*$E$8) | F12: =IF($A12="","",D12+E12+((V12+Y12+AB12)/60)*$E$4) | G12: =IF($A12="","",SUMIFS(Payments!$C:$C,Payments!$A:$A,">="&$A12,Payments!$A:$A,"<"&EDATE($A12,1),Payments!$B:$B,"Salary")) | H12: =IF($A12="","",SUMIFS(Payments!$C:$C,Payments!$A:$A,">="&$A12,Payments!$A:$A,"<"&EDATE($A12,1),Payments!$B:$B,"Bonus")) | I12: =IF($A12="","",SUMIFS(Payments!$C:$C,Payments!$A:$A,">="&$A12,Payments!$A:$A,"<"&EDATE($A12,1))) | J12: =IF($A12="","",$I12-$F12) | K12: =IF($A12="","",IF($E$3="Monthly",SUMIFS('Work report'!$F:$F,'Work report'!$A:$A,">="&$A12,'Work report'!$A:$A,"<"&EDATE($A12,1),'Work report'!$B:$B,"<>",'Work report'!$B:$B,"<>1001")/60,SUMIFS('Work report'!$G:$G,'Work report'!$A:$A,">="&$A12,'Work report'!$A:$A,"<"&EDATE($A12,1),'Work report'!$B:$B,"<>",'Work report'!$B:$B,"<>1001")/60)) | L12: =IF($A12="","",IF($E$3="Monthly",SUMIFS('Work report'!$F:$F,'Work report'!$A:$A,">="&$A12,'Work report'!$A:$A,"<"&EDATE($A12,1),'Work report'!$B:$B,1001)/60,SUMIFS('Work report'!$G:$G,'Work report'!$A:$A,">="&$A12,'Work report'!$A:$A,"<"&EDATE($A12,1),'Work report'!$B:$B,1001)/60)) | M12: =IF($A12="","",$K12+$L12-$C12) | N12: =IF($A12="","",$E$4*($K12+$L12)) | O12: =IF($A12="","",$I12-$D12) | P12: =IFERROR($C12/($K12+$L12),"") | Q12: =IF($A12="","",IF($E$3<>"Monthly","",IFERROR($C12-($E$5/$E$4),""))) | R12: =IF($A12="","",SUMIFS('Work report'!$L:$L,'Work report'!$A:$A,">="&$A12,'Work report'!$A:$A,"<"&EDATE($A12,1))) | S12: =IF($A12="","",SUMIFS('Work report'!$M:$M,'Work report'!$A:$A,">="&$A12,'Work report'!$A:$A,"<"&EDATE($A12,1))) | T12: =IF($A12="","",SUMIFS('Missing tasks'!$E:$E,'Missing tasks'!$A:$A,">="&$A12,'Missing tasks'!$A:$A,"<"&EDATE($A12,1))) | U12: =IF($A12="","",SUMIFS('Missing tasks'!$H:$H,'Missing tasks'!$A:$A,">="&$A12,'Missing tasks'!$A:$A,"<"&EDATE($A12,1))) | V12: =IF($A12="","",SUMIFS('Missing tasks'!$J:$J,'Missing tasks'!$I:$I,">="&$A12,'Missing tasks'!$I:$I,"<"&EDATE($A12,1))) | W12: =IF($A12="","",COUNTIFS('Time check for tasks'!$A:$A,">="&$A12,'Time check for tasks'!$A:$A,"<"&EDATE($A12,1),'Time check for tasks'!$K:$K,">0",'Time check for tasks'!$L:$L,"Time check – lower")) | X12: =IF($A12="","",SUMIFS('Time check for tasks'!$K:$K,'Time check for tasks'!$A:$A,">="&$A12,'Time check for tasks'!$A:$A,"<"&EDATE($A12,1),'Time check for tasks'!$K:$K,">0",'Time check for tasks'!$L:$L,"Time check – lower")) | Y12: =IF($A12="","",SUMIFS('Time check for tasks'!$P:$P,'Time check for tasks'!$A:$A,">="&$A12,'Time check for tasks'!$A:$A,"<"&EDATE($A12,1),'Time check for tasks'!$P:$P,">0",'Time check for tasks'!$L:$L,"Time check – lower")) | Z12: =IF($A12="","",COUNTIFS('Time check for tasks'!$A:$A,">="&$A12,'Time check for tasks'!$A:$A,"<"&EDATE($A12,1),'Time check for tasks'!$K:$K,">0",'Time check for tasks'!$L:$L,"Time check – higher")) | AA12: =IF($A12="","",SUMIFS('Time check for tasks'!$K:$K,'Time check for tasks'!$A:$A,">="&$A12,'Time check for tasks'!$A:$A,"<"&EDATE($A12,1),'Time check for tasks'!$K:$K,">0",'Time check for tasks'!$L:$L,"Time check – higher")) | AB12: =IF($A12="","",SUMIFS('Time check for tasks'!$P:$P,'Time check for tasks'!$A:$A,">="&$A12,'Time check for tasks'!$A:$A,"<"&EDATE($A12,1),'Time check for tasks'!$P:$P,">0",'Time check for tasks'!$L:$L,"Time check – higher")) | AH12: =IF(COUNT(AC12:AG12)=0,"",SUM(AC12:AG12)) | AI12: =IF($A12="","",SUMIFS('Work report'!$N:$N,'Work report'!$A:$A,">="&$A12,'Work report'!$A:$A,"<"&EDATE($A12,1))) | AJ12: =IF($A12="","",SUMIFS(Messages!$T:$T,Messages!$A:$A,">="&$A12,Messages!$A:$A,"<"&EDATE($A12,1)))
A13: =IF(A12="","",IF(EDATE(A12,1)>$B$8,"",EDATE(A12,1))) | B13: =IF($A13="","",COUNTIFS('Work report'!$A:$A,">="&$A13,'Work report'!$A:$A,"<"&EDATE($A13,1),'Work report'!$B:$B,"<>")) | C13: =IF($A13="","",(SUMIFS('Work report'!$I:$I,'Work report'!$A:$A,">="&$A13,'Work report'!$A:$A,"<"&EDATE($A13,1),'Work report'!$B:$B,"<>",'Work report'!$B:$B,"<>1001")+SUMIFS('Work report'!$I:$I,'Work report'!$A:$A,">="&$A13,'Work report'!$A:$A,"<"&EDATE($A13,1),'Work report'!$B:$B,1001,'Work report'!$U:$U,"<>")+SUMIFS('Office time approval'!$M:$M,'Office time approval'!$A:$A,">="&$A13,'Office time approval'!$A:$A,"<"&EDATE($A13,1),'Office time approval'!$L:$L,"Approved")+SUMIFS('Vacation, holiday, illness'!$K:$K,'Vacation, holiday, illness'!$A:$A,">="&$A13,'Vacation, holiday, illness'!$A:$A,"<"&EDATE($A13,1)))/60) | D13: =IF($A13="","",IF($E$3="Hourly",$C13*$E$4,IF($E$3="Monthly",IF($C13>0,$E$5,0),0))) | E13: =IF($A13="","",$D13*$E$8) | F13: =IF($A13="","",D13+E13+((V13+Y13+AB13)/60)*$E$4) | G13: =IF($A13="","",SUMIFS(Payments!$C:$C,Payments!$A:$A,">="&$A13,Payments!$A:$A,"<"&EDATE($A13,1),Payments!$B:$B,"Salary")) | H13: =IF($A13="","",SUMIFS(Payments!$C:$C,Payments!$A:$A,">="&$A13,Payments!$A:$A,"<"&EDATE($A13,1),Payments!$B:$B,"Bonus")) | I13: =IF($A13="","",SUMIFS(Payments!$C:$C,Payments!$A:$A,">="&$A13,Payments!$A:$A,"<"&EDATE($A13,1))) | J13: =IF($A13="","",$I13-$F13) | K13: =IF($A13="","",IF($E$3="Monthly",SUMIFS('Work report'!$F:$F,'Work report'!$A:$A,">="&$A13,'Work report'!$A:$A,"<"&EDATE($A13,1),'Work report'!$B:$B,"<>",'Work report'!$B:$B,"<>1001")/60,SUMIFS('Work report'!$G:$G,'Work report'!$A:$A,">="&$A13,'Work report'!$A:$A,"<"&EDATE($A13,1),'Work report'!$B:$B,"<>",'Work report'!$B:$B,"<>1001")/60)) | L13: =IF($A13="","",IF($E$3="Monthly",SUMIFS('Work report'!$F:$F,'Work report'!$A:$A,">="&$A13,'Work report'!$A:$A,"<"&EDATE($A13,1),'Work report'!$B:$B,1001)/60,SUMIFS('Work report'!$G:$G,'Work report'!$A:$A,">="&$A13,'Work report'!$A:$A,"<"&EDATE($A13,1),'Work report'!$B:$B,1001)/60)) | M13: =IF($A13="","",$K13+$L13-$C13) | N13: =IF($A13="","",$E$4*($K13+$L13)) | O13: =IF($A13="","",$I13-$D13) | P13: =IFERROR($C13/($K13+$L13),"") | Q13: =IF($A13="","",IF($E$3<>"Monthly","",IFERROR($C13-($E$5/$E$4),""))) | R13: =IF($A13="","",SUMIFS('Work report'!$L:$L,'Work report'!$A:$A,">="&$A13,'Work report'!$A:$A,"<"&EDATE($A13,1))) | S13: =IF($A13="","",SUMIFS('Work report'!$M:$M,'Work report'!$A:$A,">="&$A13,'Work report'!$A:$A,"<"&EDATE($A13,1))) | T13: =IF($A13="","",SUMIFS('Missing tasks'!$E:$E,'Missing tasks'!$A:$A,">="&$A13,'Missing tasks'!$A:$A,"<"&EDATE($A13,1))) | U13: =IF($A13="","",SUMIFS('Missing tasks'!$H:$H,'Missing tasks'!$A:$A,">="&$A13,'Missing tasks'!$A:$A,"<"&EDATE($A13,1))) | V13: =IF($A13="","",SUMIFS('Missing tasks'!$J:$J,'Missing tasks'!$I:$I,">="&$A13,'Missing tasks'!$I:$I,"<"&EDATE($A13,1))) | W13: =IF($A13="","",COUNTIFS('Time check for tasks'!$A:$A,">="&$A13,'Time check for tasks'!$A:$A,"<"&EDATE($A13,1),'Time check for tasks'!$K:$K,">0",'Time check for tasks'!$L:$L,"Time check – lower")) | X13: =IF($A13="","",SUMIFS('Time check for tasks'!$K:$K,'Time check for tasks'!$A:$A,">="&$A13,'Time check for tasks'!$A:$A,"<"&EDATE($A13,1),'Time check for tasks'!$K:$K,">0",'Time check for tasks'!$L:$L,"Time check – lower")) | Y13: =IF($A13="","",SUMIFS('Time check for tasks'!$P:$P,'Time check for tasks'!$A:$A,">="&$A13,'Time check for tasks'!$A:$A,"<"&EDATE($A13,1),'Time check for tasks'!$P:$P,">0",'Time check for tasks'!$L:$L,"Time check – lower")) | Z13: =IF($A13="","",COUNTIFS('Time check for tasks'!$A:$A,">="&$A13,'Time check for tasks'!$A:$A,"<"&EDATE($A13,1),'Time check for tasks'!$K:$K,">0",'Time check for tasks'!$L:$L,"Time check – higher")) | AA13: =IF($A13="","",SUMIFS('Time check for tasks'!$K:$K,'Time check for tasks'!$A:$A,">="&$A13,'Time check for tasks'!$A:$A,"<"&EDATE($A13,1),'Time check for tasks'!$K:$K,">0",'Time check for tasks'!$L:$L,"Time check – higher")) | AB13: =IF($A13="","",SUMIFS('Time check for tasks'!$P:$P,'Time check for tasks'!$A:$A,">="&$A13,'Time check for tasks'!$A:$A,"<"&EDATE($A13,1),'Time check for tasks'!$P:$P,">0",'Time check for tasks'!$L:$L,"Time check – higher")) | AH13: =IF(COUNT(AC13:AG13)=0,"",SUM(AC13:AG13)) | AI13: =IF($A13="","",SUMIFS('Work report'!$N:$N,'Work report'!$A:$A,">="&$A13,'Work report'!$A:$A,"<"&EDATE($A13,1))) | AJ13: =IF($A13="","",SUMIFS(Messages!$T:$T,Messages!$A:$A,">="&$A13,Messages!$A:$A,"<"&EDATE($A13,1)))
A14: =IF(A13="","",IF(EDATE(A13,1)>$B$8,"",EDATE(A13,1))) | B14: =IF($A14="","",COUNTIFS('Work report'!$A:$A,">="&$A14,'Work report'!$A:$A,"<"&EDATE($A14,1),'Work report'!$B:$B,"<>")) | C14: =IF($A14="","",(SUMIFS('Work report'!$I:$I,'Work report'!$A:$A,">="&$A14,'Work report'!$A:$A,"<"&EDATE($A14,1),'Work report'!$B:$B,"<>",'Work report'!$B:$B,"<>1001")+SUMIFS('Work report'!$I:$I,'Work report'!$A:$A,">="&$A14,'Work report'!$A:$A,"<"&EDATE($A14,1),'Work report'!$B:$B,1001,'Work report'!$U:$U,"<>")+SUMIFS('Office time approval'!$M:$M,'Office time approval'!$A:$A,">="&$A14,'Office time approval'!$A:$A,"<"&EDATE($A14,1),'Office time approval'!$L:$L,"Approved")+SUMIFS('Vacation, holiday, illness'!$K:$K,'Vacation, holiday, illness'!$A:$A,">="&$A14,'Vacation, holiday, illness'!$A:$A,"<"&EDATE($A14,1)))/60) | D14: =IF($A14="","",IF($E$3="Hourly",$C14*$E$4,IF($E$3="Monthly",IF($C14>0,$E$5,0),0))) | E14: =IF($A14="","",$D14*$E$8) | F14: =IF($A14="","",D14+E14+((V14+Y14+AB14)/60)*$E$4) | G14: =IF($A14="","",SUMIFS(Payments!$C:$C,Payments!$A:$A,">="&$A14,Payments!$A:$A,"<"&EDATE($A14,1),Payments!$B:$B,"Salary")) | H14: =IF($A14="","",SUMIFS(Payments!$C:$C,Payments!$A:$A,">="&$A14,Payments!$A:$A,"<"&EDATE($A14,1),Payments!$B:$B,"Bonus")) | I14: =IF($A14="","",SUMIFS(Payments!$C:$C,Payments!$A:$A,">="&$A14,Payments!$A:$A,"<"&EDATE($A14,1))) | J14: =IF($A14="","",$I14-$F14) | K14: =IF($A14="","",IF($E$3="Monthly",SUMIFS('Work report'!$F:$F,'Work report'!$A:$A,">="&$A14,'Work report'!$A:$A,"<"&EDATE($A14,1),'Work report'!$B:$B,"<>",'Work report'!$B:$B,"<>1001")/60,SUMIFS('Work report'!$G:$G,'Work report'!$A:$A,">="&$A14,'Work report'!$A:$A,"<"&EDATE($A14,1),'Work report'!$B:$B,"<>",'Work report'!$B:$B,"<>1001")/60)) | L14: =IF($A14="","",IF($E$3="Monthly",SUMIFS('Work report'!$F:$F,'Work report'!$A:$A,">="&$A14,'Work report'!$A:$A,"<"&EDATE($A14,1),'Work report'!$B:$B,1001)/60,SUMIFS('Work report'!$G:$G,'Work report'!$A:$A,">="&$A14,'Work report'!$A:$A,"<"&EDATE($A14,1),'Work report'!$B:$B,1001)/60)) | M14: =IF($A14="","",$K14+$L14-$C14) | N14: =IF($A14="","",$E$4*($K14+$L14)) | O14: =IF($A14="","",$I14-$D14) | P14: =IFERROR($C14/($K14+$L14),"") | Q14: =IF($A14="","",IF($E$3<>"Monthly","",IFERROR($C14-($E$5/$E$4),""))) | R14: =IF($A14="","",SUMIFS('Work report'!$L:$L,'Work report'!$A:$A,">="&$A14,'Work report'!$A:$A,"<"&EDATE($A14,1))) | S14: =IF($A14="","",SUMIFS('Work report'!$M:$M,'Work report'!$A:$A,">="&$A14,'Work report'!$A:$A,"<"&EDATE($A14,1))) | T14: =IF($A14="","",SUMIFS('Missing tasks'!$E:$E,'Missing tasks'!$A:$A,">="&$A14,'Missing tasks'!$A:$A,"<"&EDATE($A14,1))) | U14: =IF($A14="","",SUMIFS('Missing tasks'!$H:$H,'Missing tasks'!$A:$A,">="&$A14,'Missing tasks'!$A:$A,"<"&EDATE($A14,1))) | V14: =IF($A14="","",SUMIFS('Missing tasks'!$J:$J,'Missing tasks'!$I:$I,">="&$A14,'Missing tasks'!$I:$I,"<"&EDATE($A14,1))) | W14: =IF($A14="","",COUNTIFS('Time check for tasks'!$A:$A,">="&$A14,'Time check for tasks'!$A:$A,"<"&EDATE($A14,1),'Time check for tasks'!$K:$K,">0",'Time check for tasks'!$L:$L,"Time check – lower")) | X14: =IF($A14="","",SUMIFS('Time check for tasks'!$K:$K,'Time check for tasks'!$A:$A,">="&$A14,'Time check for tasks'!$A:$A,"<"&EDATE($A14,1),'Time check for tasks'!$K:$K,">0",'Time check for tasks'!$L:$L,"Time check – lower")) | Y14: =IF($A14="","",SUMIFS('Time check for tasks'!$P:$P,'Time check for tasks'!$A:$A,">="&$A14,'Time check for tasks'!$A:$A,"<"&EDATE($A14,1),'Time check for tasks'!$P:$P,">0",'Time check for tasks'!$L:$L,"Time check – lower")) | Z14: =IF($A14="","",COUNTIFS('Time check for tasks'!$A:$A,">="&$A14,'Time check for tasks'!$A:$A,"<"&EDATE($A14,1),'Time check for tasks'!$K:$K,">0",'Time check for tasks'!$L:$L,"Time check – higher")) | AA14: =IF($A14="","",SUMIFS('Time check for tasks'!$K:$K,'Time check for tasks'!$A:$A,">="&$A14,'Time check for tasks'!$A:$A,"<"&EDATE($A14,1),'Time check for tasks'!$K:$K,">0",'Time check for tasks'!$L:$L,"Time check – higher")) | AB14: =IF($A14="","",SUMIFS('Time check for tasks'!$P:$P,'Time check for tasks'!$A:$A,">="&$A14,'Time check for tasks'!$A:$A,"<"&EDATE($A14,1),'Time check for tasks'!$P:$P,">0",'Time check for tasks'!$L:$L,"Time check – higher")) | AH14: =IF(COUNT(AC14:AG14)=0,"",SUM(AC14:AG14)) | AI14: =IF($A14="","",SUMIFS('Work report'!$N:$N,'Work report'!$A:$A,">="&$A14,'Work report'!$A:$A,"<"&EDATE($A14,1))) | AJ14: =IF($A14="","",SUMIFS(Messages!$T:$T,Messages!$A:$A,">="&$A14,Messages!$A:$A,"<"&EDATE($A14,1)))
A15: =IF(A14="","",IF(EDATE(A14,1)>$B$8,"",EDATE(A14,1))) | B15: =IF($A15="","",COUNTIFS('Work report'!$A:$A,">="&$A15,'Work report'!$A:$A,"<"&EDATE($A15,1),'Work report'!$B:$B,"<>")) | C15: =IF($A15="","",(SUMIFS('Work report'!$I:$I,'Work report'!$A:$A,">="&$A15,'Work report'!$A:$A,"<"&EDATE($A15,1),'Work report'!$B:$B,"<>",'Work report'!$B:$B,"<>1001")+SUMIFS('Work report'!$I:$I,'Work report'!$A:$A,">="&$A15,'Work report'!$A:$A,"<"&EDATE($A15,1),'Work report'!$B:$B,1001,'Work report'!$U:$U,"<>")+SUMIFS('Office time approval'!$M:$M,'Office time approval'!$A:$A,">="&$A15,'Office time approval'!$A:$A,"<"&EDATE($A15,1),'Office time approval'!$L:$L,"Approved")+SUMIFS('Vacation, holiday, illness'!$K:$K,'Vacation, holiday, illness'!$A:$A,">="&$A15,'Vacation, holiday, illness'!$A:$A,"<"&EDATE($A15,1)))/60) | D15: =IF($A15="","",IF($E$3="Hourly",$C15*$E$4,IF($E$3="Monthly",IF($C15>0,$E$5,0),0))) | E15: =IF($A15="","",$D15*$E$8) | F15: =IF($A15="","",D15+E15+((V15+Y15+AB15)/60)*$E$4) | G15: =IF($A15="","",SUMIFS(Payments!$C:$C,Payments!$A:$A,">="&$A15,Payments!$A:$A,"<"&EDATE($A15,1),Payments!$B:$B,"Salary")) | H15: =IF($A15="","",SUMIFS(Payments!$C:$C,Payments!$A:$A,">="&$A15,Payments!$A:$A,"<"&EDATE($A15,1),Payments!$B:$B,"Bonus")) | I15: =IF($A15="","",SUMIFS(Payments!$C:$C,Payments!$A:$A,">="&$A15,Payments!$A:$A,"<"&EDATE($A15,1))) | J15: =IF($A15="","",$I15-$F15) | K15: =IF($A15="","",IF($E$3="Monthly",SUMIFS('Work report'!$F:$F,'Work report'!$A:$A,">="&$A15,'Work report'!$A:$A,"<"&EDATE($A15,1),'Work report'!$B:$B,"<>",'Work report'!$B:$B,"<>1001")/60,SUMIFS('Work report'!$G:$G,'Work report'!$A:$A,">="&$A15,'Work report'!$A:$A,"<"&EDATE($A15,1),'Work report'!$B:$B,"<>",'Work report'!$B:$B,"<>1001")/60)) | L15: =IF($A15="","",IF($E$3="Monthly",SUMIFS('Work report'!$F:$F,'Work report'!$A:$A,">="&$A15,'Work report'!$A:$A,"<"&EDATE($A15,1),'Work report'!$B:$B,1001)/60,SUMIFS('Work report'!$G:$G,'Work report'!$A:$A,">="&$A15,'Work report'!$A:$A,"<"&EDATE($A15,1),'Work report'!$B:$B,1001)/60)) | M15: =IF($A15="","",$K15+$L15-$C15) | N15: =IF($A15="","",$E$4*($K15+$L15)) | O15: =IF($A15="","",$I15-$D15) | P15: =IFERROR($C15/($K15+$L15),"") | Q15: =IF($A15="","",IF($E$3<>"Monthly","",IFERROR($C15-($E$5/$E$4),""))) | R15: =IF($A15="","",SUMIFS('Work report'!$L:$L,'Work report'!$A:$A,">="&$A15,'Work report'!$A:$A,"<"&EDATE($A15,1))) | S15: =IF($A15="","",SUMIFS('Work report'!$M:$M,'Work report'!$A:$A,">="&$A15,'Work report'!$A:$A,"<"&EDATE($A15,1))) | T15: =IF($A15="","",SUMIFS('Missing tasks'!$E:$E,'Missing tasks'!$A:$A,">="&$A15,'Missing tasks'!$A:$A,"<"&EDATE($A15,1))) | U15: =IF($A15="","",SUMIFS('Missing tasks'!$H:$H,'Missing tasks'!$A:$A,">="&$A15,'Missing tasks'!$A:$A,"<"&EDATE($A15,1))) | V15: =IF($A15="","",SUMIFS('Missing tasks'!$J:$J,'Missing tasks'!$I:$I,">="&$A15,'Missing tasks'!$I:$I,"<"&EDATE($A15,1))) | W15: =IF($A15="","",COUNTIFS('Time check for tasks'!$A:$A,">="&$A15,'Time check for tasks'!$A:$A,"<"&EDATE($A15,1),'Time check for tasks'!$K:$K,">0",'Time check for tasks'!$L:$L,"Time check – lower")) | X15: =IF($A15="","",SUMIFS('Time check for tasks'!$K:$K,'Time check for tasks'!$A:$A,">="&$A15,'Time check for tasks'!$A:$A,"<"&EDATE($A15,1),'Time check for tasks'!$K:$K,">0",'Time check for tasks'!$L:$L,"Time check – lower")) | Y15: =IF($A15="","",SUMIFS('Time check for tasks'!$P:$P,'Time check for tasks'!$A:$A,">="&$A15,'Time check for tasks'!$A:$A,"<"&EDATE($A15,1),'Time check for tasks'!$P:$P,">0",'Time check for tasks'!$L:$L,"Time check – lower")) | Z15: =IF($A15="","",COUNTIFS('Time check for tasks'!$A:$A,">="&$A15,'Time check for tasks'!$A:$A,"<"&EDATE($A15,1),'Time check for tasks'!$K:$K,">0",'Time check for tasks'!$L:$L,"Time check – higher")) | AA15: =IF($A15="","",SUMIFS('Time check for tasks'!$K:$K,'Time check for tasks'!$A:$A,">="&$A15,'Time check for tasks'!$A:$A,"<"&EDATE($A15,1),'Time check for tasks'!$K:$K,">0",'Time check for tasks'!$L:$L,"Time check – higher")) | AB15: =IF($A15="","",SUMIFS('Time check for tasks'!$P:$P,'Time check for tasks'!$A:$A,">="&$A15,'Time check for tasks'!$A:$A,"<"&EDATE($A15,1),'Time check for tasks'!$P:$P,">0",'Time check for tasks'!$L:$L,"Time check – higher")) | AH15: =IF(COUNT(AC15:AG15)=0,"",SUM(AC15:AG15)) | AI15: =IF($A15="","",SUMIFS('Work report'!$N:$N,'Work report'!$A:$A,">="&$A15,'Work report'!$A:$A,"<"&EDATE($A15,1))) | AJ15: =IF($A15="","",SUMIFS(Messages!$T:$T,Messages!$A:$A,">="&$A15,Messages!$A:$A,"<"&EDATE($A15,1)))
A16: =IF(A15="","",IF(EDATE(A15,1)>$B$8,"",EDATE(A15,1))) | B16: =IF($A16="","",COUNTIFS('Work report'!$A:$A,">="&$A16,'Work report'!$A:$A,"<"&EDATE($A16,1),'Work report'!$B:$B,"<>")) | C16: =IF($A16="","",(SUMIFS('Work report'!$I:$I,'Work report'!$A:$A,">="&$A16,'Work report'!$A:$A,"<"&EDATE($A16,1),'Work report'!$B:$B,"<>",'Work report'!$B:$B,"<>1001")+SUMIFS('Work report'!$I:$I,'Work report'!$A:$A,">="&$A16,'Work report'!$A:$A,"<"&EDATE($A16,1),'Work report'!$B:$B,1001,'Work report'!$U:$U,"<>")+SUMIFS('Office time approval'!$M:$M,'Office time approval'!$A:$A,">="&$A16,'Office time approval'!$A:$A,"<"&EDATE($A16,1),'Office time approval'!$L:$L,"Approved")+SUMIFS('Vacation, holiday, illness'!$K:$K,'Vacation, holiday, illness'!$A:$A,">="&$A16,'Vacation, holiday, illness'!$A:$A,"<"&EDATE($A16,1)))/60) | D16: =IF($A16="","",IF($E$3="Hourly",$C16*$E$4,IF($E$3="Monthly",IF($C16>0,$E$5,0),0))) | E16: =IF($A16="","",$D16*$E$8) | F16: =IF($A16="","",D16+E16+((V16+Y16+AB16)/60)*$E$4) | G16: =IF($A16="","",SUMIFS(Payments!$C:$C,Payments!$A:$A,">="&$A16,Payments!$A:$A,"<"&EDATE($A16,1),Payments!$B:$B,"Salary")) | H16: =IF($A16="","",SUMIFS(Payments!$C:$C,Payments!$A:$A,">="&$A16,Payments!$A:$A,"<"&EDATE($A16,1),Payments!$B:$B,"Bonus")) | I16: =IF($A16="","",SUMIFS(Payments!$C:$C,Payments!$A:$A,">="&$A16,Payments!$A:$A,"<"&EDATE($A16,1))) | J16: =IF($A16="","",$I16-$F16) | K16: =IF($A16="","",IF($E$3="Monthly",SUMIFS('Work report'!$F:$F,'Work report'!$A:$A,">="&$A16,'Work report'!$A:$A,"<"&EDATE($A16,1),'Work report'!$B:$B,"<>",'Work report'!$B:$B,"<>1001")/60,SUMIFS('Work report'!$G:$G,'Work report'!$A:$A,">="&$A16,'Work report'!$A:$A,"<"&EDATE($A16,1),'Work report'!$B:$B,"<>",'Work report'!$B:$B,"<>1001")/60)) | L16: =IF($A16="","",IF($E$3="Monthly",SUMIFS('Work report'!$F:$F,'Work report'!$A:$A,">="&$A16,'Work report'!$A:$A,"<"&EDATE($A16,1),'Work report'!$B:$B,1001)/60,SUMIFS('Work report'!$G:$G,'Work report'!$A:$A,">="&$A16,'Work report'!$A:$A,"<"&EDATE($A16,1),'Work report'!$B:$B,1001)/60)) | M16: =IF($A16="","",$K16+$L16-$C16) | N16: =IF($A16="","",$E$4*($K16+$L16)) | O16: =IF($A16="","",$I16-$D16) | P16: =IFERROR($C16/($K16+$L16),"") | Q16: =IF($A16="","",IF($E$3<>"Monthly","",IFERROR($C16-($E$5/$E$4),""))) | R16: =IF($A16="","",SUMIFS('Work report'!$L:$L,'Work report'!$A:$A,">="&$A16,'Work report'!$A:$A,"<"&EDATE($A16,1))) | S16: =IF($A16="","",SUMIFS('Work report'!$M:$M,'Work report'!$A:$A,">="&$A16,'Work report'!$A:$A,"<"&EDATE($A16,1))) | T16: =IF($A16="","",SUMIFS('Missing tasks'!$E:$E,'Missing tasks'!$A:$A,">="&$A16,'Missing tasks'!$A:$A,"<"&EDATE($A16,1))) | U16: =IF($A16="","",SUMIFS('Missing tasks'!$H:$H,'Missing tasks'!$A:$A,">="&$A16,'Missing tasks'!$A:$A,"<"&EDATE($A16,1))) | V16: =IF($A16="","",SUMIFS('Missing tasks'!$J:$J,'Missing tasks'!$I:$I,">="&$A16,'Missing tasks'!$I:$I,"<"&EDATE($A16,1))) | W16: =IF($A16="","",COUNTIFS('Time check for tasks'!$A:$A,">="&$A16,'Time check for tasks'!$A:$A,"<"&EDATE($A16,1),'Time check for tasks'!$K:$K,">0",'Time check for tasks'!$L:$L,"Time check – lower")) | X16: =IF($A16="","",SUMIFS('Time check for tasks'!$K:$K,'Time check for tasks'!$A:$A,">="&$A16,'Time check for tasks'!$A:$A,"<"&EDATE($A16,1),'Time check for tasks'!$K:$K,">0",'Time check for tasks'!$L:$L,"Time check – lower")) | Y16: =IF($A16="","",SUMIFS('Time check for tasks'!$P:$P,'Time check for tasks'!$A:$A,">="&$A16,'Time check for tasks'!$A:$A,"<"&EDATE($A16,1),'Time check for tasks'!$P:$P,">0",'Time check for tasks'!$L:$L,"Time check – lower")) | Z16: =IF($A16="","",COUNTIFS('Time check for tasks'!$A:$A,">="&$A16,'Time check for tasks'!$A:$A,"<"&EDATE($A16,1),'Time check for tasks'!$K:$K,">0",'Time check for tasks'!$L:$L,"Time check – higher")) | AA16: =IF($A16="","",SUMIFS('Time check for tasks'!$K:$K,'Time check for tasks'!$A:$A,">="&$A16,'Time check for tasks'!$A:$A,"<"&EDATE($A16,1),'Time check for tasks'!$K:$K,">0",'Time check for tasks'!$L:$L,"Time check – higher")) | AB16: =IF($A16="","",SUMIFS('Time check for tasks'!$P:$P,'Time check for tasks'!$A:$A,">="&$A16,'Time check for tasks'!$A:$A,"<"&EDATE($A16,1),'Time check for tasks'!$P:$P,">0",'Time check for tasks'!$L:$L,"Time check – higher")) | AH16: =IF(COUNT(AC16:AG16)=0,"",SUM(AC16:AG16)) | AI16: =IF($A16="","",SUMIFS('Work report'!$N:$N,'Work report'!$A:$A,">="&$A16,'Work report'!$A:$A,"<"&EDATE($A16,1))) | AJ16: =IF($A16="","",SUMIFS(Messages!$T:$T,Messages!$A:$A,">="&$A16,Messages!$A:$A,"<"&EDATE($A16,1)))
A17: =IF(A16="","",IF(EDATE(A16,1)>$B$8,"",EDATE(A16,1))) | B17: =IF($A17="","",COUNTIFS('Work report'!$A:$A,">="&$A17,'Work report'!$A:$A,"<"&EDATE($A17,1),'Work report'!$B:$B,"<>")) | C17: =IF($A17="","",(SUMIFS('Work report'!$I:$I,'Work report'!$A:$A,">="&$A17,'Work report'!$A:$A,"<"&EDATE($A17,1),'Work report'!$B:$B,"<>",'Work report'!$B:$B,"<>1001")+SUMIFS('Work report'!$I:$I,'Work report'!$A:$A,">="&$A17,'Work report'!$A:$A,"<"&EDATE($A17,1),'Work report'!$B:$B,1001,'Work report'!$U:$U,"<>")+SUMIFS('Office time approval'!$M:$M,'Office time approval'!$A:$A,">="&$A17,'Office time approval'!$A:$A,"<"&EDATE($A17,1),'Office time approval'!$L:$L,"Approved")+SUMIFS('Vacation, holiday, illness'!$K:$K,'Vacation, holiday, illness'!$A:$A,">="&$A17,'Vacation, holiday, illness'!$A:$A,"<"&EDATE($A17,1)))/60) | D17: =IF($A17="","",IF($E$3="Hourly",$C17*$E$4,IF($E$3="Monthly",IF($C17>0,$E$5,0),0))) | E17: =IF($A17="","",$D17*$E$8) | F17: =IF($A17="","",D17+E17+((V17+Y17+AB17)/60)*$E$4) | G17: =IF($A17="","",SUMIFS(Payments!$C:$C,Payments!$A:$A,">="&$A17,Payments!$A:$A,"<"&EDATE($A17,1),Payments!$B:$B,"Salary")) | H17: =IF($A17="","",SUMIFS(Payments!$C:$C,Payments!$A:$A,">="&$A17,Payments!$A:$A,"<"&EDATE($A17,1),Payments!$B:$B,"Bonus")) | I17: =IF($A17="","",SUMIFS(Payments!$C:$C,Payments!$A:$A,">="&$A17,Payments!$A:$A,"<"&EDATE($A17,1))) | J17: =IF($A17="","",$I17-$F17) | K17: =IF($A17="","",IF($E$3="Monthly",SUMIFS('Work report'!$F:$F,'Work report'!$A:$A,">="&$A17,'Work report'!$A:$A,"<"&EDATE($A17,1),'Work report'!$B:$B,"<>",'Work report'!$B:$B,"<>1001")/60,SUMIFS('Work report'!$G:$G,'Work report'!$A:$A,">="&$A17,'Work report'!$A:$A,"<"&EDATE($A17,1),'Work report'!$B:$B,"<>",'Work report'!$B:$B,"<>1001")/60)) | L17: =IF($A17="","",IF($E$3="Monthly",SUMIFS('Work report'!$F:$F,'Work report'!$A:$A,">="&$A17,'Work report'!$A:$A,"<"&EDATE($A17,1),'Work report'!$B:$B,1001)/60,SUMIFS('Work report'!$G:$G,'Work report'!$A:$A,">="&$A17,'Work report'!$A:$A,"<"&EDATE($A17,1),'Work report'!$B:$B,1001)/60)) | M17: =IF($A17="","",$K17+$L17-$C17) | N17: =IF($A17="","",$E$4*($K17+$L17)) | O17: =IF($A17="","",$I17-$D17) | P17: =IFERROR($C17/($K17+$L17),"") | Q17: =IF($A17="","",IF($E$3<>"Monthly","",IFERROR($C17-($E$5/$E$4),""))) | R17: =IF($A17="","",SUMIFS('Work report'!$L:$L,'Work report'!$A:$A,">="&$A17,'Work report'!$A:$A,"<"&EDATE($A17,1))) | S17: =IF($A17="","",SUMIFS('Work report'!$M:$M,'Work report'!$A:$A,">="&$A17,'Work report'!$A:$A,"<"&EDATE($A17,1))) | T17: =IF($A17="","",SUMIFS('Missing tasks'!$E:$E,'Missing tasks'!$A:$A,">="&$A17,'Missing tasks'!$A:$A,"<"&EDATE($A17,1))) | U17: =IF($A17="","",SUMIFS('Missing tasks'!$H:$H,'Missing tasks'!$A:$A,">="&$A17,'Missing tasks'!$A:$A,"<"&EDATE($A17,1))) | V17: =IF($A17="","",SUMIFS('Missing tasks'!$J:$J,'Missing tasks'!$I:$I,">="&$A17,'Missing tasks'!$I:$I,"<"&EDATE($A17,1))) | W17: =IF($A17="","",COUNTIFS('Time check for tasks'!$A:$A,">="&$A17,'Time check for tasks'!$A:$A,"<"&EDATE($A17,1),'Time check for tasks'!$K:$K,">0",'Time check for tasks'!$L:$L,"Time check – lower")) | X17: =IF($A17="","",SUMIFS('Time check for tasks'!$K:$K,'Time check for tasks'!$A:$A,">="&$A17,'Time check for tasks'!$A:$A,"<"&EDATE($A17,1),'Time check for tasks'!$K:$K,">0",'Time check for tasks'!$L:$L,"Time check – lower")) | Y17: =IF($A17="","",SUMIFS('Time check for tasks'!$P:$P,'Time check for tasks'!$A:$A,">="&$A17,'Time check for tasks'!$A:$A,"<"&EDATE($A17,1),'Time check for tasks'!$P:$P,">0",'Time check for tasks'!$L:$L,"Time check – lower")) | Z17: =IF($A17="","",COUNTIFS('Time check for tasks'!$A:$A,">="&$A17,'Time check for tasks'!$A:$A,"<"&EDATE($A17,1),'Time check for tasks'!$K:$K,">0",'Time check for tasks'!$L:$L,"Time check – higher")) | AA17: =IF($A17="","",SUMIFS('Time check for tasks'!$K:$K,'Time check for tasks'!$A:$A,">="&$A17,'Time check for tasks'!$A:$A,"<"&EDATE($A17,1),'Time check for tasks'!$K:$K,">0",'Time check for tasks'!$L:$L,"Time check – higher")) | AB17: =IF($A17="","",SUMIFS('Time check for tasks'!$P:$P,'Time check for tasks'!$A:$A,">="&$A17,'Time check for tasks'!$A:$A,"<"&EDATE($A17,1),'Time check for tasks'!$P:$P,">0",'Time check for tasks'!$L:$L,"Time check – higher")) | AH17: =IF(COUNT(AC17:AG17)=0,"",SUM(AC17:AG17)) | AI17: =IF($A17="","",SUMIFS('Work report'!$N:$N,'Work report'!$A:$A,">="&$A17,'Work report'!$A:$A,"<"&EDATE($A17,1))) | AJ17: =IF($A17="","",SUMIFS(Messages!$T:$T,Messages!$A:$A,">="&$A17,Messages!$A:$A,"<"&EDATE($A17,1)))
A18: =IF(A17="","",IF(EDATE(A17,1)>$B$8,"",EDATE(A17,1))) | B18: =IF($A18="","",COUNTIFS('Work report'!$A:$A,">="&$A18,'Work report'!$A:$A,"<"&EDATE($A18,1),'Work report'!$B:$B,"<>")) | C18: =IF($A18="","",(SUMIFS('Work report'!$I:$I,'Work report'!$A:$A,">="&$A18,'Work report'!$A:$A,"<"&EDATE($A18,1),'Work report'!$B:$B,"<>",'Work report'!$B:$B,"<>1001")+SUMIFS('Work report'!$I:$I,'Work report'!$A:$A,">="&$A18,'Work report'!$A:$A,"<"&EDATE($A18,1),'Work report'!$B:$B,1001,'Work report'!$U:$U,"<>")+SUMIFS('Office time approval'!$M:$M,'Office time approval'!$A:$A,">="&$A18,'Office time approval'!$A:$A,"<"&EDATE($A18,1),'Office time approval'!$L:$L,"Approved")+SUMIFS('Vacation, holiday, illness'!$K:$K,'Vacation, holiday, illness'!$A:$A,">="&$A18,'Vacation, holiday, illness'!$A:$A,"<"&EDATE($A18,1)))/60) | D18: =IF($A18="","",IF($E$3="Hourly",$C18*$E$4,IF($E$3="Monthly",IF($C18>0,$E$5,0),0))) | E18: =IF($A18="","",$D18*$E$8) | F18: =IF($A18="","",D18+E18+((V18+Y18+AB18)/60)*$E$4) | G18: =IF($A18="","",SUMIFS(Payments!$C:$C,Payments!$A:$A,">="&$A18,Payments!$A:$A,"<"&EDATE($A18,1),Payments!$B:$B,"Salary")) | H18: =IF($A18="","",SUMIFS(Payments!$C:$C,Payments!$A:$A,">="&$A18,Payments!$A:$A,"<"&EDATE($A18,1),Payments!$B:$B,"Bonus")) | I18: =IF($A18="","",SUMIFS(Payments!$C:$C,Payments!$A:$A,">="&$A18,Payments!$A:$A,"<"&EDATE($A18,1))) | J18: =IF($A18="","",$I18-$F18) | K18: =IF($A18="","",IF($E$3="Monthly",SUMIFS('Work report'!$F:$F,'Work report'!$A:$A,">="&$A18,'Work report'!$A:$A,"<"&EDATE($A18,1),'Work report'!$B:$B,"<>",'Work report'!$B:$B,"<>1001")/60,SUMIFS('Work report'!$G:$G,'Work report'!$A:$A,">="&$A18,'Work report'!$A:$A,"<"&EDATE($A18,1),'Work report'!$B:$B,"<>",'Work report'!$B:$B,"<>1001")/60)) | L18: =IF($A18="","",IF($E$3="Monthly",SUMIFS('Work report'!$F:$F,'Work report'!$A:$A,">="&$A18,'Work report'!$A:$A,"<"&EDATE($A18,1),'Work report'!$B:$B,1001)/60,SUMIFS('Work report'!$G:$G,'Work report'!$A:$A,">="&$A18,'Work report'!$A:$A,"<"&EDATE($A18,1),'Work report'!$B:$B,1001)/60)) | M18: =IF($A18="","",$K18+$L18-$C18) | N18: =IF($A18="","",$E$4*($K18+$L18)) | O18: =IF($A18="","",$I18-$D18) | P18: =IFERROR($C18/($K18+$L18),"") | Q18: =IF($A18="","",IF($E$3<>"Monthly","",IFERROR($C18-($E$5/$E$4),""))) | R18: =IF($A18="","",SUMIFS('Work report'!$L:$L,'Work report'!$A:$A,">="&$A18,'Work report'!$A:$A,"<"&EDATE($A18,1))) | S18: =IF($A18="","",SUMIFS('Work report'!$M:$M,'Work report'!$A:$A,">="&$A18,'Work report'!$A:$A,"<"&EDATE($A18,1))) | T18: =IF($A18="","",SUMIFS('Missing tasks'!$E:$E,'Missing tasks'!$A:$A,">="&$A18,'Missing tasks'!$A:$A,"<"&EDATE($A18,1))) | U18: =IF($A18="","",SUMIFS('Missing tasks'!$H:$H,'Missing tasks'!$A:$A,">="&$A18,'Missing tasks'!$A:$A,"<"&EDATE($A18,1))) | V18: =IF($A18="","",SUMIFS('Missing tasks'!$J:$J,'Missing tasks'!$I:$I,">="&$A18,'Missing tasks'!$I:$I,"<"&EDATE($A18,1))) | W18: =IF($A18="","",COUNTIFS('Time check for tasks'!$A:$A,">="&$A18,'Time check for tasks'!$A:$A,"<"&EDATE($A18,1),'Time check for tasks'!$K:$K,">0",'Time check for tasks'!$L:$L,"Time check – lower")) | X18: =IF($A18="","",SUMIFS('Time check for tasks'!$K:$K,'Time check for tasks'!$A:$A,">="&$A18,'Time check for tasks'!$A:$A,"<"&EDATE($A18,1),'Time check for tasks'!$K:$K,">0",'Time check for tasks'!$L:$L,"Time check – lower")) | Y18: =IF($A18="","",SUMIFS('Time check for tasks'!$P:$P,'Time check for tasks'!$A:$A,">="&$A18,'Time check for tasks'!$A:$A,"<"&EDATE($A18,1),'Time check for tasks'!$P:$P,">0",'Time check for tasks'!$L:$L,"Time check – lower")) | Z18: =IF($A18="","",COUNTIFS('Time check for tasks'!$A:$A,">="&$A18,'Time check for tasks'!$A:$A,"<"&EDATE($A18,1),'Time check for tasks'!$K:$K,">0",'Time check for tasks'!$L:$L,"Time check – higher")) | AA18: =IF($A18="","",SUMIFS('Time check for tasks'!$K:$K,'Time check for tasks'!$A:$A,">="&$A18,'Time check for tasks'!$A:$A,"<"&EDATE($A18,1),'Time check for tasks'!$K:$K,">0",'Time check for tasks'!$L:$L,"Time check – higher")) | AB18: =IF($A18="","",SUMIFS('Time check for tasks'!$P:$P,'Time check for tasks'!$A:$A,">="&$A18,'Time check for tasks'!$A:$A,"<"&EDATE($A18,1),'Time check for tasks'!$P:$P,">0",'Time check for tasks'!$L:$L,"Time check – higher")) | AH18: =IF(COUNT(AC18:AG18)=0,"",SUM(AC18:AG18)) | AI18: =IF($A18="","",SUMIFS('Work report'!$N:$N,'Work report'!$A:$A,">="&$A18,'Work report'!$A:$A,"<"&EDATE($A18,1))) | AJ18: =IF($A18="","",SUMIFS(Messages!$T:$T,Messages!$A:$A,">="&$A18,Messages!$A:$A,"<"&EDATE($A18,1)))
A19: =IF(A18="","",IF(EDATE(A18,1)>$B$8,"",EDATE(A18,1))) | B19: =IF($A19="","",COUNTIFS('Work report'!$A:$A,">="&$A19,'Work report'!$A:$A,"<"&EDATE($A19,1),'Work report'!$B:$B,"<>")) | C19: =IF($A19="","",(SUMIFS('Work report'!$I:$I,'Work report'!$A:$A,">="&$A19,'Work report'!$A:$A,"<"&EDATE($A19,1),'Work report'!$B:$B,"<>",'Work report'!$B:$B,"<>1001")+SUMIFS('Work report'!$I:$I,'Work report'!$A:$A,">="&$A19,'Work report'!$A:$A,"<"&EDATE($A19,1),'Work report'!$B:$B,1001,'Work report'!$U:$U,"<>")+SUMIFS('Office time approval'!$M:$M,'Office time approval'!$A:$A,">="&$A19,'Office time approval'!$A:$A,"<"&EDATE($A19,1),'Office time approval'!$L:$L,"Approved")+SUMIFS('Vacation, holiday, illness'!$K:$K,'Vacation, holiday, illness'!$A:$A,">="&$A19,'Vacation, holiday, illness'!$A:$A,"<"&EDATE($A19,1)))/60) | D19: =IF($A19="","",IF($E$3="Hourly",$C19*$E$4,IF($E$3="Monthly",IF($C19>0,$E$5,0),0))) | E19: =IF($A19="","",$D19*$E$8) | F19: =IF($A19="","",D19+E19+((V19+Y19+AB19)/60)*$E$4) | G19: =IF($A19="","",SUMIFS(Payments!$C:$C,Payments!$A:$A,">="&$A19,Payments!$A:$A,"<"&EDATE($A19,1),Payments!$B:$B,"Salary")) | H19: =IF($A19="","",SUMIFS(Payments!$C:$C,Payments!$A:$A,">="&$A19,Payments!$A:$A,"<"&EDATE($A19,1),Payments!$B:$B,"Bonus")) | I19: =IF($A19="","",SUMIFS(Payments!$C:$C,Payments!$A:$A,">="&$A19,Payments!$A:$A,"<"&EDATE($A19,1))) | J19: =IF($A19="","",$I19-$F19) | K19: =IF($A19="","",IF($E$3="Monthly",SUMIFS('Work report'!$F:$F,'Work report'!$A:$A,">="&$A19,'Work report'!$A:$A,"<"&EDATE($A19,1),'Work report'!$B:$B,"<>",'Work report'!$B:$B,"<>1001")/60,SUMIFS('Work report'!$G:$G,'Work report'!$A:$A,">="&$A19,'Work report'!$A:$A,"<"&EDATE($A19,1),'Work report'!$B:$B,"<>",'Work report'!$B:$B,"<>1001")/60)) | L19: =IF($A19="","",IF($E$3="Monthly",SUMIFS('Work report'!$F:$F,'Work report'!$A:$A,">="&$A19,'Work report'!$A:$A,"<"&EDATE($A19,1),'Work report'!$B:$B,1001)/60,SUMIFS('Work report'!$G:$G,'Work report'!$A:$A,">="&$A19,'Work report'!$A:$A,"<"&EDATE($A19,1),'Work report'!$B:$B,1001)/60)) | M19: =IF($A19="","",$K19+$L19-$C19) | N19: =IF($A19="","",$E$4*($K19+$L19)) | O19: =IF($A19="","",$I19-$D19) | P19: =IFERROR($C19/($K19+$L19),"") | Q19: =IF($A19="","",IF($E$3<>"Monthly","",IFERROR($C19-($E$5/$E$4),""))) | R19: =IF($A19="","",SUMIFS('Work report'!$L:$L,'Work report'!$A:$A,">="&$A19,'Work report'!$A:$A,"<"&EDATE($A19,1))) | S19: =IF($A19="","",SUMIFS('Work report'!$M:$M,'Work report'!$A:$A,">="&$A19,'Work report'!$A:$A,"<"&EDATE($A19,1))) | T19: =IF($A19="","",SUMIFS('Missing tasks'!$E:$E,'Missing tasks'!$A:$A,">="&$A19,'Missing tasks'!$A:$A,"<"&EDATE($A19,1))) | U19: =IF($A19="","",SUMIFS('Missing tasks'!$H:$H,'Missing tasks'!$A:$A,">="&$A19,'Missing tasks'!$A:$A,"<"&EDATE($A19,1))) | V19: =IF($A19="","",SUMIFS('Missing tasks'!$J:$J,'Missing tasks'!$I:$I,">="&$A19,'Missing tasks'!$I:$I,"<"&EDATE($A19,1))) | W19: =IF($A19="","",COUNTIFS('Time check for tasks'!$A:$A,">="&$A19,'Time check for tasks'!$A:$A,"<"&EDATE($A19,1),'Time check for tasks'!$K:$K,">0",'Time check for tasks'!$L:$L,"Time check – lower")) | X19: =IF($A19="","",SUMIFS('Time check for tasks'!$K:$K,'Time check for tasks'!$A:$A,">="&$A19,'Time check for tasks'!$A:$A,"<"&EDATE($A19,1),'Time check for tasks'!$K:$K,">0",'Time check for tasks'!$L:$L,"Time check – lower")) | Y19: =IF($A19="","",SUMIFS('Time check for tasks'!$P:$P,'Time check for tasks'!$A:$A,">="&$A19,'Time check for tasks'!$A:$A,"<"&EDATE($A19,1),'Time check for tasks'!$P:$P,">0",'Time check for tasks'!$L:$L,"Time check – lower")) | Z19: =IF($A19="","",COUNTIFS('Time check for tasks'!$A:$A,">="&$A19,'Time check for tasks'!$A:$A,"<"&EDATE($A19,1),'Time check for tasks'!$K:$K,">0",'Time check for tasks'!$L:$L,"Time check – higher")) | AA19: =IF($A19="","",SUMIFS('Time check for tasks'!$K:$K,'Time check for tasks'!$A:$A,">="&$A19,'Time check for tasks'!$A:$A,"<"&EDATE($A19,1),'Time check for tasks'!$K:$K,">0",'Time check for tasks'!$L:$L,"Time check – higher")) | AB19: =IF($A19="","",SUMIFS('Time check for tasks'!$P:$P,'Time check for tasks'!$A:$A,">="&$A19,'Time check for tasks'!$A:$A,"<"&EDATE($A19,1),'Time check for tasks'!$P:$P,">0",'Time check for tasks'!$L:$L,"Time check – higher")) | AH19: =IF(COUNT(AC19:AG19)=0,"",SUM(AC19:AG19)) | AI19: =IF($A19="","",SUMIFS('Work report'!$N:$N,'Work report'!$A:$A,">="&$A19,'Work report'!$A:$A,"<"&EDATE($A19,1))) | AJ19: =IF($A19="","",SUMIFS(Messages!$T:$T,Messages!$A:$A,">="&$A19,Messages!$A:$A,"<"&EDATE($A19,1)))
A20: =IF(A19="","",IF(EDATE(A19,1)>$B$8,"",EDATE(A19,1))) | B20: =IF($A20="","",COUNTIFS('Work report'!$A:$A,">="&$A20,'Work report'!$A:$A,"<"&EDATE($A20,1),'Work report'!$B:$B,"<>")) | C20: =IF($A20="","",(SUMIFS('Work report'!$I:$I,'Work report'!$A:$A,">="&$A20,'Work report'!$A:$A,"<"&EDATE($A20,1),'Work report'!$B:$B,"<>",'Work report'!$B:$B,"<>1001")+SUMIFS('Work report'!$I:$I,'Work report'!$A:$A,">="&$A20,'Work report'!$A:$A,"<"&EDATE($A20,1),'Work report'!$B:$B,1001,'Work report'!$U:$U,"<>")+SUMIFS('Office time approval'!$M:$M,'Office time approval'!$A:$A,">="&$A20,'Office time approval'!$A:$A,"<"&EDATE($A20,1),'Office time approval'!$L:$L,"Approved")+SUMIFS('Vacation, holiday, illness'!$K:$K,'Vacation, holiday, illness'!$A:$A,">="&$A20,'Vacation, holiday, illness'!$A:$A,"<"&EDATE($A20,1)))/60) | D20: =IF($A20="","",IF($E$3="Hourly",$C20*$E$4,IF($E$3="Monthly",IF($C20>0,$E$5,0),0))) | E20: =IF($A20="","",$D20*$E$8) | F20: =IF($A20="","",D20+E20+((V20+Y20+AB20)/60)*$E$4) | G20: =IF($A20="","",SUMIFS(Payments!$C:$C,Payments!$A:$A,">="&$A20,Payments!$A:$A,"<"&EDATE($A20,1),Payments!$B:$B,"Salary")) | H20: =IF($A20="","",SUMIFS(Payments!$C:$C,Payments!$A:$A,">="&$A20,Payments!$A:$A,"<"&EDATE($A20,1),Payments!$B:$B,"Bonus")) | I20: =IF($A20="","",SUMIFS(Payments!$C:$C,Payments!$A:$A,">="&$A20,Payments!$A:$A,"<"&EDATE($A20,1))) | J20: =IF($A20="","",$I20-$F20) | K20: =IF($A20="","",IF($E$3="Monthly",SUMIFS('Work report'!$F:$F,'Work report'!$A:$A,">="&$A20,'Work report'!$A:$A,"<"&EDATE($A20,1),'Work report'!$B:$B,"<>",'Work report'!$B:$B,"<>1001")/60,SUMIFS('Work report'!$G:$G,'Work report'!$A:$A,">="&$A20,'Work report'!$A:$A,"<"&EDATE($A20,1),'Work report'!$B:$B,"<>",'Work report'!$B:$B,"<>1001")/60)) | L20: =IF($A20="","",IF($E$3="Monthly",SUMIFS('Work report'!$F:$F,'Work report'!$A:$A,">="&$A20,'Work report'!$A:$A,"<"&EDATE($A20,1),'Work report'!$B:$B,1001)/60,SUMIFS('Work report'!$G:$G,'Work report'!$A:$A,">="&$A20,'Work report'!$A:$A,"<"&EDATE($A20,1),'Work report'!$B:$B,1001)/60)) | M20: =IF($A20="","",$K20+$L20-$C20) | N20: =IF($A20="","",$E$4*($K20+$L20)) | O20: =IF($A20="","",$I20-$D20) | P20: =IFERROR($C20/($K20+$L20),"") | Q20: =IF($A20="","",IF($E$3<>"Monthly","",IFERROR($C20-($E$5/$E$4),""))) | R20: =IF($A20="","",SUMIFS('Work report'!$L:$L,'Work report'!$A:$A,">="&$A20,'Work report'!$A:$A,"<"&EDATE($A20,1))) | S20: =IF($A20="","",SUMIFS('Work report'!$M:$M,'Work report'!$A:$A,">="&$A20,'Work report'!$A:$A,"<"&EDATE($A20,1))) | T20: =IF($A20="","",SUMIFS('Missing tasks'!$E:$E,'Missing tasks'!$A:$A,">="&$A20,'Missing tasks'!$A:$A,"<"&EDATE($A20,1))) | U20: =IF($A20="","",SUMIFS('Missing tasks'!$H:$H,'Missing tasks'!$A:$A,">="&$A20,'Missing tasks'!$A:$A,"<"&EDATE($A20,1))) | V20: =IF($A20="","",SUMIFS('Missing tasks'!$J:$J,'Missing tasks'!$I:$I,">="&$A20,'Missing tasks'!$I:$I,"<"&EDATE($A20,1))) | W20: =IF($A20="","",COUNTIFS('Time check for tasks'!$A:$A,">="&$A20,'Time check for tasks'!$A:$A,"<"&EDATE($A20,1),'Time check for tasks'!$K:$K,">0",'Time check for tasks'!$L:$L,"Time check – lower")) | X20: =IF($A20="","",SUMIFS('Time check for tasks'!$K:$K,'Time check for tasks'!$A:$A,">="&$A20,'Time check for tasks'!$A:$A,"<"&EDATE($A20,1),'Time check for tasks'!$K:$K,">0",'Time check for tasks'!$L:$L,"Time check – lower")) | Y20: =IF($A20="","",SUMIFS('Time check for tasks'!$P:$P,'Time check for tasks'!$A:$A,">="&$A20,'Time check for tasks'!$A:$A,"<"&EDATE($A20,1),'Time check for tasks'!$P:$P,">0",'Time check for tasks'!$L:$L,"Time check – lower")) | Z20: =IF($A20="","",COUNTIFS('Time check for tasks'!$A:$A,">="&$A20,'Time check for tasks'!$A:$A,"<"&EDATE($A20,1),'Time check for tasks'!$K:$K,">0",'Time check for tasks'!$L:$L,"Time check – higher")) | AA20: =IF($A20="","",SUMIFS('Time check for tasks'!$K:$K,'Time check for tasks'!$A:$A,">="&$A20,'Time check for tasks'!$A:$A,"<"&EDATE($A20,1),'Time check for tasks'!$K:$K,">0",'Time check for tasks'!$L:$L,"Time check – higher")) | AB20: =IF($A20="","",SUMIFS('Time check for tasks'!$P:$P,'Time check for tasks'!$A:$A,">="&$A20,'Time check for tasks'!$A:$A,"<"&EDATE($A20,1),'Time check for tasks'!$P:$P,">0",'Time check for tasks'!$L:$L,"Time check – higher")) | AH20: =IF(COUNT(AC20:AG20)=0,"",SUM(AC20:AG20)) | AI20: =IF($A20="","",SUMIFS('Work report'!$N:$N,'Work report'!$A:$A,">="&$A20,'Work report'!$A:$A,"<"&EDATE($A20,1))) | AJ20: =IF($A20="","",SUMIFS(Messages!$T:$T,Messages!$A:$A,">="&$A20,Messages!$A:$A,"<"&EDATE($A20,1)))
A21: =IF(A20="","",IF(EDATE(A20,1)>$B$8,"",EDATE(A20,1))) | B21: =IF($A21="","",COUNTIFS('Work report'!$A:$A,">="&$A21,'Work report'!$A:$A,"<"&EDATE($A21,1),'Work report'!$B:$B,"<>")) | C21: =IF($A21="","",(SUMIFS('Work report'!$I:$I,'Work report'!$A:$A,">="&$A21,'Work report'!$A:$A,"<"&EDATE($A21,1),'Work report'!$B:$B,"<>",'Work report'!$B:$B,"<>1001")+SUMIFS('Work report'!$I:$I,'Work report'!$A:$A,">="&$A21,'Work report'!$A:$A,"<"&EDATE($A21,1),'Work report'!$B:$B,1001,'Work report'!$U:$U,"<>")+SUMIFS('Office time approval'!$M:$M,'Office time approval'!$A:$A,">="&$A21,'Office time approval'!$A:$A,"<"&EDATE($A21,1),'Office time approval'!$L:$L,"Approved")+SUMIFS('Vacation, holiday, illness'!$K:$K,'Vacation, holiday, illness'!$A:$A,">="&$A21,'Vacation, holiday, illness'!$A:$A,"<"&EDATE($A21,1)))/60) | D21: =IF($A21="","",IF($E$3="Hourly",$C21*$E$4,IF($E$3="Monthly",IF($C21>0,$E$5,0),0))) | E21: =IF($A21="","",$D21*$E$8) | F21: =IF($A21="","",D21+E21+((V21+Y21+AB21)/60)*$E$4) | G21: =IF($A21="","",SUMIFS(Payments!$C:$C,Payments!$A:$A,">="&$A21,Payments!$A:$A,"<"&EDATE($A21,1),Payments!$B:$B,"Salary")) | H21: =IF($A21="","",SUMIFS(Payments!$C:$C,Payments!$A:$A,">="&$A21,Payments!$A:$A,"<"&EDATE($A21,1),Payments!$B:$B,"Bonus")) | I21: =IF($A21="","",SUMIFS(Payments!$C:$C,Payments!$A:$A,">="&$A21,Payments!$A:$A,"<"&EDATE($A21,1))) | J21: =IF($A21="","",$I21-$F21) | K21: =IF($A21="","",IF($E$3="Monthly",SUMIFS('Work report'!$F:$F,'Work report'!$A:$A,">="&$A21,'Work report'!$A:$A,"<"&EDATE($A21,1),'Work report'!$B:$B,"<>",'Work report'!$B:$B,"<>1001")/60,SUMIFS('Work report'!$G:$G,'Work report'!$A:$A,">="&$A21,'Work report'!$A:$A,"<"&EDATE($A21,1),'Work report'!$B:$B,"<>",'Work report'!$B:$B,"<>1001")/60)) | L21: =IF($A21="","",IF($E$3="Monthly",SUMIFS('Work report'!$F:$F,'Work report'!$A:$A,">="&$A21,'Work report'!$A:$A,"<"&EDATE($A21,1),'Work report'!$B:$B,1001)/60,SUMIFS('Work report'!$G:$G,'Work report'!$A:$A,">="&$A21,'Work report'!$A:$A,"<"&EDATE($A21,1),'Work report'!$B:$B,1001)/60)) | M21: =IF($A21="","",$K21+$L21-$C21) | N21: =IF($A21="","",$E$4*($K21+$L21)) | O21: =IF($A21="","",$I21-$D21) | P21: =IFERROR($C21/($K21+$L21),"") | Q21: =IF($A21="","",IF($E$3<>"Monthly","",IFERROR($C21-($E$5/$E$4),""))) | R21: =IF($A21="","",SUMIFS('Work report'!$L:$L,'Work report'!$A:$A,">="&$A21,'Work report'!$A:$A,"<"&EDATE($A21,1))) | S21: =IF($A21="","",SUMIFS('Work report'!$M:$M,'Work report'!$A:$A,">="&$A21,'Work report'!$A:$A,"<"&EDATE($A21,1))) | T21: =IF($A21="","",SUMIFS('Missing tasks'!$E:$E,'Missing tasks'!$A:$A,">="&$A21,'Missing tasks'!$A:$A,"<"&EDATE($A21,1))) | U21: =IF($A21="","",SUMIFS('Missing tasks'!$H:$H,'Missing tasks'!$A:$A,">="&$A21,'Missing tasks'!$A:$A,"<"&EDATE($A21,1))) | V21: =IF($A21="","",SUMIFS('Missing tasks'!$J:$J,'Missing tasks'!$I:$I,">="&$A21,'Missing tasks'!$I:$I,"<"&EDATE($A21,1))) | W21: =IF($A21="","",COUNTIFS('Time check for tasks'!$A:$A,">="&$A21,'Time check for tasks'!$A:$A,"<"&EDATE($A21,1),'Time check for tasks'!$K:$K,">0",'Time check for tasks'!$L:$L,"Time check – lower")) | X21: =IF($A21="","",SUMIFS('Time check for tasks'!$K:$K,'Time check for tasks'!$A:$A,">="&$A21,'Time check for tasks'!$A:$A,"<"&EDATE($A21,1),'Time check for tasks'!$K:$K,">0",'Time check for tasks'!$L:$L,"Time check – lower")) | Y21: =IF($A21="","",SUMIFS('Time check for tasks'!$P:$P,'Time check for tasks'!$A:$A,">="&$A21,'Time check for tasks'!$A:$A,"<"&EDATE($A21,1),'Time check for tasks'!$P:$P,">0",'Time check for tasks'!$L:$L,"Time check – lower")) | Z21: =IF($A21="","",COUNTIFS('Time check for tasks'!$A:$A,">="&$A21,'Time check for tasks'!$A:$A,"<"&EDATE($A21,1),'Time check for tasks'!$K:$K,">0",'Time check for tasks'!$L:$L,"Time check – higher")) | AA21: =IF($A21="","",SUMIFS('Time check for tasks'!$K:$K,'Time check for tasks'!$A:$A,">="&$A21,'Time check for tasks'!$A:$A,"<"&EDATE($A21,1),'Time check for tasks'!$K:$K,">0",'Time check for tasks'!$L:$L,"Time check – higher")) | AB21: =IF($A21="","",SUMIFS('Time check for tasks'!$P:$P,'Time check for tasks'!$A:$A,">="&$A21,'Time check for tasks'!$A:$A,"<"&EDATE($A21,1),'Time check for tasks'!$P:$P,">0",'Time check for tasks'!$L:$L,"Time check – higher")) | AH21: =IF(COUNT(AC21:AG21)=0,"",SUM(AC21:AG21)) | AI21: =IF($A21="","",SUMIFS('Work report'!$N:$N,'Work report'!$A:$A,">="&$A21,'Work report'!$A:$A,"<"&EDATE($A21,1))) | AJ21: =IF($A21="","",SUMIFS(Messages!$T:$T,Messages!$A:$A,">="&$A21,Messages!$A:$A,"<"&EDATE($A21,1)))
A22: =IF(A21="","",IF(EDATE(A21,1)>$B$8,"",EDATE(A21,1))) | B22: =IF($A22="","",COUNTIFS('Work report'!$A:$A,">="&$A22,'Work report'!$A:$A,"<"&EDATE($A22,1),'Work report'!$B:$B,"<>")) | C22: =IF($A22="","",(SUMIFS('Work report'!$I:$I,'Work report'!$A:$A,">="&$A22,'Work report'!$A:$A,"<"&EDATE($A22,1),'Work report'!$B:$B,"<>",'Work report'!$B:$B,"<>1001")+SUMIFS('Work report'!$I:$I,'Work report'!$A:$A,">="&$A22,'Work report'!$A:$A,"<"&EDATE($A22,1),'Work report'!$B:$B,1001,'Work report'!$U:$U,"<>")+SUMIFS('Office time approval'!$M:$M,'Office time approval'!$A:$A,">="&$A22,'Office time approval'!$A:$A,"<"&EDATE($A22,1),'Office time approval'!$L:$L,"Approved")+SUMIFS('Vacation, holiday, illness'!$K:$K,'Vacation, holiday, illness'!$A:$A,">="&$A22,'Vacation, holiday, illness'!$A:$A,"<"&EDATE($A22,1)))/60) | D22: =IF($A22="","",IF($E$3="Hourly",$C22*$E$4,IF($E$3="Monthly",IF($C22>0,$E$5,0),0))) | E22: =IF($A22="","",$D22*$E$8) | F22: =IF($A22="","",D22+E22+((V22+Y22+AB22)/60)*$E$4) | G22: =IF($A22="","",SUMIFS(Payments!$C:$C,Payments!$A:$A,">="&$A22,Payments!$A:$A,"<"&EDATE($A22,1),Payments!$B:$B,"Salary")) | H22: =IF($A22="","",SUMIFS(Payments!$C:$C,Payments!$A:$A,">="&$A22,Payments!$A:$A,"<"&EDATE($A22,1),Payments!$B:$B,"Bonus")) | I22: =IF($A22="","",SUMIFS(Payments!$C:$C,Payments!$A:$A,">="&$A22,Payments!$A:$A,"<"&EDATE($A22,1))) | J22: =IF($A22="","",$I22-$F22) | K22: =IF($A22="","",IF($E$3="Monthly",SUMIFS('Work report'!$F:$F,'Work report'!$A:$A,">="&$A22,'Work report'!$A:$A,"<"&EDATE($A22,1),'Work report'!$B:$B,"<>",'Work report'!$B:$B,"<>1001")/60,SUMIFS('Work report'!$G:$G,'Work report'!$A:$A,">="&$A22,'Work report'!$A:$A,"<"&EDATE($A22,1),'Work report'!$B:$B,"<>",'Work report'!$B:$B,"<>1001")/60)) | L22: =IF($A22="","",IF($E$3="Monthly",SUMIFS('Work report'!$F:$F,'Work report'!$A:$A,">="&$A22,'Work report'!$A:$A,"<"&EDATE($A22,1),'Work report'!$B:$B,1001)/60,SUMIFS('Work report'!$G:$G,'Work report'!$A:$A,">="&$A22,'Work report'!$A:$A,"<"&EDATE($A22,1),'Work report'!$B:$B,1001)/60)) | M22: =IF($A22="","",$K22+$L22-$C22) | N22: =IF($A22="","",$E$4*($K22+$L22)) | O22: =IF($A22="","",$I22-$D22) | P22: =IFERROR($C22/($K22+$L22),"") | Q22: =IF($A22="","",IF($E$3<>"Monthly","",IFERROR($C22-($E$5/$E$4),""))) | R22: =IF($A22="","",SUMIFS('Work report'!$L:$L,'Work report'!$A:$A,">="&$A22,'Work report'!$A:$A,"<"&EDATE($A22,1))) | S22: =IF($A22="","",SUMIFS('Work report'!$M:$M,'Work report'!$A:$A,">="&$A22,'Work report'!$A:$A,"<"&EDATE($A22,1))) | T22: =IF($A22="","",SUMIFS('Missing tasks'!$E:$E,'Missing tasks'!$A:$A,">="&$A22,'Missing tasks'!$A:$A,"<"&EDATE($A22,1))) | U22: =IF($A22="","",SUMIFS('Missing tasks'!$H:$H,'Missing tasks'!$A:$A,">="&$A22,'Missing tasks'!$A:$A,"<"&EDATE($A22,1))) | V22: =IF($A22="","",SUMIFS('Missing tasks'!$J:$J,'Missing tasks'!$I:$I,">="&$A22,'Missing tasks'!$I:$I,"<"&EDATE($A22,1))) | W22: =IF($A22="","",COUNTIFS('Time check for tasks'!$A:$A,">="&$A22,'Time check for tasks'!$A:$A,"<"&EDATE($A22,1),'Time check for tasks'!$K:$K,">0",'Time check for tasks'!$L:$L,"Time check – lower")) | X22: =IF($A22="","",SUMIFS('Time check for tasks'!$K:$K,'Time check for tasks'!$A:$A,">="&$A22,'Time check for tasks'!$A:$A,"<"&EDATE($A22,1),'Time check for tasks'!$K:$K,">0",'Time check for tasks'!$L:$L,"Time check – lower")) | Y22: =IF($A22="","",SUMIFS('Time check for tasks'!$P:$P,'Time check for tasks'!$A:$A,">="&$A22,'Time check for tasks'!$A:$A,"<"&EDATE($A22,1),'Time check for tasks'!$P:$P,">0",'Time check for tasks'!$L:$L,"Time check – lower")) | Z22: =IF($A22="","",COUNTIFS('Time check for tasks'!$A:$A,">="&$A22,'Time check for tasks'!$A:$A,"<"&EDATE($A22,1),'Time check for tasks'!$K:$K,">0",'Time check for tasks'!$L:$L,"Time check – higher")) | AA22: =IF($A22="","",SUMIFS('Time check for tasks'!$K:$K,'Time check for tasks'!$A:$A,">="&$A22,'Time check for tasks'!$A:$A,"<"&EDATE($A22,1),'Time check for tasks'!$K:$K,">0",'Time check for tasks'!$L:$L,"Time check – higher")) | AB22: =IF($A22="","",SUMIFS('Time check for tasks'!$P:$P,'Time check for tasks'!$A:$A,">="&$A22,'Time check for tasks'!$A:$A,"<"&EDATE($A22,1),'Time check for tasks'!$P:$P,">0",'Time check for tasks'!$L:$L,"Time check – higher")) | AH22: =IF(COUNT(AC22:AG22)=0,"",SUM(AC22:AG22)) | AI22: =IF($A22="","",SUMIFS('Work report'!$N:$N,'Work report'!$A:$A,">="&$A22,'Work report'!$A:$A,"<"&EDATE($A22,1))) | AJ22: =IF($A22="","",SUMIFS(Messages!$T:$T,Messages!$A:$A,">="&$A22,Messages!$A:$A,"<"&EDATE($A22,1)))
A23: =IF(A22="","",IF(EDATE(A22,1)>$B$8,"",EDATE(A22,1))) | B23: =IF($A23="","",COUNTIFS('Work report'!$A:$A,">="&$A23,'Work report'!$A:$A,"<"&EDATE($A23,1),'Work report'!$B:$B,"<>")) | C23: =IF($A23="","",(SUMIFS('Work report'!$I:$I,'Work report'!$A:$A,">="&$A23,'Work report'!$A:$A,"<"&EDATE($A23,1),'Work report'!$B:$B,"<>",'Work report'!$B:$B,"<>1001")+SUMIFS('Work report'!$I:$I,'Work report'!$A:$A,">="&$A23,'Work report'!$A:$A,"<"&EDATE($A23,1),'Work report'!$B:$B,1001,'Work report'!$U:$U,"<>")+SUMIFS('Office time approval'!$M:$M,'Office time approval'!$A:$A,">="&$A23,'Office time approval'!$A:$A,"<"&EDATE($A23,1),'Office time approval'!$L:$L,"Approved")+SUMIFS('Vacation, holiday, illness'!$K:$K,'Vacation, holiday, illness'!$A:$A,">="&$A23,'Vacation, holiday, illness'!$A:$A,"<"&EDATE($A23,1)))/60) | D23: =IF($A23="","",IF($E$3="Hourly",$C23*$E$4,IF($E$3="Monthly",IF($C23>0,$E$5,0),0))) | E23: =IF($A23="","",$D23*$E$8) | F23: =IF($A23="","",D23+E23+((V23+Y23+AB23)/60)*$E$4) | G23: =IF($A23="","",SUMIFS(Payments!$C:$C,Payments!$A:$A,">="&$A23,Payments!$A:$A,"<"&EDATE($A23,1),Payments!$B:$B,"Salary")) | H23: =IF($A23="","",SUMIFS(Payments!$C:$C,Payments!$A:$A,">="&$A23,Payments!$A:$A,"<"&EDATE($A23,1),Payments!$B:$B,"Bonus")) | I23: =IF($A23="","",SUMIFS(Payments!$C:$C,Payments!$A:$A,">="&$A23,Payments!$A:$A,"<"&EDATE($A23,1))) | J23: =IF($A23="","",$I23-$F23) | K23: =IF($A23="","",IF($E$3="Monthly",SUMIFS('Work report'!$F:$F,'Work report'!$A:$A,">="&$A23,'Work report'!$A:$A,"<"&EDATE($A23,1),'Work report'!$B:$B,"<>",'Work report'!$B:$B,"<>1001")/60,SUMIFS('Work report'!$G:$G,'Work report'!$A:$A,">="&$A23,'Work report'!$A:$A,"<"&EDATE($A23,1),'Work report'!$B:$B,"<>",'Work report'!$B:$B,"<>1001")/60)) | L23: =IF($A23="","",IF($E$3="Monthly",SUMIFS('Work report'!$F:$F,'Work report'!$A:$A,">="&$A23,'Work report'!$A:$A,"<"&EDATE($A23,1),'Work report'!$B:$B,1001)/60,SUMIFS('Work report'!$G:$G,'Work report'!$A:$A,">="&$A23,'Work report'!$A:$A,"<"&EDATE($A23,1),'Work report'!$B:$B,1001)/60)) | M23: =IF($A23="","",$K23+$L23-$C23) | N23: =IF($A23="","",$E$4*($K23+$L23)) | O23: =IF($A23="","",$I23-$D23) | P23: =IFERROR($C23/($K23+$L23),"") | Q23: =IF($A23="","",IF($E$3<>"Monthly","",IFERROR($C23-($E$5/$E$4),""))) | R23: =IF($A23="","",SUMIFS('Work report'!$L:$L,'Work report'!$A:$A,">="&$A23,'Work report'!$A:$A,"<"&EDATE($A23,1))) | S23: =IF($A23="","",SUMIFS('Work report'!$M:$M,'Work report'!$A:$A,">="&$A23,'Work report'!$A:$A,"<"&EDATE($A23,1))) | T23: =IF($A23="","",SUMIFS('Missing tasks'!$E:$E,'Missing tasks'!$A:$A,">="&$A23,'Missing tasks'!$A:$A,"<"&EDATE($A23,1))) | U23: =IF($A23="","",SUMIFS('Missing tasks'!$H:$H,'Missing tasks'!$A:$A,">="&$A23,'Missing tasks'!$A:$A,"<"&EDATE($A23,1))) | V23: =IF($A23="","",SUMIFS('Missing tasks'!$J:$J,'Missing tasks'!$I:$I,">="&$A23,'Missing tasks'!$I:$I,"<"&EDATE($A23,1))) | W23: =IF($A23="","",COUNTIFS('Time check for tasks'!$A:$A,">="&$A23,'Time check for tasks'!$A:$A,"<"&EDATE($A23,1),'Time check for tasks'!$K:$K,">0",'Time check for tasks'!$L:$L,"Time check – lower")) | X23: =IF($A23="","",SUMIFS('Time check for tasks'!$K:$K,'Time check for tasks'!$A:$A,">="&$A23,'Time check for tasks'!$A:$A,"<"&EDATE($A23,1),'Time check for tasks'!$K:$K,">0",'Time check for tasks'!$L:$L,"Time check – lower")) | Y23: =IF($A23="","",SUMIFS('Time check for tasks'!$P:$P,'Time check for tasks'!$A:$A,">="&$A23,'Time check for tasks'!$A:$A,"<"&EDATE($A23,1),'Time check for tasks'!$P:$P,">0",'Time check for tasks'!$L:$L,"Time check – lower")) | Z23: =IF($A23="","",COUNTIFS('Time check for tasks'!$A:$A,">="&$A23,'Time check for tasks'!$A:$A,"<"&EDATE($A23,1),'Time check for tasks'!$K:$K,">0",'Time check for tasks'!$L:$L,"Time check – higher")) | AA23: =IF($A23="","",SUMIFS('Time check for tasks'!$K:$K,'Time check for tasks'!$A:$A,">="&$A23,'Time check for tasks'!$A:$A,"<"&EDATE($A23,1),'Time check for tasks'!$K:$K,">0",'Time check for tasks'!$L:$L,"Time check – higher")) | AB23: =IF($A23="","",SUMIFS('Time check for tasks'!$P:$P,'Time check for tasks'!$A:$A,">="&$A23,'Time check for tasks'!$A:$A,"<"&EDATE($A23,1),'Time check for tasks'!$P:$P,">0",'Time check for tasks'!$L:$L,"Time check – higher")) | AH23: =IF(COUNT(AC23:AG23)=0,"",SUM(AC23:AG23)) | AI23: =IF($A23="","",SUMIFS('Work report'!$N:$N,'Work report'!$A:$A,">="&$A23,'Work report'!$A:$A,"<"&EDATE($A23,1))) | AJ23: =IF($A23="","",SUMIFS(Messages!$T:$T,Messages!$A:$A,">="&$A23,Messages!$A:$A,"<"&EDATE($A23,1)))
... A70: =IF(A69="","",IF(EDATE(A69,1)>$B$8,"",EDATE(A69,1))) | B70: =IF($A70="","",COUNTIFS('Work report'!$A:$A,">="&$A70,'Work report'!$A:$A,"<"&EDATE($A70,1),'Work report'!$B:$B,"<>")) | C70: =IF($A70="","",(SUMIFS('Work report'!$I:$I,'Work report'!$A:$A,">="&$A70,'Work report'!$A:$A,"<"&EDATE($A70,1),'Work report'!$B:$B,"<>",'Work report'!$B:$B,"<>1001")+SUMIFS('Work report'!$I:$I,'Work report'!$A:$A,">="&$A70,'Work report'!$A:$A,"<"&EDATE($A70,1),'Work report'!$B:$B,1001,'Work report'!$U:$U,"<>")+SUMIFS('Office time approval'!$M:$M,'Office time approval'!$A:$A,">="&$A70,'Office time approval'!$A:$A,"<"&EDATE($A70,1),'Office time approval'!$L:$L,"Approved")+SUMIFS('Vacation, holiday, illness'!$K:$K,'Vacation, holiday, illness'!$A:$A,">="&$A70,'Vacation, holiday, illness'!$A:$A,"<"&EDATE($A70,1)))/60) | D70: =IF($A70="","",IF($E$3="Hourly",$C70*$E$4,IF($E$3="Monthly",IF($C70>0,$E$5,0),0))) | E70: =IF($A70="","",$D70*$E$8) | F70: =IF($A70="","",D70+E70+((V70+Y70+AB70)/60)*$E$4) | G70: =IF($A70="","",SUMIFS(Payments!$C:$C,Payments!$A:$A,">="&$A70,Payments!$A:$A,"<"&EDATE($A70,1),Payments!$B:$B,"Salary")) | H70: =IF($A70="","",SUMIFS(Payments!$C:$C,Payments!$A:$A,">="&$A70,Payments!$A:$A,"<"&EDATE($A70,1),Payments!$B:$B,"Bonus")) | I70: =IF($A70="","",SUMIFS(Payments!$C:$C,Payments!$A:$A,">="&$A70,Payments!$A:$A,"<"&EDATE($A70,1))) | J70: =IF($A70="","",$I70-$F70) | K70: =IF($A70="","",IF($E$3="Monthly",SUMIFS('Work report'!$F:$F,'Work report'!$A:$A,">="&$A70,'Work report'!$A:$A,"<"&EDATE($A70,1),'Work report'!$B:$B,"<>",'Work report'!$B:$B,"<>1001")/60,SUMIFS('Work report'!$G:$G,'Work report'!$A:$A,">="&$A70,'Work report'!$A:$A,"<"&EDATE($A70,1),'Work report'!$B:$B,"<>",'Work report'!$B:$B,"<>1001")/60)) | L70: =IF($A70="","",IF($E$3="Monthly",SUMIFS('Work report'!$F:$F,'Work report'!$A:$A,">="&$A70,'Work report'!$A:$A,"<"&EDATE($A70,1),'Work report'!$B:$B,1001)/60,SUMIFS('Work report'!$G:$G,'Work report'!$A:$A,">="&$A70,'Work report'!$A:$A,"<"&EDATE($A70,1),'Work report'!$B:$B,1001)/60)) | M70: =IF($A70="","",$K70+$L70-$C70) | N70: =IF($A70="","",$E$4*($K70+$L70)) | O70: =IF($A70="","",$I70-$D70) | P70: =IFERROR($C70/($K70+$L70),"") | Q70: =IF($A70="","",IF($E$3<>"Monthly","",IFERROR($C70-($E$5/$E$4),""))) | R70: =IF($A70="","",SUMIFS('Work report'!$L:$L,'Work report'!$A:$A,">="&$A70,'Work report'!$A:$A,"<"&EDATE($A70,1))) | S70: =IF($A70="","",SUMIFS('Work report'!$M:$M,'Work report'!$A:$A,">="&$A70,'Work report'!$A:$A,"<"&EDATE($A70,1))) | T70: =IF($A70="","",SUMIFS('Missing tasks'!$E:$E,'Missing tasks'!$A:$A,">="&$A70,'Missing tasks'!$A:$A,"<"&EDATE($A70,1))) | U70: =IF($A70="","",SUMIFS('Missing tasks'!$H:$H,'Missing tasks'!$A:$A,">="&$A70,'Missing tasks'!$A:$A,"<"&EDATE($A70,1))) | V70: =IF($A70="","",SUMIFS('Missing tasks'!$J:$J,'Missing tasks'!$I:$I,">="&$A70,'Missing tasks'!$I:$I,"<"&EDATE($A70,1))) | W70: =IF($A70="","",COUNTIFS('Time check for tasks'!$A:$A,">="&$A70,'Time check for tasks'!$A:$A,"<"&EDATE($A70,1),'Time check for tasks'!$K:$K,">0",'Time check for tasks'!$L:$L,"Time check – lower")) | X70: =IF($A70="","",SUMIFS('Time check for tasks'!$K:$K,'Time check for tasks'!$A:$A,">="&$A70,'Time check for tasks'!$A:$A,"<"&EDATE($A70,1),'Time check for tasks'!$K:$K,">0",'Time check for tasks'!$L:$L,"Time check – lower")) | Y70: =IF($A70="","",SUMIFS('Time check for tasks'!$P:$P,'Time check for tasks'!$A:$A,">="&$A70,'Time check for tasks'!$A:$A,"<"&EDATE($A70,1),'Time check for tasks'!$P:$P,">0",'Time check for tasks'!$L:$L,"Time check – lower")) | Z70: =IF($A70="","",COUNTIFS('Time check for tasks'!$A:$A,">="&$A70,'Time check for tasks'!$A:$A,"<"&EDATE($A70,1),'Time check for tasks'!$K:$K,">0",'Time check for tasks'!$L:$L,"Time check – higher")) | AA70: =IF($A70="","",SUMIFS('Time check for tasks'!$K:$K,'Time check for tasks'!$A:$A,">="&$A70,'Time check for tasks'!$A:$A,"<"&EDATE($A70,1),'Time check for tasks'!$K:$K,">0",'Time check for tasks'!$L:$L,"Time check – higher")) | AB70: =IF($A70="","",SUMIFS('Time check for tasks'!$P:$P,'Time check for tasks'!$A:$A,">="&$A70,'Time check for tasks'!$A:$A,"<"&EDATE($A70,1),'Time check for tasks'!$P:$P,">0",'Time check for tasks'!$L:$L,"Time check – higher")) | AH70: =IF(COUNT(AC70:AG70)=0,"",SUM(AC70:AG70)) | AI70: =IF($A70="","",SUMIFS('Work report'!$N:$N,'Work report'!$A:$A,">="&$A70,'Work report'!$A:$A,"<"&EDATE($A70,1))) | AJ70: =IF($A70="","",SUMIFS(Messages!$T:$T,Messages!$A:$A,">="&$A70,Messages!$A:$A,"<"&EDATE($A70,1)))
P71: =IFERROR($C71/($K71+$L71),"") | R71: =IF($A71="","",SUMIFS('Work report'!$L:$L,'Work report'!$A:$A,">="&$A71,'Work report'!$A:$A,"<"&EDATE($A71,1))) | S71: =IF($A71="","",SUMIFS('Work report'!$M:$M,'Work report'!$A:$A,">="&$A71,'Work report'!$A:$A,"<"&EDATE($A71,1))) | T71: =IF($A71="","",SUMIFS('Missing tasks'!$E:$E,'Missing tasks'!$A:$A,">="&$A71,'Missing tasks'!$A:$A,"<"&EDATE($A71,1))) | U71: =IF($A71="","",SUMIFS('Missing tasks'!$H:$H,'Missing tasks'!$A:$A,">="&$A71,'Missing tasks'!$A:$A,"<"&EDATE($A71,1))) | V71: =IF($A71="","",SUMIFS('Missing tasks'!$J:$J,'Missing tasks'!$I:$I,">="&$A71,'Missing tasks'!$I:$I,"<"&EDATE($A71,1))) | W71: =IF($A71="","",COUNTIFS('Time check for tasks'!$A:$A,">="&$A71,'Time check for tasks'!$A:$A,"<"&EDATE($A71,1),'Time check for tasks'!$K:$K,">0",'Time check for tasks'!$L:$L,"Time check – lower")) | X71: =IF($A71="","",SUMIFS('Time check for tasks'!$K:$K,'Time check for tasks'!$A:$A,">="&$A71,'Time check for tasks'!$A:$A,"<"&EDATE($A71,1),'Time check for tasks'!$K:$K,">0",'Time check for tasks'!$L:$L,"Time check – lower")) | Y71: =IF($A71="","",SUMIFS('Time check for tasks'!$P:$P,'Time check for tasks'!$A:$A,">="&$A71,'Time check for tasks'!$A:$A,"<"&EDATE($A71,1),'Time check for tasks'!$P:$P,">0",'Time check for tasks'!$L:$L,"Time check – lower")) | Z71: =IF($A71="","",COUNTIFS('Time check for tasks'!$A:$A,">="&$A71,'Time check for tasks'!$A:$A,"<"&EDATE($A71,1),'Time check for tasks'!$K:$K,">0",'Time check for tasks'!$L:$L,"Time check – higher")) | AA71: =IF($A71="","",SUMIFS('Time check for tasks'!$K:$K,'Time check for tasks'!$A:$A,">="&$A71,'Time check for tasks'!$A:$A,"<"&EDATE($A71,1),'Time check for tasks'!$K:$K,">0",'Time check for tasks'!$L:$L,"Time check – higher")) | AB71: =IF($A71="","",SUMIFS('Time check for tasks'!$P:$P,'Time check for tasks'!$A:$A,">="&$A71,'Time check for tasks'!$A:$A,"<"&EDATE($A71,1),'Time check for tasks'!$P:$P,">0",'Time check for tasks'!$L:$L,"Time check – higher")) | AH71: =IF(COUNT(AC71:AG71)=0,"",SUM(AC71:AG71)) | AJ71: =IF($A71="","",SUMIFS(Messages!$T:$T,Messages!$A:$A,">="&$A71,Messages!$A:$A,"<"&EDATE($A71,1)))
P72: =IFERROR($C72/($K72+$L72),"") | R72: =IF($A72="","",SUMIFS('Work report'!$L:$L,'Work report'!$A:$A,">="&$A72,'Work report'!$A:$A,"<"&EDATE($A72,1))) | S72: =IF($A72="","",SUMIFS('Work report'!$M:$M,'Work report'!$A:$A,">="&$A72,'Work report'!$A:$A,"<"&EDATE($A72,1))) | T72: =IF($A72="","",SUMIFS('Missing tasks'!$E:$E,'Missing tasks'!$A:$A,">="&$A72,'Missing tasks'!$A:$A,"<"&EDATE($A72,1))) | U72: =IF($A72="","",SUMIFS('Missing tasks'!$H:$H,'Missing tasks'!$A:$A,">="&$A72,'Missing tasks'!$A:$A,"<"&EDATE($A72,1))) | V72: =IF($A72="","",SUMIFS('Missing tasks'!$J:$J,'Missing tasks'!$I:$I,">="&$A72,'Missing tasks'!$I:$I,"<"&EDATE($A72,1))) | W72: =IF($A72="","",COUNTIFS('Time check for tasks'!$A:$A,">="&$A72,'Time check for tasks'!$A:$A,"<"&EDATE($A72,1),'Time check for tasks'!$K:$K,">0",'Time check for tasks'!$L:$L,"Time check – lower")) | X72: =IF($A72="","",SUMIFS('Time check for tasks'!$K:$K,'Time check for tasks'!$A:$A,">="&$A72,'Time check for tasks'!$A:$A,"<"&EDATE($A72,1),'Time check for tasks'!$K:$K,">0",'Time check for tasks'!$L:$L,"Time check – lower")) | Y72: =IF($A72="","",SUMIFS('Time check for tasks'!$P:$P,'Time check for tasks'!$A:$A,">="&$A72,'Time check for tasks'!$A:$A,"<"&EDATE($A72,1),'Time check for tasks'!$P:$P,">0",'Time check for tasks'!$L:$L,"Time check – lower")) | Z72: =IF($A72="","",COUNTIFS('Time check for tasks'!$A:$A,">="&$A72,'Time check for tasks'!$A:$A,"<"&EDATE($A72,1),'Time check for tasks'!$K:$K,">0",'Time check for tasks'!$L:$L,"Time check – higher")) | AA72: =IF($A72="","",SUMIFS('Time check for tasks'!$K:$K,'Time check for tasks'!$A:$A,">="&$A72,'Time check for tasks'!$A:$A,"<"&EDATE($A72,1),'Time check for tasks'!$K:$K,">0",'Time check for tasks'!$L:$L,"Time check – higher")) | AB72: =IF($A72="","",SUMIFS('Time check for tasks'!$P:$P,'Time check for tasks'!$A:$A,">="&$A72,'Time check for tasks'!$A:$A,"<"&EDATE($A72,1),'Time check for tasks'!$P:$P,">0",'Time check for tasks'!$L:$L,"Time check – higher")) | AH72: =IF(COUNT(AC72:AG72)=0,"",SUM(AC72:AG72)) | AJ72: =IF($A72="","",SUMIFS(Messages!$T:$T,Messages!$A:$A,">="&$A72,Messages!$A:$A,"<"&EDATE($A72,1)))
A73: TỔNG THEO NĂM (năm chọn ở B6) | P73: =IFERROR($C73/($K73+$L73),"") | Q73: =IF($A73="","",IF($E$3<>"Monthly","",IFERROR($C73-($E$5/$E$4),""))) | R73: =IF($A73="","",SUMIFS('Work report'!$L:$L,'Work report'!$A:$A,">="&$A73,'Work report'!$A:$A,"<"&EDATE($A73,1))) -> 0 | S73: =IF($A73="","",SUMIFS('Work report'!$M:$M,'Work report'!$A:$A,">="&$A73,'Work report'!$A:$A,"<"&EDATE($A73,1))) -> 0 | T73: =IF($A73="","",SUMIFS('Missing tasks'!$E:$E,'Missing tasks'!$A:$A,">="&$A73,'Missing tasks'!$A:$A,"<"&EDATE($A73,1))) -> 0 | U73: =IF($A73="","",SUMIFS('Missing tasks'!$H:$H,'Missing tasks'!$A:$A,">="&$A73,'Missing tasks'!$A:$A,"<"&EDATE($A73,1))) -> 0 | V73: =IF($A73="","",SUMIFS('Missing tasks'!$J:$J,'Missing tasks'!$I:$I,">="&$A73,'Missing tasks'!$I:$I,"<"&EDATE($A73,1))) -> 0 | W73: =IF($A73="","",COUNTIFS('Time check for tasks'!$A:$A,">="&$A73,'Time check for tasks'!$A:$A,"<"&EDATE($A73,1),'Time check for tasks'!$K:$K,">0",'Time check for tasks'!$L:$L,"Time check – lower")) -> 0 | X73: =IF($A73="","",SUMIFS('Time check for tasks'!$K:$K,'Time check for tasks'!$A:$A,">="&$A73,'Time check for tasks'!$A:$A,"<"&EDATE($A73,1),'Time check for tasks'!$K:$K,">0",'Time check for tasks'!$L:$L,"Time check – lower")) -> 0 | Y73: =IF($A73="","",SUMIFS('Time check for tasks'!$P:$P,'Time check for tasks'!$A:$A,">="&$A73,'Time check for tasks'!$A:$A,"<"&EDATE($A73,1),'Time check for tasks'!$P:$P,">0",'Time check for tasks'!$L:$L,"Time check – lower")) -> 0 | Z73: =IF($A73="","",COUNTIFS('Time check for tasks'!$A:$A,">="&$A73,'Time check for tasks'!$A:$A,"<"&EDATE($A73,1),'Time check for tasks'!$K:$K,">0",'Time check for tasks'!$L:$L,"Time check – higher")) -> 0 | AA73: =IF($A73="","",SUMIFS('Time check for tasks'!$K:$K,'Time check for tasks'!$A:$A,">="&$A73,'Time check for tasks'!$A:$A,"<"&EDATE($A73,1),'Time check for tasks'!$K:$K,">0",'Time check for tasks'!$L:$L,"Time check – higher")) -> 0 | AB73: =IF($A73="","",SUMIFS('Time check for tasks'!$P:$P,'Time check for tasks'!$A:$A,">="&$A73,'Time check for tasks'!$A:$A,"<"&EDATE($A73,1),'Time check for tasks'!$P:$P,">0",'Time check for tasks'!$L:$L,"Time check – higher")) -> 0 | AH73: =IF(COUNT(AC73:AG73)=0,"",SUM(AC73:AG73)) | AJ73: =IF($A73="","",SUMIFS(Messages!$T:$T,Messages!$A:$A,">="&$A73,Messages!$A:$A,"<"&EDATE($A73,1))) -> 0
A74: Total hours (year) | B74: =IF($B$6="","",SUMIFS('Work report'!$J:$J,'Work report'!$A:$A,">="&DATE($B$6,1,1),'Work report'!$A:$A,"<"&DATE($B$6+1,1,1))) | P74: =IFERROR($C74/($K74+$L74),"") | Q74: =IF($A74="","",IF($E$3<>"Monthly","",IFERROR($C74-($E$5/$E$4),""))) | R74: =IF($A74="","",SUMIFS('Work report'!$L:$L,'Work report'!$A:$A,">="&$A74,'Work report'!$A:$A,"<"&EDATE($A74,1))) -> 0 | S74: =IF($A74="","",SUMIFS('Work report'!$M:$M,'Work report'!$A:$A,">="&$A74,'Work report'!$A:$A,"<"&EDATE($A74,1))) -> 0 | T74: =IF($A74="","",SUMIFS('Missing tasks'!$E:$E,'Missing tasks'!$A:$A,">="&$A74,'Missing tasks'!$A:$A,"<"&EDATE($A74,1))) -> 0 | U74: =IF($A74="","",SUMIFS('Missing tasks'!$H:$H,'Missing tasks'!$A:$A,">="&$A74,'Missing tasks'!$A:$A,"<"&EDATE($A74,1))) -> 0 | V74: =IF($A74="","",SUMIFS('Missing tasks'!$J:$J,'Missing tasks'!$I:$I,">="&$A74,'Missing tasks'!$I:$I,"<"&EDATE($A74,1))) -> 0 | W74: =IF($A74="","",COUNTIFS('Time check for tasks'!$A:$A,">="&$A74,'Time check for tasks'!$A:$A,"<"&EDATE($A74,1),'Time check for tasks'!$K:$K,">0",'Time check for tasks'!$L:$L,"Time check – lower")) -> 0 | X74: =IF($A74="","",SUMIFS('Time check for tasks'!$K:$K,'Time check for tasks'!$A:$A,">="&$A74,'Time check for tasks'!$A:$A,"<"&EDATE($A74,1),'Time check for tasks'!$K:$K,">0",'Time check for tasks'!$L:$L,"Time check – lower")) -> 0 | Y74: =IF($A74="","",SUMIFS('Time check for tasks'!$P:$P,'Time check for tasks'!$A:$A,">="&$A74,'Time check for tasks'!$A:$A,"<"&EDATE($A74,1),'Time check for tasks'!$P:$P,">0",'Time check for tasks'!$L:$L,"Time check – lower")) -> 0 | Z74: =IF($A74="","",COUNTIFS('Time check for tasks'!$A:$A,">="&$A74,'Time check for tasks'!$A:$A,"<"&EDATE($A74,1),'Time check for tasks'!$K:$K,">0",'Time check for tasks'!$L:$L,"Time check – higher")) -> 0 | AA74: =IF($A74="","",SUMIFS('Time check for tasks'!$K:$K,'Time check for tasks'!$A:$A,">="&$A74,'Time check for tasks'!$A:$A,"<"&EDATE($A74,1),'Time check for tasks'!$K:$K,">0",'Time check for tasks'!$L:$L,"Time check – higher")) -> 0 | AB74: =IF($A74="","",SUMIFS('Time check for tasks'!$P:$P,'Time check for tasks'!$A:$A,">="&$A74,'Time check for tasks'!$A:$A,"<"&EDATE($A74,1),'Time check for tasks'!$P:$P,">0",'Time check for tasks'!$L:$L,"Time check – higher")) -> 0 | AH74: =IF(COUNT(AC74:AG74)=0,"",SUM(AC74:AG74)) | AI74: =IF($B$6="","",SUMIFS($AI$11:$AI$70,$A$11:$A$70,">="&DATE($B$6,1,1),$A$11:$A$70,"<"&DATE($B$6+1,1,1))) | AJ74: =IF($A74="","",SUMIFS(Messages!$T:$T,Messages!$A:$A,">="&$A74,Messages!$A:$A,"<"&EDATE($A74,1))) -> 0
A75: Salary calc (year) | B75: =IF($B$6="","",SUMIFS($D$11:$D$70,$A$11:$A$70,">="&DATE($B$6,1,1),$A$11:$A$70,"<"&DATE($B$6+1,1,1))) | P75: =IFERROR($C75/($K75+$L75),"") | Q75: =IF($A75="","",IF($E$3<>"Monthly","",IFERROR($C75-($E$5/$E$4),""))) | R75: =IF($A75="","",SUMIFS('Work report'!$L:$L,'Work report'!$A:$A,">="&$A75,'Work report'!$A:$A,"<"&EDATE($A75,1))) -> 0 | S75: =IF($A75="","",SUMIFS('Work report'!$M:$M,'Work report'!$A:$A,">="&$A75,'Work report'!$A:$A,"<"&EDATE($A75,1))) -> 0 | T75: =IF($A75="","",SUMIFS('Missing tasks'!$E:$E,'Missing tasks'!$A:$A,">="&$A75,'Missing tasks'!$A:$A,"<"&EDATE($A75,1))) -> 0 | U75: =IF($A75="","",SUMIFS('Missing tasks'!$H:$H,'Missing tasks'!$A:$A,">="&$A75,'Missing tasks'!$A:$A,"<"&EDATE($A75,1))) -> 0 | V75: =IF($A75="","",SUMIFS('Missing tasks'!$J:$J,'Missing tasks'!$I:$I,">="&$A75,'Missing tasks'!$I:$I,"<"&EDATE($A75,1))) -> 0 | W75: =IF($A75="","",COUNTIFS('Time check for tasks'!$A:$A,">="&$A75,'Time check for tasks'!$A:$A,"<"&EDATE($A75,1),'Time check for tasks'!$K:$K,">0",'Time check for tasks'!$L:$L,"Time check – lower")) -> 0 | X75: =IF($A75="","",SUMIFS('Time check for tasks'!$K:$K,'Time check for tasks'!$A:$A,">="&$A75,'Time check for tasks'!$A:$A,"<"&EDATE($A75,1),'Time check for tasks'!$K:$K,">0",'Time check for tasks'!$L:$L,"Time check – lower")) -> 0 | Y75: =IF($A75="","",SUMIFS('Time check for tasks'!$P:$P,'Time check for tasks'!$A:$A,">="&$A75,'Time check for tasks'!$A:$A,"<"&EDATE($A75,1),'Time check for tasks'!$P:$P,">0",'Time check for tasks'!$L:$L,"Time check – lower")) -> 0 | Z75: =IF($A75="","",COUNTIFS('Time check for tasks'!$A:$A,">="&$A75,'Time check for tasks'!$A:$A,"<"&EDATE($A75,1),'Time check for tasks'!$K:$K,">0",'Time check for tasks'!$L:$L,"Time check – higher")) -> 0 | AA75: =IF($A75="","",SUMIFS('Time check for tasks'!$K:$K,'Time check for tasks'!$A:$A,">="&$A75,'Time check for tasks'!$A:$A,"<"&EDATE($A75,1),'Time check for tasks'!$K:$K,">0",'Time check for tasks'!$L:$L,"Time check – higher")) -> 0 | AB75: =IF($A75="","",SUMIFS('Time check for tasks'!$P:$P,'Time check for tasks'!$A:$A,">="&$A75,'Time check for tasks'!$A:$A,"<"&EDATE($A75,1),'Time check for tasks'!$P:$P,">0",'Time check for tasks'!$L:$L,"Time check – higher")) -> 0 | AH75: =IF(COUNT(AC75:AG75)=0,"",SUM(AC75:AG75)) | AJ75: =IF($A75="","",SUMIFS(Messages!$T:$T,Messages!$A:$A,">="&$A75,Messages!$A:$A,"<"&EDATE($A75,1))) -> 0
A76: Bonus calc (year) | B76: =IF($B$6="","",SUMIFS($E$11:$E$70,$A$11:$A$70,">="&DATE($B$6,1,1),$A$11:$A$70,"<"&DATE($B$6+1,1,1))) | P76: =IFERROR($C76/($K76+$L76),"") | Q76: =IF($A76="","",IF($E$3<>"Monthly","",IFERROR($C76-($E$5/$E$4),""))) | R76: =IF($A76="","",SUMIFS('Work report'!$L:$L,'Work report'!$A:$A,">="&$A76,'Work report'!$A:$A,"<"&EDATE($A76,1))) -> 0 | S76: =IF($A76="","",SUMIFS('Work report'!$M:$M,'Work report'!$A:$A,">="&$A76,'Work report'!$A:$A,"<"&EDATE($A76,1))) -> 0 | T76: =IF($A76="","",SUMIFS('Missing tasks'!$E:$E,'Missing tasks'!$A:$A,">="&$A76,'Missing tasks'!$A:$A,"<"&EDATE($A76,1))) -> 0 | U76: =IF($A76="","",SUMIFS('Missing tasks'!$H:$H,'Missing tasks'!$A:$A,">="&$A76,'Missing tasks'!$A:$A,"<"&EDATE($A76,1))) -> 0 | V76: =IF($A76="","",SUMIFS('Missing tasks'!$J:$J,'Missing tasks'!$I:$I,">="&$A76,'Missing tasks'!$I:$I,"<"&EDATE($A76,1))) -> 0 | W76: =IF($A76="","",COUNTIFS('Time check for tasks'!$A:$A,">="&$A76,'Time check for tasks'!$A:$A,"<"&EDATE($A76,1),'Time check for tasks'!$K:$K,">0",'Time check for tasks'!$L:$L,"Time check – lower")) -> 0 | X76: =IF($A76="","",SUMIFS('Time check for tasks'!$K:$K,'Time check for tasks'!$A:$A,">="&$A76,'Time check for tasks'!$A:$A,"<"&EDATE($A76,1),'Time check for tasks'!$K:$K,">0",'Time check for tasks'!$L:$L,"Time check – lower")) -> 0 | Y76: =IF($A76="","",SUMIFS('Time check for tasks'!$P:$P,'Time check for tasks'!$A:$A,">="&$A76,'Time check for tasks'!$A:$A,"<"&EDATE($A76,1),'Time check for tasks'!$P:$P,">0",'Time check for tasks'!$L:$L,"Time check – lower")) -> 0 | Z76: =IF($A76="","",COUNTIFS('Time check for tasks'!$A:$A,">="&$A76,'Time check for tasks'!$A:$A,"<"&EDATE($A76,1),'Time check for tasks'!$K:$K,">0",'Time check for tasks'!$L:$L,"Time check – higher")) -> 0 | AA76: =IF($A76="","",SUMIFS('Time check for tasks'!$K:$K,'Time check for tasks'!$A:$A,">="&$A76,'Time check for tasks'!$A:$A,"<"&EDATE($A76,1),'Time check for tasks'!$K:$K,">0",'Time check for tasks'!$L:$L,"Time check – higher")) -> 0 | AB76: =IF($A76="","",SUMIFS('Time check for tasks'!$P:$P,'Time check for tasks'!$A:$A,">="&$A76,'Time check for tasks'!$A:$A,"<"&EDATE($A76,1),'Time check for tasks'!$P:$P,">0",'Time check for tasks'!$L:$L,"Time check – higher")) -> 0 | AH76: =IF(COUNT(AC76:AG76)=0,"",SUM(AC76:AG76)) | AJ76: =IF($A76="","",SUMIFS(Messages!$T:$T,Messages!$A:$A,">="&$A76,Messages!$A:$A,"<"&EDATE($A76,1))) -> 0
A77: Total calc (year) | B77: =IF($B$6="","",SUMIFS($F$11:$F$70,$A$11:$A$70,">="&DATE($B$6,1,1),$A$11:$A$70,"<"&DATE($B$6+1,1,1))) | P77: =IFERROR($C77/($K77+$L77),"") | Q77: =IF($A77="","",IF($E$3<>"Monthly","",IFERROR($C77-($E$5/$E$4),""))) | R77: =IF($A77="","",SUMIFS('Work report'!$L:$L,'Work report'!$A:$A,">="&$A77,'Work report'!$A:$A,"<"&EDATE($A77,1))) -> 0 | S77: =IF($A77="","",SUMIFS('Work report'!$M:$M,'Work report'!$A:$A,">="&$A77,'Work report'!$A:$A,"<"&EDATE($A77,1))) -> 0 | T77: =IF($A77="","",SUMIFS('Missing tasks'!$E:$E,'Missing tasks'!$A:$A,">="&$A77,'Missing tasks'!$A:$A,"<"&EDATE($A77,1))) -> 0 | U77: =IF($A77="","",SUMIFS('Missing tasks'!$H:$H,'Missing tasks'!$A:$A,">="&$A77,'Missing tasks'!$A:$A,"<"&EDATE($A77,1))) -> 0 | V77: =IF($A77="","",SUMIFS('Missing tasks'!$J:$J,'Missing tasks'!$I:$I,">="&$A77,'Missing tasks'!$I:$I,"<"&EDATE($A77,1))) -> 0 | W77: =IF($A77="","",COUNTIFS('Time check for tasks'!$A:$A,">="&$A77,'Time check for tasks'!$A:$A,"<"&EDATE($A77,1),'Time check for tasks'!$K:$K,">0",'Time check for tasks'!$L:$L,"Time check – lower")) -> 0 | X77: =IF($A77="","",SUMIFS('Time check for tasks'!$K:$K,'Time check for tasks'!$A:$A,">="&$A77,'Time check for tasks'!$A:$A,"<"&EDATE($A77,1),'Time check for tasks'!$K:$K,">0",'Time check for tasks'!$L:$L,"Time check – lower")) -> 0 | Y77: =IF($A77="","",SUMIFS('Time check for tasks'!$P:$P,'Time check for tasks'!$A:$A,">="&$A77,'Time check for tasks'!$A:$A,"<"&EDATE($A77,1),'Time check for tasks'!$P:$P,">0",'Time check for tasks'!$L:$L,"Time check – lower")) -> 0 | Z77: =IF($A77="","",COUNTIFS('Time check for tasks'!$A:$A,">="&$A77,'Time check for tasks'!$A:$A,"<"&EDATE($A77,1),'Time check for tasks'!$K:$K,">0",'Time check for tasks'!$L:$L,"Time check – higher")) -> 0 | AA77: =IF($A77="","",SUMIFS('Time check for tasks'!$K:$K,'Time check for tasks'!$A:$A,">="&$A77,'Time check for tasks'!$A:$A,"<"&EDATE($A77,1),'Time check for tasks'!$K:$K,">0",'Time check for tasks'!$L:$L,"Time check – higher")) -> 0 | AB77: =IF($A77="","",SUMIFS('Time check for tasks'!$P:$P,'Time check for tasks'!$A:$A,">="&$A77,'Time check for tasks'!$A:$A,"<"&EDATE($A77,1),'Time check for tasks'!$P:$P,">0",'Time check for tasks'!$L:$L,"Time check – higher")) -> 0 | AH77: =IF(COUNT(AC77:AG77)=0,"",SUM(AC77:AG77)) | AJ77: =IF($A77="","",SUMIFS(Messages!$T:$T,Messages!$A:$A,">="&$A77,Messages!$A:$A,"<"&EDATE($A77,1))) -> 0
A78: Money received (year) | B78: =IF($B$6="","",SUMIFS($I$11:$I$70,$A$11:$A$70,">="&DATE($B$6,1,1),$A$11:$A$70,"<"&DATE($B$6+1,1,1))) | P78: =IFERROR($C78/($K78+$L78),"") | Q78: =IF($A78="","",IF($E$3<>"Monthly","",IFERROR($C78-($E$5/$E$4),""))) | R78: =IF($A78="","",SUMIFS('Work report'!$L:$L,'Work report'!$A:$A,">="&$A78,'Work report'!$A:$A,"<"&EDATE($A78,1))) -> 0 | S78: =IF($A78="","",SUMIFS('Work report'!$M:$M,'Work report'!$A:$A,">="&$A78,'Work report'!$A:$A,"<"&EDATE($A78,1))) -> 0 | T78: =IF($A78="","",SUMIFS('Missing tasks'!$E:$E,'Missing tasks'!$A:$A,">="&$A78,'Missing tasks'!$A:$A,"<"&EDATE($A78,1))) -> 0 | U78: =IF($A78="","",SUMIFS('Missing tasks'!$H:$H,'Missing tasks'!$A:$A,">="&$A78,'Missing tasks'!$A:$A,"<"&EDATE($A78,1))) -> 0 | V78: =IF($A78="","",SUMIFS('Missing tasks'!$J:$J,'Missing tasks'!$I:$I,">="&$A78,'Missing tasks'!$I:$I,"<"&EDATE($A78,1))) -> 0 | W78: =IF($A78="","",COUNTIFS('Time check for tasks'!$A:$A,">="&$A78,'Time check for tasks'!$A:$A,"<"&EDATE($A78,1),'Time check for tasks'!$K:$K,">0",'Time check for tasks'!$L:$L,"Time check – lower")) -> 0 | X78: =IF($A78="","",SUMIFS('Time check for tasks'!$K:$K,'Time check for tasks'!$A:$A,">="&$A78,'Time check for tasks'!$A:$A,"<"&EDATE($A78,1),'Time check for tasks'!$K:$K,">0",'Time check for tasks'!$L:$L,"Time check – lower")) -> 0 | Y78: =IF($A78="","",SUMIFS('Time check for tasks'!$P:$P,'Time check for tasks'!$A:$A,">="&$A78,'Time check for tasks'!$A:$A,"<"&EDATE($A78,1),'Time check for tasks'!$P:$P,">0",'Time check for tasks'!$L:$L,"Time check – lower")) -> 0 | Z78: =IF($A78="","",COUNTIFS('Time check for tasks'!$A:$A,">="&$A78,'Time check for tasks'!$A:$A,"<"&EDATE($A78,1),'Time check for tasks'!$K:$K,">0",'Time check for tasks'!$L:$L,"Time check – higher")) -> 0 | AA78: =IF($A78="","",SUMIFS('Time check for tasks'!$K:$K,'Time check for tasks'!$A:$A,">="&$A78,'Time check for tasks'!$A:$A,"<"&EDATE($A78,1),'Time check for tasks'!$K:$K,">0",'Time check for tasks'!$L:$L,"Time check – higher")) -> 0 | AB78: =IF($A78="","",SUMIFS('Time check for tasks'!$P:$P,'Time check for tasks'!$A:$A,">="&$A78,'Time check for tasks'!$A:$A,"<"&EDATE($A78,1),'Time check for tasks'!$P:$P,">0",'Time check for tasks'!$L:$L,"Time check – higher")) -> 0 | AH78: =IF(COUNT(AC78:AG78)=0,"",SUM(AC78:AG78)) | AJ78: =IF($A78="","",SUMIFS(Messages!$T:$T,Messages!$A:$A,">="&$A78,Messages!$A:$A,"<"&EDATE($A78,1))) -> 0
A79: Salary paid (year) | B79: =IF($B$6="","",SUMIFS($G$11:$G$70,$A$11:$A$70,">="&DATE($B$6,1,1),$A$11:$A$70,"<"&DATE($B$6+1,1,1))) | P79: =IFERROR($C79/($K79+$L79),"") | Q79: =IF($A79="","",IF($E$3<>"Monthly","",IFERROR($C79-($E$5/$E$4),""))) | R79: =IF($A79="","",SUMIFS('Work report'!$L:$L,'Work report'!$A:$A,">="&$A79,'Work report'!$A:$A,"<"&EDATE($A79,1))) -> 0 | S79: =IF($A79="","",SUMIFS('Work report'!$M:$M,'Work report'!$A:$A,">="&$A79,'Work report'!$A:$A,"<"&EDATE($A79,1))) -> 0 | T79: =IF($A79="","",SUMIFS('Missing tasks'!$E:$E,'Missing tasks'!$A:$A,">="&$A79,'Missing tasks'!$A:$A,"<"&EDATE($A79,1))) -> 0 | U79: =IF($A79="","",SUMIFS('Missing tasks'!$H:$H,'Missing tasks'!$A:$A,">="&$A79,'Missing tasks'!$A:$A,"<"&EDATE($A79,1))) -> 0 | V79: =IF($A79="","",SUMIFS('Missing tasks'!$J:$J,'Missing tasks'!$I:$I,">="&$A79,'Missing tasks'!$I:$I,"<"&EDATE($A79,1))) -> 0 | W79: =IF($A79="","",COUNTIFS('Time check for tasks'!$A:$A,">="&$A79,'Time check for tasks'!$A:$A,"<"&EDATE($A79,1),'Time check for tasks'!$K:$K,">0",'Time check for tasks'!$L:$L,"Time check – lower")) -> 0 | X79: =IF($A79="","",SUMIFS('Time check for tasks'!$K:$K,'Time check for tasks'!$A:$A,">="&$A79,'Time check for tasks'!$A:$A,"<"&EDATE($A79,1),'Time check for tasks'!$K:$K,">0",'Time check for tasks'!$L:$L,"Time check – lower")) -> 0 | Y79: =IF($A79="","",SUMIFS('Time check for tasks'!$P:$P,'Time check for tasks'!$A:$A,">="&$A79,'Time check for tasks'!$A:$A,"<"&EDATE($A79,1),'Time check for tasks'!$P:$P,">0",'Time check for tasks'!$L:$L,"Time check – lower")) -> 0 | Z79: =IF($A79="","",COUNTIFS('Time check for tasks'!$A:$A,">="&$A79,'Time check for tasks'!$A:$A,"<"&EDATE($A79,1),'Time check for tasks'!$K:$K,">0",'Time check for tasks'!$L:$L,"Time check – higher")) -> 0 | AA79: =IF($A79="","",SUMIFS('Time check for tasks'!$K:$K,'Time check for tasks'!$A:$A,">="&$A79,'Time check for tasks'!$A:$A,"<"&EDATE($A79,1),'Time check for tasks'!$K:$K,">0",'Time check for tasks'!$L:$L,"Time check – higher")) -> 0 | AB79: =IF($A79="","",SUMIFS('Time check for tasks'!$P:$P,'Time check for tasks'!$A:$A,">="&$A79,'Time check for tasks'!$A:$A,"<"&EDATE($A79,1),'Time check for tasks'!$P:$P,">0",'Time check for tasks'!$L:$L,"Time check – higher")) -> 0 | AH79: =IF(COUNT(AC79:AG79)=0,"",SUM(AC79:AG79)) | AJ79: =IF($A79="","",SUMIFS(Messages!$T:$T,Messages!$A:$A,">="&$A79,Messages!$A:$A,"<"&EDATE($A79,1))) -> 0
A80: Bonus paid (year) | B80: =IF($B$6="","",SUMIFS($H$11:$H$70,$A$11:$A$70,">="&DATE($B$6,1,1),$A$11:$A$70,"<"&DATE($B$6+1,1,1))) | P80: =IFERROR($C80/($K80+$L80),"") | Q80: =IF($A80="","",IF($E$3<>"Monthly","",IFERROR($C80-($E$5/$E$4),""))) | R80: =IF($A80="","",SUMIFS('Work report'!$L:$L,'Work report'!$A:$A,">="&$A80,'Work report'!$A:$A,"<"&EDATE($A80,1))) -> 0 | S80: =IF($A80="","",SUMIFS('Work report'!$M:$M,'Work report'!$A:$A,">="&$A80,'Work report'!$A:$A,"<"&EDATE($A80,1))) -> 0 | T80: =IF($A80="","",SUMIFS('Missing tasks'!$E:$E,'Missing tasks'!$A:$A,">="&$A80,'Missing tasks'!$A:$A,"<"&EDATE($A80,1))) -> 0 | U80: =IF($A80="","",SUMIFS('Missing tasks'!$H:$H,'Missing tasks'!$A:$A,">="&$A80,'Missing tasks'!$A:$A,"<"&EDATE($A80,1))) -> 0 | V80: =IF($A80="","",SUMIFS('Missing tasks'!$J:$J,'Missing tasks'!$I:$I,">="&$A80,'Missing tasks'!$I:$I,"<"&EDATE($A80,1))) -> 0 | W80: =IF($A80="","",COUNTIFS('Time check for tasks'!$A:$A,">="&$A80,'Time check for tasks'!$A:$A,"<"&EDATE($A80,1),'Time check for tasks'!$K:$K,">0",'Time check for tasks'!$L:$L,"Time check – lower")) -> 0 | X80: =IF($A80="","",SUMIFS('Time check for tasks'!$K:$K,'Time check for tasks'!$A:$A,">="&$A80,'Time check for tasks'!$A:$A,"<"&EDATE($A80,1),'Time check for tasks'!$K:$K,">0",'Time check for tasks'!$L:$L,"Time check – lower")) -> 0 | Y80: =IF($A80="","",SUMIFS('Time check for tasks'!$P:$P,'Time check for tasks'!$A:$A,">="&$A80,'Time check for tasks'!$A:$A,"<"&EDATE($A80,1),'Time check for tasks'!$P:$P,">0",'Time check for tasks'!$L:$L,"Time check – lower")) -> 0 | Z80: =IF($A80="","",COUNTIFS('Time check for tasks'!$A:$A,">="&$A80,'Time check for tasks'!$A:$A,"<"&EDATE($A80,1),'Time check for tasks'!$K:$K,">0",'Time check for tasks'!$L:$L,"Time check – higher")) -> 0 | AA80: =IF($A80="","",SUMIFS('Time check for tasks'!$K:$K,'Time check for tasks'!$A:$A,">="&$A80,'Time check for tasks'!$A:$A,"<"&EDATE($A80,1),'Time check for tasks'!$K:$K,">0",'Time check for tasks'!$L:$L,"Time check – higher")) -> 0 | AB80: =IF($A80="","",SUMIFS('Time check for tasks'!$P:$P,'Time check for tasks'!$A:$A,">="&$A80,'Time check for tasks'!$A:$A,"<"&EDATE($A80,1),'Time check for tasks'!$P:$P,">0",'Time check for tasks'!$L:$L,"Time check – higher")) -> 0 | AH80: =IF(COUNT(AC80:AG80)=0,"",SUM(AC80:AG80)) | AJ80: =IF($A80="","",SUMIFS(Messages!$T:$T,Messages!$A:$A,">="&$A80,Messages!$A:$A,"<"&EDATE($A80,1))) -> 0
P81: =IFERROR($C81/($K81+$L81),"") | R81: =IF($A81="","",SUMIFS('Work report'!$L:$L,'Work report'!$A:$A,">="&$A81,'Work report'!$A:$A,"<"&EDATE($A81,1))) | S81: =IF($A81="","",SUMIFS('Work report'!$M:$M,'Work report'!$A:$A,">="&$A81,'Work report'!$A:$A,"<"&EDATE($A81,1))) | T81: =IF($A81="","",SUMIFS('Missing tasks'!$E:$E,'Missing tasks'!$A:$A,">="&$A81,'Missing tasks'!$A:$A,"<"&EDATE($A81,1))) | U81: =IF($A81="","",SUMIFS('Missing tasks'!$H:$H,'Missing tasks'!$A:$A,">="&$A81,'Missing tasks'!$A:$A,"<"&EDATE($A81,1))) | V81: =IF($A81="","",SUMIFS('Missing tasks'!$J:$J,'Missing tasks'!$I:$I,">="&$A81,'Missing tasks'!$I:$I,"<"&EDATE($A81,1))) | W81: =IF($A81="","",COUNTIFS('Time check for tasks'!$A:$A,">="&$A81,'Time check for tasks'!$A:$A,"<"&EDATE($A81,1),'Time check for tasks'!$K:$K,">0",'Time check for tasks'!$L:$L,"Time check – lower")) | X81: =IF($A81="","",SUMIFS('Time check for tasks'!$K:$K,'Time check for tasks'!$A:$A,">="&$A81,'Time check for tasks'!$A:$A,"<"&EDATE($A81,1),'Time check for tasks'!$K:$K,">0",'Time check for tasks'!$L:$L,"Time check – lower")) | Y81: =IF($A81="","",SUMIFS('Time check for tasks'!$P:$P,'Time check for tasks'!$A:$A,">="&$A81,'Time check for tasks'!$A:$A,"<"&EDATE($A81,1),'Time check for tasks'!$P:$P,">0",'Time check for tasks'!$L:$L,"Time check – lower")) | Z81: =IF($A81="","",COUNTIFS('Time check for tasks'!$A:$A,">="&$A81,'Time check for tasks'!$A:$A,"<"&EDATE($A81,1),'Time check for tasks'!$K:$K,">0",'Time check for tasks'!$L:$L,"Time check – higher")) | AA81: =IF($A81="","",SUMIFS('Time check for tasks'!$K:$K,'Time check for tasks'!$A:$A,">="&$A81,'Time check for tasks'!$A:$A,"<"&EDATE($A81,1),'Time check for tasks'!$K:$K,">0",'Time check for tasks'!$L:$L,"Time check – higher")) | AB81: =IF($A81="","",SUMIFS('Time check for tasks'!$P:$P,'Time check for tasks'!$A:$A,">="&$A81,'Time check for tasks'!$A:$A,"<"&EDATE($A81,1),'Time check for tasks'!$P:$P,">0",'Time check for tasks'!$L:$L,"Time check – higher")) | AH81: =IF(COUNT(AC81:AG81)=0,"",SUM(AC81:AG81)) | AJ81: =IF($A81="","",SUMIFS(Messages!$T:$T,Messages!$A:$A,">="&$A81,Messages!$A:$A,"<"&EDATE($A81,1)))
A82: TỔNG TỪ LÚC BẮT ĐẦU | P82: =IFERROR($C82/($K82+$L82),"") | Q82: =IF($A82="","",IF($E$3<>"Monthly","",IFERROR($C82-($E$5/$E$4),""))) | R82: =IF($A82="","",SUMIFS('Work report'!$L:$L,'Work report'!$A:$A,">="&$A82,'Work report'!$A:$A,"<"&EDATE($A82,1))) -> 0 | S82: =IF($A82="","",SUMIFS('Work report'!$M:$M,'Work report'!$A:$A,">="&$A82,'Work report'!$A:$A,"<"&EDATE($A82,1))) -> 0 | T82: =IF($A82="","",SUMIFS('Missing tasks'!$E:$E,'Missing tasks'!$A:$A,">="&$A82,'Missing tasks'!$A:$A,"<"&EDATE($A82,1))) -> 0 | U82: =IF($A82="","",SUMIFS('Missing tasks'!$H:$H,'Missing tasks'!$A:$A,">="&$A82,'Missing tasks'!$A:$A,"<"&EDATE($A82,1))) -> 0 | V82: =IF($A82="","",SUMIFS('Missing tasks'!$J:$J,'Missing tasks'!$I:$I,">="&$A82,'Missing tasks'!$I:$I,"<"&EDATE($A82,1))) -> 0 | W82: =IF($A82="","",COUNTIFS('Time check for tasks'!$A:$A,">="&$A82,'Time check for tasks'!$A:$A,"<"&EDATE($A82,1),'Time check for tasks'!$K:$K,">0",'Time check for tasks'!$L:$L,"Time check – lower")) -> 0 | X82: =IF($A82="","",SUMIFS('Time check for tasks'!$K:$K,'Time check for tasks'!$A:$A,">="&$A82,'Time check for tasks'!$A:$A,"<"&EDATE($A82,1),'Time check for tasks'!$K:$K,">0",'Time check for tasks'!$L:$L,"Time check – lower")) -> 0 | Y82: =IF($A82="","",SUMIFS('Time check for tasks'!$P:$P,'Time check for tasks'!$A:$A,">="&$A82,'Time check for tasks'!$A:$A,"<"&EDATE($A82,1),'Time check for tasks'!$P:$P,">0",'Time check for tasks'!$L:$L,"Time check – lower")) -> 0 | Z82: =IF($A82="","",COUNTIFS('Time check for tasks'!$A:$A,">="&$A82,'Time check for tasks'!$A:$A,"<"&EDATE($A82,1),'Time check for tasks'!$K:$K,">0",'Time check for tasks'!$L:$L,"Time check – higher")) -> 0 | AA82: =IF($A82="","",SUMIFS('Time check for tasks'!$K:$K,'Time check for tasks'!$A:$A,">="&$A82,'Time check for tasks'!$A:$A,"<"&EDATE($A82,1),'Time check for tasks'!$K:$K,">0",'Time check for tasks'!$L:$L,"Time check – higher")) -> 0 | AB82: =IF($A82="","",SUMIFS('Time check for tasks'!$P:$P,'Time check for tasks'!$A:$A,">="&$A82,'Time check for tasks'!$A:$A,"<"&EDATE($A82,1),'Time check for tasks'!$P:$P,">0",'Time check for tasks'!$L:$L,"Time check – higher")) -> 0 | AH82: =IF(COUNT(AC82:AG82)=0,"",SUM(AC82:AG82)) | AJ82: =IF($A82="","",SUMIFS(Messages!$T:$T,Messages!$A:$A,">="&$A82,Messages!$A:$A,"<"&EDATE($A82,1))) -> 0
A83: Total hours (all) | B83: =SUM($C$11:$C$70) -> 0 | P83: =IFERROR($C83/($K83+$L83),"") | Q83: =IF($A83="","",IF($E$3<>"Monthly","",IFERROR($C83-($E$5/$E$4),""))) | R83: =IF($A83="","",SUMIFS('Work report'!$L:$L,'Work report'!$A:$A,">="&$A83,'Work report'!$A:$A,"<"&EDATE($A83,1))) -> 0 | S83: =IF($A83="","",SUMIFS('Work report'!$M:$M,'Work report'!$A:$A,">="&$A83,'Work report'!$A:$A,"<"&EDATE($A83,1))) -> 0 | T83: =IF($A83="","",SUMIFS('Missing tasks'!$E:$E,'Missing tasks'!$A:$A,">="&$A83,'Missing tasks'!$A:$A,"<"&EDATE($A83,1))) -> 0 | U83: =IF($A83="","",SUMIFS('Missing tasks'!$H:$H,'Missing tasks'!$A:$A,">="&$A83,'Missing tasks'!$A:$A,"<"&EDATE($A83,1))) -> 0 | V83: =IF($A83="","",SUMIFS('Missing tasks'!$J:$J,'Missing tasks'!$I:$I,">="&$A83,'Missing tasks'!$I:$I,"<"&EDATE($A83,1))) -> 0 | W83: =IF($A83="","",COUNTIFS('Time check for tasks'!$A:$A,">="&$A83,'Time check for tasks'!$A:$A,"<"&EDATE($A83,1),'Time check for tasks'!$K:$K,">0",'Time check for tasks'!$L:$L,"Time check – lower")) -> 0 | X83: =IF($A83="","",SUMIFS('Time check for tasks'!$K:$K,'Time check for tasks'!$A:$A,">="&$A83,'Time check for tasks'!$A:$A,"<"&EDATE($A83,1),'Time check for tasks'!$K:$K,">0",'Time check for tasks'!$L:$L,"Time check – lower")) -> 0 | Y83: =IF($A83="","",SUMIFS('Time check for tasks'!$P:$P,'Time check for tasks'!$A:$A,">="&$A83,'Time check for tasks'!$A:$A,"<"&EDATE($A83,1),'Time check for tasks'!$P:$P,">0",'Time check for tasks'!$L:$L,"Time check – lower")) -> 0 | Z83: =IF($A83="","",COUNTIFS('Time check for tasks'!$A:$A,">="&$A83,'Time check for tasks'!$A:$A,"<"&EDATE($A83,1),'Time check for tasks'!$K:$K,">0",'Time check for tasks'!$L:$L,"Time check – higher")) -> 0 | AA83: =IF($A83="","",SUMIFS('Time check for tasks'!$K:$K,'Time check for tasks'!$A:$A,">="&$A83,'Time check for tasks'!$A:$A,"<"&EDATE($A83,1),'Time check for tasks'!$K:$K,">0",'Time check for tasks'!$L:$L,"Time check – higher")) -> 0 | AB83: =IF($A83="","",SUMIFS('Time check for tasks'!$P:$P,'Time check for tasks'!$A:$A,">="&$A83,'Time check for tasks'!$A:$A,"<"&EDATE($A83,1),'Time check for tasks'!$P:$P,">0",'Time check for tasks'!$L:$L,"Time check – higher")) -> 0 | AH83: =IF(COUNT(AC83:AG83)=0,"",SUM(AC83:AG83)) | AI83: =SUM($AI$11:$AI$70) -> 0 | AJ83: =IF($A83="","",SUMIFS(Messages!$T:$T,Messages!$A:$A,">="&$A83,Messages!$A:$A,"<"&EDATE($A83,1))) -> 0
A84: Salary calc (all) | B84: =SUM($D$11:$D$70) -> 0 | P84: =IFERROR($C84/($K84+$L84),"") | Q84: =IF($A84="","",IF($E$3<>"Monthly","",IFERROR($C84-($E$5/$E$4),""))) | R84: =IF($A84="","",SUMIFS('Work report'!$L:$L,'Work report'!$A:$A,">="&$A84,'Work report'!$A:$A,"<"&EDATE($A84,1))) -> 0 | S84: =IF($A84="","",SUMIFS('Work report'!$M:$M,'Work report'!$A:$A,">="&$A84,'Work report'!$A:$A,"<"&EDATE($A84,1))) -> 0 | T84: =IF($A84="","",SUMIFS('Missing tasks'!$E:$E,'Missing tasks'!$A:$A,">="&$A84,'Missing tasks'!$A:$A,"<"&EDATE($A84,1))) -> 0 | U84: =IF($A84="","",SUMIFS('Missing tasks'!$H:$H,'Missing tasks'!$A:$A,">="&$A84,'Missing tasks'!$A:$A,"<"&EDATE($A84,1))) -> 0 | V84: =IF($A84="","",SUMIFS('Missing tasks'!$J:$J,'Missing tasks'!$I:$I,">="&$A84,'Missing tasks'!$I:$I,"<"&EDATE($A84,1))) -> 0 | W84: =IF($A84="","",COUNTIFS('Time check for tasks'!$A:$A,">="&$A84,'Time check for tasks'!$A:$A,"<"&EDATE($A84,1),'Time check for tasks'!$K:$K,">0",'Time check for tasks'!$L:$L,"Time check – lower")) -> 0 | X84: =IF($A84="","",SUMIFS('Time check for tasks'!$K:$K,'Time check for tasks'!$A:$A,">="&$A84,'Time check for tasks'!$A:$A,"<"&EDATE($A84,1),'Time check for tasks'!$K:$K,">0",'Time check for tasks'!$L:$L,"Time check – lower")) -> 0 | Y84: =IF($A84="","",SUMIFS('Time check for tasks'!$P:$P,'Time check for tasks'!$A:$A,">="&$A84,'Time check for tasks'!$A:$A,"<"&EDATE($A84,1),'Time check for tasks'!$P:$P,">0",'Time check for tasks'!$L:$L,"Time check – lower")) -> 0 | Z84: =IF($A84="","",COUNTIFS('Time check for tasks'!$A:$A,">="&$A84,'Time check for tasks'!$A:$A,"<"&EDATE($A84,1),'Time check for tasks'!$K:$K,">0",'Time check for tasks'!$L:$L,"Time check – higher")) -> 0 | AA84: =IF($A84="","",SUMIFS('Time check for tasks'!$K:$K,'Time check for tasks'!$A:$A,">="&$A84,'Time check for tasks'!$A:$A,"<"&EDATE($A84,1),'Time check for tasks'!$K:$K,">0",'Time check for tasks'!$L:$L,"Time check – higher")) -> 0 | AB84: =IF($A84="","",SUMIFS('Time check for tasks'!$P:$P,'Time check for tasks'!$A:$A,">="&$A84,'Time check for tasks'!$A:$A,"<"&EDATE($A84,1),'Time check for tasks'!$P:$P,">0",'Time check for tasks'!$L:$L,"Time check – higher")) -> 0 | AH84: =IF(COUNT(AC84:AG84)=0,"",SUM(AC84:AG84)) | AJ84: =IF($A84="","",SUMIFS(Messages!$T:$T,Messages!$A:$A,">="&$A84,Messages!$A:$A,"<"&EDATE($A84,1))) -> 0
A85: Bonus calc (all) | B85: =SUM($E$11:$E$70) -> 0 | P85: =IFERROR($C85/($K85+$L85),"") | Q85: =IF($A85="","",IF($E$3<>"Monthly","",IFERROR($C85-($E$5/$E$4),""))) | R85: =IF($A85="","",SUMIFS('Work report'!$L:$L,'Work report'!$A:$A,">="&$A85,'Work report'!$A:$A,"<"&EDATE($A85,1))) -> 0 | S85: =IF($A85="","",SUMIFS('Work report'!$M:$M,'Work report'!$A:$A,">="&$A85,'Work report'!$A:$A,"<"&EDATE($A85,1))) -> 0 | T85: =IF($A85="","",SUMIFS('Missing tasks'!$E:$E,'Missing tasks'!$A:$A,">="&$A85,'Missing tasks'!$A:$A,"<"&EDATE($A85,1))) -> 0 | U85: =IF($A85="","",SUMIFS('Missing tasks'!$H:$H,'Missing tasks'!$A:$A,">="&$A85,'Missing tasks'!$A:$A,"<"&EDATE($A85,1))) -> 0 | V85: =IF($A85="","",SUMIFS('Missing tasks'!$J:$J,'Missing tasks'!$I:$I,">="&$A85,'Missing tasks'!$I:$I,"<"&EDATE($A85,1))) -> 0 | W85: =IF($A85="","",COUNTIFS('Time check for tasks'!$A:$A,">="&$A85,'Time check for tasks'!$A:$A,"<"&EDATE($A85,1),'Time check for tasks'!$K:$K,">0",'Time check for tasks'!$L:$L,"Time check – lower")) -> 0 | X85: =IF($A85="","",SUMIFS('Time check for tasks'!$K:$K,'Time check for tasks'!$A:$A,">="&$A85,'Time check for tasks'!$A:$A,"<"&EDATE($A85,1),'Time check for tasks'!$K:$K,">0",'Time check for tasks'!$L:$L,"Time check – lower")) -> 0 | Y85: =IF($A85="","",SUMIFS('Time check for tasks'!$P:$P,'Time check for tasks'!$A:$A,">="&$A85,'Time check for tasks'!$A:$A,"<"&EDATE($A85,1),'Time check for tasks'!$P:$P,">0",'Time check for tasks'!$L:$L,"Time check – lower")) -> 0 | Z85: =IF($A85="","",COUNTIFS('Time check for tasks'!$A:$A,">="&$A85,'Time check for tasks'!$A:$A,"<"&EDATE($A85,1),'Time check for tasks'!$K:$K,">0",'Time check for tasks'!$L:$L,"Time check – higher")) -> 0 | AA85: =IF($A85="","",SUMIFS('Time check for tasks'!$K:$K,'Time check for tasks'!$A:$A,">="&$A85,'Time check for tasks'!$A:$A,"<"&EDATE($A85,1),'Time check for tasks'!$K:$K,">0",'Time check for tasks'!$L:$L,"Time check – higher")) -> 0 | AB85: =IF($A85="","",SUMIFS('Time check for tasks'!$P:$P,'Time check for tasks'!$A:$A,">="&$A85,'Time check for tasks'!$A:$A,"<"&EDATE($A85,1),'Time check for tasks'!$P:$P,">0",'Time check for tasks'!$L:$L,"Time check – higher")) -> 0 | AH85: =IF(COUNT(AC85:AG85)=0,"",SUM(AC85:AG85)) | AJ85: =IF($A85="","",SUMIFS(Messages!$T:$T,Messages!$A:$A,">="&$A85,Messages!$A:$A,"<"&EDATE($A85,1))) -> 0
A86: Total calc (all) | B86: =SUM($F$11:$F$70) -> 0 | P86: =IFERROR($C86/($K86+$L86),"") | Q86: =IF($A86="","",IF($E$3<>"Monthly","",IFERROR($C86-($E$5/$E$4),""))) | R86: =IF($A86="","",SUMIFS('Work report'!$L:$L,'Work report'!$A:$A,">="&$A86,'Work report'!$A:$A,"<"&EDATE($A86,1))) -> 0 | S86: =IF($A86="","",SUMIFS('Work report'!$M:$M,'Work report'!$A:$A,">="&$A86,'Work report'!$A:$A,"<"&EDATE($A86,1))) -> 0 | T86: =IF($A86="","",SUMIFS('Missing tasks'!$E:$E,'Missing tasks'!$A:$A,">="&$A86,'Missing tasks'!$A:$A,"<"&EDATE($A86,1))) -> 0 | U86: =IF($A86="","",SUMIFS('Missing tasks'!$H:$H,'Missing tasks'!$A:$A,">="&$A86,'Missing tasks'!$A:$A,"<"&EDATE($A86,1))) -> 0 | V86: =IF($A86="","",SUMIFS('Missing tasks'!$J:$J,'Missing tasks'!$I:$I,">="&$A86,'Missing tasks'!$I:$I,"<"&EDATE($A86,1))) -> 0 | W86: =IF($A86="","",COUNTIFS('Time check for tasks'!$A:$A,">="&$A86,'Time check for tasks'!$A:$A,"<"&EDATE($A86,1),'Time check for tasks'!$K:$K,">0",'Time check for tasks'!$L:$L,"Time check – lower")) -> 0 | X86: =IF($A86="","",SUMIFS('Time check for tasks'!$K:$K,'Time check for tasks'!$A:$A,">="&$A86,'Time check for tasks'!$A:$A,"<"&EDATE($A86,1),'Time check for tasks'!$K:$K,">0",'Time check for tasks'!$L:$L,"Time check – lower")) -> 0 | Y86: =IF($A86="","",SUMIFS('Time check for tasks'!$P:$P,'Time check for tasks'!$A:$A,">="&$A86,'Time check for tasks'!$A:$A,"<"&EDATE($A86,1),'Time check for tasks'!$P:$P,">0",'Time check for tasks'!$L:$L,"Time check – lower")) -> 0 | Z86: =IF($A86="","",COUNTIFS('Time check for tasks'!$A:$A,">="&$A86,'Time check for tasks'!$A:$A,"<"&EDATE($A86,1),'Time check for tasks'!$K:$K,">0",'Time check for tasks'!$L:$L,"Time check – higher")) -> 0 | AA86: =IF($A86="","",SUMIFS('Time check for tasks'!$K:$K,'Time check for tasks'!$A:$A,">="&$A86,'Time check for tasks'!$A:$A,"<"&EDATE($A86,1),'Time check for tasks'!$K:$K,">0",'Time check for tasks'!$L:$L,"Time check – higher")) -> 0 | AB86: =IF($A86="","",SUMIFS('Time check for tasks'!$P:$P,'Time check for tasks'!$A:$A,">="&$A86,'Time check for tasks'!$A:$A,"<"&EDATE($A86,1),'Time check for tasks'!$P:$P,">0",'Time check for tasks'!$L:$L,"Time check – higher")) -> 0 | AH86: =IF(COUNT(AC86:AG86)=0,"",SUM(AC86:AG86)) | AJ86: =IF($A86="","",SUMIFS(Messages!$T:$T,Messages!$A:$A,">="&$A86,Messages!$A:$A,"<"&EDATE($A86,1))) -> 0
A87: Money received (all) | B87: =SUM($I$11:$I$70) -> 0 | P87: =IFERROR($C87/($K87+$L87),"") | Q87: =IF($A87="","",IF($E$3<>"Monthly","",IFERROR($C87-($E$5/$E$4),""))) | R87: =IF($A87="","",SUMIFS('Work report'!$L:$L,'Work report'!$A:$A,">="&$A87,'Work report'!$A:$A,"<"&EDATE($A87,1))) -> 0 | S87: =IF($A87="","",SUMIFS('Work report'!$M:$M,'Work report'!$A:$A,">="&$A87,'Work report'!$A:$A,"<"&EDATE($A87,1))) -> 0 | T87: =IF($A87="","",SUMIFS('Missing tasks'!$E:$E,'Missing tasks'!$A:$A,">="&$A87,'Missing tasks'!$A:$A,"<"&EDATE($A87,1))) -> 0 | U87: =IF($A87="","",SUMIFS('Missing tasks'!$H:$H,'Missing tasks'!$A:$A,">="&$A87,'Missing tasks'!$A:$A,"<"&EDATE($A87,1))) -> 0 | V87: =IF($A87="","",SUMIFS('Missing tasks'!$J:$J,'Missing tasks'!$I:$I,">="&$A87,'Missing tasks'!$I:$I,"<"&EDATE($A87,1))) -> 0 | W87: =IF($A87="","",COUNTIFS('Time check for tasks'!$A:$A,">="&$A87,'Time check for tasks'!$A:$A,"<"&EDATE($A87,1),'Time check for tasks'!$K:$K,">0",'Time check for tasks'!$L:$L,"Time check – lower")) -> 0 | X87: =IF($A87="","",SUMIFS('Time check for tasks'!$K:$K,'Time check for tasks'!$A:$A,">="&$A87,'Time check for tasks'!$A:$A,"<"&EDATE($A87,1),'Time check for tasks'!$K:$K,">0",'Time check for tasks'!$L:$L,"Time check – lower")) -> 0 | Y87: =IF($A87="","",SUMIFS('Time check for tasks'!$P:$P,'Time check for tasks'!$A:$A,">="&$A87,'Time check for tasks'!$A:$A,"<"&EDATE($A87,1),'Time check for tasks'!$P:$P,">0",'Time check for tasks'!$L:$L,"Time check – lower")) -> 0 | Z87: =IF($A87="","",COUNTIFS('Time check for tasks'!$A:$A,">="&$A87,'Time check for tasks'!$A:$A,"<"&EDATE($A87,1),'Time check for tasks'!$K:$K,">0",'Time check for tasks'!$L:$L,"Time check – higher")) -> 0 | AA87: =IF($A87="","",SUMIFS('Time check for tasks'!$K:$K,'Time check for tasks'!$A:$A,">="&$A87,'Time check for tasks'!$A:$A,"<"&EDATE($A87,1),'Time check for tasks'!$K:$K,">0",'Time check for tasks'!$L:$L,"Time check – higher")) -> 0 | AB87: =IF($A87="","",SUMIFS('Time check for tasks'!$P:$P,'Time check for tasks'!$A:$A,">="&$A87,'Time check for tasks'!$A:$A,"<"&EDATE($A87,1),'Time check for tasks'!$P:$P,">0",'Time check for tasks'!$L:$L,"Time check – higher")) -> 0 | AH87: =IF(COUNT(AC87:AG87)=0,"",SUM(AC87:AG87)) | AJ87: =IF($A87="","",SUMIFS(Messages!$T:$T,Messages!$A:$A,">="&$A87,Messages!$A:$A,"<"&EDATE($A87,1))) -> 0
A88: Salary paid (all) | B88: =SUM($G$11:$G$70) -> 0 | P88: =IFERROR($C88/($K88+$L88),"") | Q88: =IF($A88="","",IF($E$3<>"Monthly","",IFERROR($C88-($E$5/$E$4),""))) | R88: =IF($A88="","",SUMIFS('Work report'!$L:$L,'Work report'!$A:$A,">="&$A88,'Work report'!$A:$A,"<"&EDATE($A88,1))) -> 0 | S88: =IF($A88="","",SUMIFS('Work report'!$M:$M,'Work report'!$A:$A,">="&$A88,'Work report'!$A:$A,"<"&EDATE($A88,1))) -> 0 | T88: =IF($A88="","",SUMIFS('Missing tasks'!$E:$E,'Missing tasks'!$A:$A,">="&$A88,'Missing tasks'!$A:$A,"<"&EDATE($A88,1))) -> 0 | U88: =IF($A88="","",SUMIFS('Missing tasks'!$H:$H,'Missing tasks'!$A:$A,">="&$A88,'Missing tasks'!$A:$A,"<"&EDATE($A88,1))) -> 0 | V88: =IF($A88="","",SUMIFS('Missing tasks'!$J:$J,'Missing tasks'!$I:$I,">="&$A88,'Missing tasks'!$I:$I,"<"&EDATE($A88,1))) -> 0 | W88: =IF($A88="","",COUNTIFS('Time check for tasks'!$A:$A,">="&$A88,'Time check for tasks'!$A:$A,"<"&EDATE($A88,1),'Time check for tasks'!$K:$K,">0",'Time check for tasks'!$L:$L,"Time check – lower")) -> 0 | X88: =IF($A88="","",SUMIFS('Time check for tasks'!$K:$K,'Time check for tasks'!$A:$A,">="&$A88,'Time check for tasks'!$A:$A,"<"&EDATE($A88,1),'Time check for tasks'!$K:$K,">0",'Time check for tasks'!$L:$L,"Time check – lower")) -> 0 | Y88: =IF($A88="","",SUMIFS('Time check for tasks'!$P:$P,'Time check for tasks'!$A:$A,">="&$A88,'Time check for tasks'!$A:$A,"<"&EDATE($A88,1),'Time check for tasks'!$P:$P,">0",'Time check for tasks'!$L:$L,"Time check – lower")) -> 0 | Z88: =IF($A88="","",COUNTIFS('Time check for tasks'!$A:$A,">="&$A88,'Time check for tasks'!$A:$A,"<"&EDATE($A88,1),'Time check for tasks'!$K:$K,">0",'Time check for tasks'!$L:$L,"Time check – higher")) -> 0 | AA88: =IF($A88="","",SUMIFS('Time check for tasks'!$K:$K,'Time check for tasks'!$A:$A,">="&$A88,'Time check for tasks'!$A:$A,"<"&EDATE($A88,1),'Time check for tasks'!$K:$K,">0",'Time check for tasks'!$L:$L,"Time check – higher")) -> 0 | AB88: =IF($A88="","",SUMIFS('Time check for tasks'!$P:$P,'Time check for tasks'!$A:$A,">="&$A88,'Time check for tasks'!$A:$A,"<"&EDATE($A88,1),'Time check for tasks'!$P:$P,">0",'Time check for tasks'!$L:$L,"Time check – higher")) -> 0 | AH88: =IF(COUNT(AC88:AG88)=0,"",SUM(AC88:AG88)) | AJ88: =IF($A88="","",SUMIFS(Messages!$T:$T,Messages!$A:$A,">="&$A88,Messages!$A:$A,"<"&EDATE($A88,1))) -> 0
